Workbook

Sheet 使用方法&新聞
A1: 此表單使用方法 | C1: 我會從紅綠篩選頁面內挑自己有興趣的股票進模擬盤跑 而實際真實買賣會公告在"買賣通知line群"並填寫進"持股"頁面 | J1: 資料去這邊抓
C2: 初步篩選出標的後 還需要去查各股相關新聞 看是否利空利多 常有突然被檢調 或是倒貨 欠賬的公司 然後剔除 | J2: 每月期貨結算日 (每月第三個禮拜三) | K2: https://www.taifex.com.tw/file/taifex/CHINESE/4/2026Calendar.pdf
C3: 模擬操作會同步貼到 "模擬盤"並每日更新<我寫入只代表我關注 不代表我一定買進!!> | J3: 外資未平倉口數 | K3: https://stock.wearn.com/taifexphoto.asp
C4: 請其他使用者自行開立自己的google sheet 自己記錄自己的操作!!!! 不要寫在這邊讓我看到!! | J4: 外資未平倉口數2 | K4: https://www.taifex.com.tw/cht/3/futContractsDate
J5: 外資買賣超排行 | K5: https://tw.stock.yahoo.com/rank/foreign-investor-buy
A6: 規律跌注意: | B6: 1.每月月初123 (遇假日提前發生) <外資結算> | E6: 3.每月期貨結算請看期貨行事曆 | G6: 5. 每500點階段 | J6: 除權息資訊 | K6: https://concords.moneydj.com/z/ze/zeb/zeb.djhtm
B7: 2.每月第一個星期5 非農 | E7: 4.連假 | G7: 6. 每月10日財報公布 | J7: 除權息資訊2(拉到下方) | K7: https://mops.twse.com.tw/mops/#/web/home
B8: 7.每年過農曆年會提前休市 需要注意去查實際休市日 | J8: 上市櫃注意股查詢 (當天) | K8: https://www.twse.com.tw/zh/announcement/notice.html
B9: 放假 | C9: 漲 | D9: 跌 | E9: 消息日 不確定 | F9: 上格為事前猜 中格為實際 下格為操作 最下格為失準原因or世界情勢 | J9: 上市處置股查詢 | K9: https://www.twse.com.tw/zh/announcement/punish.html
A10: 個人行事曆 | B10: 日 | C10: 一 | D10: 二 | E10: 三 | F10: 四 | G10: 五 | H10: 六 | I10: 每季檢查MSCI | J10: 上櫃處置股查詢 | K10: https://www.tpex.org.tw/zh-tw/announce/market/disposal.html
A11: 46113 | B11: 29 | C11: 30/外資結算前 | D11: 31/外資結算前 | E11: 1/外資結算 | F11: 2/連假前 | G11: 3/清明節 非農 | H11: 4 | I11: 每年2/5/8/11月 | J11: 美國非農就業數據 (每月第一個星期五更新) | K11: https://tradingeconomics.com/united-states/non-farm-payrolls
C12: 市跌 772/1047 櫃跌 603/825 空單: -37282 | D12: 市跌 890/1047 櫃跌 699/825 空單: -37214 | E12: 市跌 100/1047 櫃跌 110/825 空單: -31373 | F12: 市跌 566/1047 櫃跌 788/825 空單: -34855 | J12: 上市櫃公司當日重大訊息 | K12: https://mops.twse.com.tw/mops/#/web/t05sr01_1
J13: 三大法人買賣超統計 | K13: https://www.twse.com.tw/zh/trading/foreign/bfi82u.html
E14: 伊朗發布停戰 | J14: 上市股漲跌狀況 | K14: https://www.twse.com.tw/zh/trading/historical/mi-index.html
B15: 5 | C15: 6/清明節 | D15: 7 | E15: 8 | F15: 9 | G15: 10/財報 | H15: 11 | J15: 上櫃股漲跌狀況 | K15: https://www.tpex.org.tw/zh-tw/mainboard/trading/historical/decline/day.html
D16: 市跌 468/1047 櫃跌 364/825 空單: -31350 | E16: 市跌 154/1047 櫃跌 172/825 空單: -32478 | F16: 市跌 566/1047 櫃跌 461/825 空單: -33399 | G16: 市跌 452/1047 櫃跌 343/825 空單: -34403 | J16: 查詢上市上櫃月營收 (每月10號前更新) | K16: https://mops.twse.com.tw/mops/#/web/t21sc04_ifrs
D17: 買回 | G17: 賣出 | J17: 查詢個股財務報表(財報狗) | K17: https://statementdog.com/
G18: 停戰談判 | J18: 查詢財務報表(win投資) | K18: https://winvest.tw/Stock/Symbol/Comment/1101
B19: 12 | C19: 13 | D19: 14 | E19: 15/期貨結算 | F19: 16 期貨回補 | G19: 17 | H19: 18 | J19: 查詢本益比(上市) | K19: https://www.twse.com.tw/zh/trading/historical/bwibbu.html
C20: 市跌 405/1047 櫃跌 384/825 空單: -35996 | D20: 市跌 331/1047 櫃跌 386/825 空單: -36664 | E20: 市跌 389/1047 櫃跌 385/825 空單: -36783 | F20: 市跌 389/1047 櫃跌 308/825 空單: -39683 | G20: 市跌 499/1047 櫃跌 376/825 空單: -41151 | J20: 查詢本益比(上櫃) | K20: https://www.tpex.org.tw/zh-tw/mainboard/trading/info/stock-pe.html
E21: 買回 | F21: 更改漲跌預估 | G21: 更改漲跌預估 | J21: 群益證卷即時消息(點選重要) | K21: https://www.capitalfutures.com.tw/zh-tw/financial/breakingnews?date=2026-04-01&important=0
C22: 停戰談判 | D22: 停戰談判 | J22: 每日融資融卷增減(上市) | K22: https://accessibility.twse.com.tw/zh/trading/margn/MI_MARGN-margin-dec30.html
B23: 19 | C23: 20 | D23: 21 | E23: 22 | F23: 23 | G23: 24 | H23: 25 | J23: 每日融資融卷增減(上櫃) | K23: https://www.tpex.org.tw/zh-tw/mainboard/trading/margin-trading/rank/day.html
C24: 市跌 532/1047 櫃跌 415/825 空單: -42618 | D24: 市跌 499/1047 櫃跌 364/825 空單: -41295 | J24: 個股每日融資融卷查詢 | K24: https://concords.moneydj.com/z/zc/zcn/zcn.djhtm?a=2330&b=3
C25: 更改漲跌預估 | D25: 更改漲跌預估 | E25: 更改漲跌預估 | J25: Chengwaye 台股觀測站 | K25: https://chengwaye.com/
B27: 26 | C27: 27 | D27: 28 | E27: 29 | F27: 30/月底結算 | G27: 1 | H27: 2
J28: 政府連假行事曆
B31: 3 | C31: 4 | D31: 5 | E31: 6 | F31: 7 | G31: 8 | H31: 9
A36: 注意事項:
B37: 1. 期貨周規律: | C37: 依據2025/11~2026/1的歷史紀錄 期貨周漲跌起伏太劇烈
C38: 最安全的方法為上禮拜五賣出 禮拜五才回補 因為通常下禮拜一都是漲
C39: 不要在期貨周內買入賺最大收益 沒辦法100%賺 至少100%不要賠
B40: 2.假期中間有一個工作日的狀況: (參考2025/12)
C41: 依據2025/12的歷史紀錄 當應該是連假時 但是中間安插了一個工作日
C42: 連假前仍然會暴跌 但是"當個工作日"會回補
C43: 正確操作是連假前的第三天要賣出 然後連假前最後一天買入 然後等"當個工作日"回補
B44: 3. 基於空單口數決定進出場日子
C45: 經由AI分析 當低於-25000時 可進場 當逼近-35000時 必須出場
A46: 優先題材(綠): | B46: 軍工 | C46: 生技醫療 | D46: PCB | E46: BBU | F46: 航太 | G46: 資訊服務 | H46: 安全監控 | I46: 機器人
A47: 46054 | B47: DIMM/DRAM | C47: 航運 | D47: 被動元件 | E47: 矽 | F47: 特化 | G47: 封測 | H47: 低軌衛星 | I47: 光通訊
B48: 雷射鑽頭/探針 | C48: 玻纖布 | D48: 廠務 | E48: 石油
A50: 時間 | B50: 新聞&注意事項 | J50: 需要關注的股神&名人資訊
A51: 月份注意事項 | B51: Q1:1~3,Q2:4~6,Q3:7~9,Q4:10~12 | J51: MrChen (ptt陳爸) | K51: https://www.pttweb.cc/user/mrchen
A52: 12月 | J52: 凱基松山哥廖學邦
A53: 46023 | J53: 巨人傑 | K53: https://www.facebook.com/bigmanJJJ/
J54: 股癌 | K54: https://www.facebook.com/Gooaye
J55: a0808996 | K55: https://www.pttweb.cc/user/a0808996
J56: 川普的個人新聞網 | K56: https://truthsocial.com/@realDonaldTrump
J57: 山椒魚 | K57: https://www.pttweb.cc/user/homoho
A58: 46082 | B58: 金像電 高技 台燿 新的CPU設計原訂Q1末期出貨 改為Q2末期出貨
A61: 46113 | B61: 關注 "資訊服務"族群 依據循環 5月開始可能是此族群上漲月份 持續到7月
A62: 46173 | B62: 金像電 高技 台燿 如無變更行程 則Q2尾(6月) 記得五月底要布局 然後持有1個月 | J62: 每天的操作如下
K63: 事項 | L63: 時間點 | M63: 判斷
J64: STOCK(後台)
J65: 合併財報 | K65: 檢查新聞 | L65: 每天
J66: 合併財報 | K66: 檢查合併財報 | L66: 每天
J67: 月營收 | K67: 檢查月財報 | L67: 每月的8~10日
J68: 消息分析 | K68: 檢查MSCI | L68: 每年2 / 5 / 8 / 11 月
J69: 標的篩選(前台)
J70: 使用方法&新聞 | K70: 更新行事曆-外資結算 | L70: 每月1~3日 | M70: 跌
J71: 使用方法&新聞 | K71: 更新行事曆-非農數據 | L71: 每月第一個禮拜五
J72: 使用方法&新聞 | K72: 更新行事曆-期貨結算 | L72: 每月第三個禮拜三 | M72: 跌
J73: 使用方法&新聞 | K73: 檢查外資空單口數 | L73: 每天
J74: 使用方法&新聞 | K74: 檢查除權息 | L74: 每天 | M74: 跌
J75: 使用方法&新聞 | K75: 檢查新聞&注意事項 | L75: 每天
J76: 使用方法&新聞 | K76: 檢查政府連假 | L76: 每天 | M76: 跌
J77: 使用方法&新聞 | K77: 檢查上市櫃處置股 | L77: 每天 | M77: 跌
J78: 使用方法&新聞 | K78: 檢查名人發文 | L78: 每天
J79: 紅綠 | K79: 更新紅綠 | L79: 每天
J80: 紅綠-績優股 | K80: 更新紅綠-績優股 | L80: 每天
J81: 題材股 | K81: 檢查題材股看趨勢 | L81: 每天
J82: 買賣 | K82: 更新價位追蹤 | L82: 每天
J83: 奇摩美股 | K83: 檢查美股漲跌 | L83: 每天1:00 看盤中
J84: PTT股版 | K84: 檢查消息 | L84: 每天

Sheet 基本觀念
A1: 股市循環觀察
A2: 每月循環 | B2: 每月開頭的1 2 3 交易日 依據歷史 當日都會暴跌(跟外資匯款限制有關) <代表每月月初可以低價買入 然後下月第一周賣出>
B3: 每年的9 月 是股災月 依據歷史 整體都是跌 <代表八月底要賣光 因為市場共識 導致散戶亂賣 9月大跌可找低點進場>
B4: 每個關鍵點位(大盤每500點) 達到目標點後 隔天都會大暴跌(外資殺盤) 請在此時前賣出 然後看情況最低點(第三天)買回
B5: 每個月第三周的星期三 要注意期貨結算日 當周會有超大震盪 建議第二周周五賣光獲利 <依據歷史紀錄 第三周會出現三種狀況>
C6: 1.結算日爆殺 此時結算日可買進
C7: 2.結算日前爆殺 可以買進 結算日會暴漲
C8: 3.結算日前平盤 結算日暴漲 則後續幾天 會爆殺>
A9: 基本觀念
A10: 外資未平倉口數增加或減少 該怎麼理解?
B11: 1.如果股市當天大跌 且 當天外資未平倉口數下降 可視為跌深反彈的訊號
A12: 什麼是紅綠買賣壓? 代表什麼意思 我應該如何使用?
B13: 先說結論: | C13: 綠比率(賣壓) > 紅比率(買壓) 代表此"瞬間"股票還會往上漲 反之 紅比率>綠比率 代表此"瞬間" 股票還會往下跌 直到比率平衡50:50保持穩定
B14: 原理舉例: | C14: 假如我們只會看到如下兩行 不是五行
C15: 10 X:O 20
C16: 15 XX:OO 20
C17: 目前股價在X:O 這行
C18: 總賣壓比較會是 10+15 : 20+20
C19: 當我們價錢推進 從X:O 跑到XX:OO
C20: 第一行消失 第一行的賣 20 被買光了對吧? 所以此行價位會從賣壓變買壓 此時變成 ?? O:OO 20
C21: 但是在O從賣變買的瞬間 是不是沒有人掛單 所以他是變成 0 O:OO 20 因為那個瞬間 賣被買光了 但買的掛單還沒人開始下
C22: 是不是 就變成突然賣壓高 所以才會顯示 綠色賣壓多於買壓 但是以股價來看 他卻是漲上去
C23: 當這個瞬間一直發生(大戶瘋狂買) 就變成連續性 然後股價就會一直往上衝 所以賣壓才會看起來一直維持比買壓高
C24: 反之 賣壓(紅)>買壓(綠) 也是同樣道理
C25: 此現象直到 比率平衡 此現象才會消失(因為沒人要往上買 或是往下賣了)
C26: 所以當天看到想要的股票時
... C28: 如果看到他跌 紅綠條 紅比較長 你可以預期他還會繼續跌 所以你可以等到紅綠條平衡再買
A29: 怎麼看待美國非農就業數據?
B30: 此為美國經濟基礎 只要非農就業高於預期 代表美國經濟好轉 會連帶影響台股"科技業"也走紅
A31: 關於除權息該怎麼看待:
B32: 就是很現實的左手換右手 幫你被動賣出又買進 唯一幫你省的只有少了1%手續費 對你個人來說 實際上根本沒賺沒賠
B33: 依據統計 大部分股票 根本不可能短時間內填息成功 而且懂這邏輯的大戶 還會在除息前的高點 直接大賣停利 導致股價跌更深
B34: 所以手持股票如果近期要除權除息 而且是在 "獲利中"的股票 強烈建議在該日期前賣出 雖然也有少數會秒填息 但是畢竟是"少數"
B35: 除非你手上現在這檔股票已經在賠錢了 那就放著吧 可以賭看看跌深反彈
A36: 如何看待現金增資
B37: 所有"高檔價位"股票 搞現金增資 增完股價就會連吃好幾隻跌停 有看到要增資的股票 要快點出清 原因在於 現金增資公司開的價位一定少於目前股票價位 會有一大波賣出賺價差
A38: 關於每大盤每漲500點 當天或隔天就會大崩跌的 階段崩跌 的狀況 (大盤盤面很好看的還是顯示大漲 但是實際上 大多股票都是綠 所以不能只單看大盤顯示數據
E39: 平日上市跌數約300~400 | F39: https://www.twse.com.tw/zh/trading/historical/mi-index.html
E40: 平日上櫃跌數約250~300 | F40: https://www.tpex.org.tw/zh-tw/mainboard/trading/historical/decline/day.html
B41: 日期 | C41: 大盤突破狀況 | D41: 實際狀況 | E41: 資料佐證
B42: 20250923 | C42: 26000 | D42: 台股暴跌三天 | E42: 上市 跌400~600檔 /總900 櫃買400~600檔跌 /總825
B43: 20250915 | C43: 25500 | D43: 台股當天一片綠 | E43: 櫃買528檔跌 / 總825檔
B44: 20250910 | C44: 25000 | D44: 隔天一片綠 | E44: 櫃買639檔跌/ 總825檔
B45: 20250908 | C45: 24500 | D45: 台股隔天開始連跌三天 | E45: 櫃買400~600檔跌 /總825
B46: 20250827 | C46: 24500 | D46: 台股崩好幾天 | E46: 櫃買400~600檔跌 /總825
B47: 20250819 | C47: 24500 | D47: 台股崩到8/21回穩 | E47: 櫃買400~600檔跌 /總825
B49: 為什麼大盤紅 但是實際卻綠?
C50: 主因在於 台積電仍然在緩慢漲 台積電指數1點 約可增加大盤8點 去除台積電指數 才是實際大盤指數
B51: 如何使用這項資訊?
C52: 這種大跌日 由於是可預期的 所以在階段前可準備資金 選好自己看好的股票 在當天暴跌約1:00左右 隨意進場 隔天通常都會反彈漲回去
C53: 由於有時候連崩好幾天 怕沒買在最低點的 可把資金分散進場 如準備30萬 則分3天 10萬 10萬 10萬進場
C54: 目前數據顯示最多連崩3天回穩 最少隔天回穩
A55: 關於每月 1 2 3 外資結算日 | C55: 線圖經驗顯示第一天大約12點開殺 第二日整體大暴跌 第三天開始回補 建議最慢第一天的9:30最高點要先逃 第三天12點後回補
E56: 平日上市跌數約300~400 | F56: https://www.twse.com.tw/zh/trading/historical/mi-index.html
E57: 平日上櫃跌數約250~300 | F57: https://www.tpex.org.tw/zh-tw/mainboard/trading/historical/decline/day.html
B58: 日期 | C58: 大盤狀況 | D58: 實際狀況 | E58: 資料佐證
B59: 20250902 | D59: 爆殺 | E59: 上市 跌 765 / 總900 上櫃 跌463 / 總825
B60: 20250903 | D60: 爆殺 | E60: 上市 跌 500 / 總900 上櫃 跌252 / 總825
B61: 20250904 | D61: 回補日 | E61: 上市 跌 300 / 總900 上櫃 跌356 / 總825
B62: 20251001 | C62: 線圖看起來紅 | D62: 12點後開始全面下殺 | E62: 上市 跌 600 / 總900 上櫃 跌450 / 總825
B63: 20251002 | C63: 線圖看起來紅 | D63: 全面下殺 | E63: 上市 跌 606 / 總900 上櫃 跌457 / 總825
B64: 20251003 | C64: 線圖看起來紅 | D64: 還在殺(剛好搭配連假效應) | E64: 上市 跌 541 / 總900 上櫃 跌436 / 總825
A66: 關於台積電權值
B67: 台積電漲一元 = 大盤漲8元 所以要看大盤真實情況 就必須要把台積電漲跌扣掉
A68: 什麼是 "公告本公司董事會決議通過私募普通股補辦公開發行案"
B69: 運作原理是: | C69: 1.公司私下募款 給大股東 相關企業 用低價買股票 用於擴廠 此股票為"私募股票" 依據政府規定 三年內不得交易所買賣
C70: 2. 經過3年後 此股票解禁
C71: 3. 由於當時是以極低價位買給各大股東 所以會有很大一部分解禁後開始利益結算
C72: 4. 由於不管怎麼賣 都是當時買入價的好幾倍 所以會亂賣 導致解禁日及後續幾天極大機率跌停 和極大賣壓
C73: 5. 手上有股票的 記得在解禁日前出清
A75: 如何解讀財報?
B76: 需要使用 | C76: 公開資訊觀測站 | D76: 重大資訊: | E76: https://mops.twse.com.tw/mops/#/web/home
D77: 每月營收報告: | E77: 政府發布
C78: 財報狗 | E78: https://statementdog.com/
B79: 重大資訊主要看的是 每季發的 "整年累積財務報告" 的消息 每間公司發布日期不一樣 需要每天去網站抓資料監控
B80: 每月營收報告是 每個月的10日前 政府會要求企業上傳 "單月"營收
B81: 注意: 月營收報告只內含 "單月營收" 不是"單月淨利" / 要看淨利 只能從 "每季發的整年合併財務報告"內 才有資料 所以公司整體有沒有賺錢 是從合併財報看 月營收 只是讓你能事前預測
B83: 舉個例子 | C83: 3706 神達 | D83: 目前時間點: 2025/11/13
B84: 目前有 Q1 Q2 Q3 三季的合併財報 & 10月的月營收報告
B90: 可從資料看出 10月 單月營收的增長率 跟上個月筆試 21.2% 跟去年的10月比是 69.99%
B91: 此時 由於今年跟去年同期比 看起來增長率很棒有69.99% 所以可以期待一下 "今年是賺錢的" 且跟上個月比增長率是21.2% 也是大賺 可以期待
B92: 但是這是以 "月營收"的層面去看 不是"淨利" 因為還沒去扣損失 也還沒有"季合併報表"出現 所以還"不能確定是否真的賺錢 充其量只能先列入關注"
B94: 季度分類如下 季度財報截止日可能慢1~1.5個月 所以可能股價早就反映過了 所以還是需要先查看每月的營收
F108: 注意!!! 如果數字被()框起來是代表 負營收 以下圖例子是 年合併營收EPS "-1.13" (有些公司會直接寫負號)
B109: 然後過幾天 幾個周 幾個月後
B110: Q3時發出 "整年的合併財報" 資訊如右圖
B123: 可以得知 目前 "全年合併 EPS是3.68"
B124: 但是此時要搭配上 "上季的整年財報" 由 "這季的整年合併財報 減掉 上一季的整年合併財報"
B125: 才能準確得知 " 這個季度 到底有沒有賺錢"
B127: 此時 一樣去公開資訊站
B128: 搜尋個股的 歷史訊息
B129: 找 Q2的整年合併財報
B136: Q2 財報如下
B154: 可以得知 Q2當時的合併EPS是2.34元
B155: Q3合併-Q2合併=Q3單季 => 3.68-2.34= 1.34元
B156: 此時 這個1.34 是好還是壞呢? 不知道 所以要搭配歷史紀錄網站 這邊推薦使用財報狗
... B168: 目前 由財報狗 可得知上個季度Q2 的EPS 是1.23
B170: 此時使用公式 | C170: (這季EPS-上季EPS)/上季EPS*100%=增長率
C171: (1.34-1.23)/1.23*100%=8% 增長
B173: 結論:
...

Sheet STOCKS
A1: ID | B1: Name | C1: Type | D1: 收盤價 | E1: 價差 | F1: 漲幅(%) | G1: 五日+- | H1: 五日漲幅(%) | I1: 漲停歷史 | J1: 交易量(張) | K1: 周轉率(%) | L1: MA5 | M1: MA10 | N1: MA20 | O1: 外資(張) | P1: 外資五日+- | Q1: 投信(張) | R1: 自營(張) | S1: 當沖(張) | T1: 當沖(%) | U1: Date | V1: News | W1: ExDate
A2: 2812 | B2: 台中銀 | C2: 金融保險業 | D2: 20.5 | E2: -0.05 | F2: -0.24 | G2: '----- | H2: -1.2 | I2: 0 | J2: 13171 | K2: 0.22 | L2: 20.62 | M2: 20.81 | N2: 20.69 | O2: -5542 | P2: '----- | Q2: 5 | R2: 53 | S2: 1216 | T2: 9.23 | U2: 46132
A3: 1708 | B3: 東鹼 | C3: 化學工業 | D3: 39.3 | E3: -0.05 | F3: -0.13 | G3: '----- | H3: -6.12 | I3: 0 | J3: 2652 | K3: 1.07 | L3: 40.1 | M3: 40.36 | N3: 41.49 | O3: 241 | P3: '-+-++ | Q3: -76 | R3: -4 | S3: 886 | T3: 33.41 | U3: 46132
A4: 6875 | B4: 國邑* | C4: 生技醫療業 | D4: 36 | E4: -0.85 | F4: -2.31 | G4: '-++-- | H4: -3.1 | I4: 0 | J4: 262 | K4: 0.2 | L4: 36.92 | M4: 37.33 | N4: 38.17 | O4: 19 | P4: '+++-+ | Q4: 0 | R4: 0 | S4: 0 | T4: 0 | U4: 46132
A5: 1340 | B5: 勝悅-KY | C5: 塑膠工業 | D5: 6.34 | E5: -0.07 | F5: -1.09 | G5: '+---- | H5: -1.55 | I5: 0 | J5: 232 | K5: 0.15 | L5: 6.43 | M5: 6.51 | N5: 6.64 | O5: 15 | P5: '+---+ | Q5: 0 | R5: 0 | S5: 16 | T5: 6.9 | U5: 46132
A6: 6996 | B6: 力領科技 | C6: 半導體業 | D6: 186 | E6: 1 | F6: 0.54 | G6: '++-++ | H6: 8.33 | I6: 0 | J6: 287 | K6: 0.68 | L6: 183.9 | M6: 176.5 | N6: 171.82 | O6: -23 | P6: '++-+- | Q6: 0 | R6: 0 | S6: 47 | T6: 16.38 | U6: 46132 | W6: 46135
A7: 4588 | B7: 玖鼎電力 | C7: 其他電子業 | D7: 60.3 | E7: 0.1 | F7: 0.17 | G7: '--+-+ | H7: -2.43 | I7: 0 | J7: 124 | K7: 0.29 | L7: 60.62 | M7: 59.6 | N7: 59.1 | O7: 34 | P7: '-++++ | Q7: 0 | R7: 3 | S7: 16 | T7: 12.9 | U7: 46132
A8: 2247 | B8: 汎德永業 | C8: 汽車工業 | D8: 230.5 | E8: -4 | F8: -1.71 | G8: '-+--- | H8: -3.59 | I8: 0 | J8: 163 | K8: 0.2 | L8: 234.4 | M8: 236.7 | N8: 236.35 | O8: -40 | P8: '-++-- | Q8: -20 | R8: 0 | S8: 5 | T8: 3.07 | U8: 46132
A9: 8932 | B9: 智通* | C9: 其他業 | D9: 98.8 | E9: 8.9 | F9: 9.9 | G9: '+--++ | H9: 19.82 | I9: 1 | J9: 4279 | K9: 1.2 | L9: 90.06 | M9: 86.05 | N9: 83.99 | O9: -445 | P9: '---+- | Q9: 0 | R9: 78 | S9: 1104 | T9: 25.8 | U9: 46132
A10: 6887 | B10: 寶綠特-KY | C10: 綠能環保 | D10: 40.3 | E10: -1.75 | F10: -4.16 | G10: '++--- | H10: -3.2 | I10: 1 | J10: 77 | K10: 0.1 | L10: 41.83 | M10: 42.52 | N10: 43.27 | O10: 16 | P10: '+++++ | Q10: 0 | R10: 1 | S10: 12 | T10: 15.58 | U10: 46132
A11: 6680 | B11: 鑫創電子 | C11: 電腦及週邊設備業 | D11: 55.7 | E11: 0.5 | F11: 0.91 | G11: '+---+ | H11: 1.5 | I11: 0 | J11: 14 | K11: 0.06 | L11: 55.82 | M11: 55.63 | N11: 56.23 | O11: 2 | P11: '-+--+ | Q11: 0 | R11: 0 | S11: 5 | T11: 35.71 | U11: 46132
A12: 6761 | B12: 穩得 | C12: 電子零組件業 | D12: 194.5 | E12: -1 | F12: -0.51 | G12: '---+- | H12: -5.6 | I12: 3 | J12: 1033 | K12: 2.96 | L12: 194.9 | M12: 188 | N12: 177.25 | O12: -32 | P12: '+-++- | Q12: 0 | R12: 19 | S12: 431 | T12: 41.72 | U12: 46132
A13: 1532 | B13: 勤美 | C13: 電機機械 | D13: 21.65 | E13: -0.15 | F13: -0.69 | G13: '+-+-- | H13: -1.11 | I13: 0 | J13: 728 | K13: 0.17 | L13: 21.87 | M13: 21.93 | N13: 21.96 | O13: -65 | P13: '+-+-- | Q13: -36 | R13: -15 | S13: 38 | T13: 5.22 | U13: 46132
A14: 2480 | B14: 敦陽科 | C14: 資訊服務業 | D14: 140 | E14: -0.5 | F14: -0.36 | G14: '+-++- | H14: 1.08 | I14: 0 | J14: 416 | K14: 0.39 | L14: 139.7 | M14: 139.75 | N14: 139.88 | O14: -37 | P14: '--++- | Q14: -3 | R14: 0 | S14: 51 | T14: 12.26 | U14: 46132
A15: 2367 | B15: 燿華 | C15: 電子零組件業 | D15: 65.6 | E15: -2.9 | F15: -4.23 | G15: '-+--- | H15: -11.85 | I15: 1 | J15: 61759 | K15: 8.74 | L15: 69.72 | M15: 72.11 | N15: 72.91 | O15: 6083 | P15: '-+--+ | Q15: -431 | R15: -808 | S15: 24374 | T15: 39.47 | U15: 46132
A16: 4557 | B16: 永新-KY | C16: 汽車工業 | D16: 52.7 | E16: -0.9 | F16: -1.68 | G16: '-++-- | H16: -2.37 | I16: 0 | J16: 125 | K16: 0.26 | L16: 53.64 | M16: 54.74 | N16: 56.71 | O16: 41 | P16: '+-+-+ | Q16: 0 | R16: 0 | S16: 15 | T16: 12 | U16: 46132
A17: 3231 | B17: 緯創 | C17: 電腦及週邊設備業 | D17: 140.5 | E17: 4 | F17: 2.93 | G17: '+-+++ | H17: 4.48 | I17: 0 | J17: 79145 | K17: 2.49 | L17: 136.1 | M17: 133.7 | N17: 130.18 | O17: 31159 | P17: '+--++ | Q17: 827 | R17: 1095 | S17: 22772 | T17: 28.77 | U17: 46132 | V17: 代⼦公司Wiwynn Technology Corporation(WYMUS)公告進行建築物改良
A18: 3527 | B18: 聚積 | C18: 半導體業 | D18: 58.7 | E18: -1.2 | F18: -2 | G18: '++++- | H18: 10.16 | I18: 0 | J18: 207 | K18: 0.47 | L18: 57.8 | M18: 55.48 | N18: 53.9 | O18: -56 | P18: '++++- | Q18: 0 | R18: 0 | S18: 27 | T18: 13.04 | U18: 46132
A19: 6592 | B19: 和潤企業 | C19: 其他業 | D19: 64.1 | E19: -0.4 | F19: -0.62 | G19: '+++-- | H19: 2.08 | I19: 0 | J19: 808 | K19: 0.13 | L19: 64.36 | M19: 63.5 | N19: 63.54 | O19: 255 | P19: '+++++ | Q19: 0 | R19: -94 | S19: 181 | T19: 22.4 | U19: 46132
A20: 2501 | B20: 國建 | C20: 建材營造業 | D20: 24.8 | E20: 0.35 | F20: 1.43 | G20: '++--+ | H20: 3.13 | I20: 0 | J20: 2772 | K20: 0.24 | L20: 24.69 | M20: 24.01 | N20: 23.67 | O20: 159 | P20: '+++++ | Q20: 4 | R20: 572 | S20: 611 | T20: 22.04 | U20: 46132
A21: 3093 | B21: 港建* | C21: 其他電子業 | D21: 73.5 | E21: 0.5 | F21: 0.68 | G21: '++--+ | H21: 17.02 | I21: 5 | J21: 5376 | K21: 3.7 | L21: 72.82 | M21: 66.42 | N21: 55.69 | O21: -528 | P21: '-+--- | Q21: 0 | R21: 0 | S21: 2316 | T21: 43.08 | U21: 46132
A22: 5403 | B22: 中菲 | C22: 資訊服務業 | D22: 93 | E22: -1.4 | F22: -1.48 | G22: '-++-- | H22: -2.12 | I22: 0 | J22: 127 | K22: 0.16 | L22: 93.54 | M22: 95.94 | N22: 99.5 | O22: -23 | P22: '++++- | Q22: 0 | R22: 3 | S22: 4 | T22: 3.15 | U22: 46132
A23: 6753 | B23: 龍德造船 | C23: 航運業 | D23: 144 | E23: 5.5 | F23: 3.97 | G23: '+++-+ | H23: 14.62 | I23: 0 | J23: 2714 | K23: 2.31 | L23: 138.6 | M23: 132.75 | N23: 130.88 | O23: 343 | P23: '+++++ | Q23: 0 | R23: 191 | S23: 1149 | T23: 42.34 | U23: 46132
A24: 6928 | B24: 攸泰科技 | C24: 電腦及週邊設備業 | D24: 48.7 | E24: -0.1 | F24: -0.2 | G24: '++-+- | H24: 6.56 | I24: 0 | J24: 144 | K24: 0.17 | L24: 48.21 | M24: 47.02 | N24: 46.71 | O24: -27 | P24: '+++-- | Q24: 0 | R24: 0 | S24: 35 | T24: 24.31 | U24: 46132
A25: 3576 | B25: 聯合再生 | C25: 光電業 | D25: 17.2 | E25: -1.1 | F25: -6.01 | G25: '-++-- | H25: 2.2 | I25: 4 | J25: 35648 | K25: 2.19 | L25: 17.27 | M25: 18.4 | N25: 20.27 | O25: 6525 | P25: '+++-+ | Q25: 0 | R25: -6 | S25: 0 | T25: 0 | U25: 46132
A26: 2323 | B26: 中環 | C26: 光電業 | D26: 10.75 | E26: 0 | F26: 0 | G26: '+-+-- | H26: 0.02 | I26: 1 | J26: 4122 | K26: 0.38 | L26: 10.83 | M26: 10.86 | N26: 11.21 | O26: 287 | P26: '+-+-+ | Q26: 0 | R26: -135 | S26: 1019 | T26: 24.72 | U26: 46132 | V26: 公告本公司取得有價證券
A27: 2301 | B27: 光寶科 | C27: 電腦及週邊設備業 | D27: 165 | E27: 3 | F27: 1.85 | G27: '+++++ | H27: 7.29 | I27: 1 | J27: 30332 | K27: 1.31 | L27: 160.9 | M27: 157.35 | N27: 154.32 | O27: 7914 | P27: '+++++ | Q27: -1339 | R27: -51 | S27: 9939 | T27: 32.77 | U27: 46132 | V27: 光寶科技115年第一季法人說明會
A28: 2867 | B28: 三商壽 | C28: 金融保險業 | D28: 7.88 | E28: 0.01 | F28: 0.13 | G28: '++--+ | H28: 2.34 | I28: 0 | J28: 12565 | K28: 0.21 | L28: 7.89 | M28: 7.82 | N28: 7.73 | O28: 7056 | P28: '+++++ | Q28: 0 | R28: -1405 | S28: 2023 | T28: 16.1 | U28: 46132
A29: 5289 | B29: 宜鼎 | C29: 電腦及週邊設備業 | D29: 1020 | E29: 15 | F29: 1.49 | G29: '+---+ | H29: -10.13 | I29: 2 | J29: 3108 | K29: 3.23 | L29: 1086 | M29: 1087.8 | N29: 1035.65 | O29: 70 | P29: '----+ | Q29: -75 | R29: 23 | S29: 1417 | T29: 45.59 | U29: 46132
A30: 2006 | B30: 東和鋼鐵 | C30: 鋼鐵工業 | D30: 70.1 | E30: -1.7 | F30: -2.37 | G30: '--++- | H30: -1.51 | I30: 0 | J30: 3004 | K30: 0.41 | L30: 70.76 | M30: 70.79 | N30: 70.58 | O30: -526 | P30: '--++- | Q30: 60 | R30: -54 | S30: 725 | T30: 24.13 | U30: 46132 | V30: 公告本公司115年第1季合併財務報告董事會預計召開 日期為115年04月28日
A31: 6491 | B31: 晶碩 | C31: 生技醫療業 | D31: 288 | E31: -5.5 | F31: -1.87 | G31: '+++-- | H31: 0.73 | I31: 0 | J31: 321 | K31: 0.41 | L31: 291.2 | M31: 290.55 | N31: 285.8 | O31: -136 | P31: '++++- | Q31: -1 | R31: -1 | S31: 39 | T31: 12.15 | U31: 46132
A32: 6431 | B32: 光麗-KY | C32: 生技醫療業 | D32: 21.3 | E32: 0 | F32: 0 | G32: '---+- | H32: -3.17 | I32: 2 | J32: 82 | K32: 0.08 | L32: 21.38 | M32: 21.87 | N32: 22.13 | O32: -15 | P32: '+-++- | Q32: 0 | R32: -1 | S32: 0 | T32: 0 | U32: 46132
A33: 1467 | B33: 南緯 | C33: 紡織纖維 | D33: 7 | E33: 0 | F33: 0 | G33: '++--- | H33: -0.71 | I33: 0 | J33: 155 | K33: 0.07 | L33: 7.03 | M33: 7.04 | N33: 7.05 | O33: 18 | P33: '++--+ | Q33: 0 | R33: 0 | S33: 17 | T33: 10.97 | U33: 46132
A34: 7788 | B34: 松川精密 | C34: 電子零組件業 | D34: 167 | E34: 4 | F34: 2.45 | G34: '++-++ | H34: 14.17 | I34: 1 | J34: 817 | K34: 1.02 | L34: 156 | M34: 148.45 | N34: 145.22 | O34: -200 | P34: '+--+- | Q34: 0 | R34: 3 | S34: 179 | T34: 21.91 | U34: 46132
A35: 3406 | B35: 玉晶光 | C35: 光電業 | D35: 544 | E35: 41 | F35: 8.15 | G35: '+-+-+ | H35: 12.92 | I35: 0 | J35: 4133 | K35: 3.67 | L35: 517 | M35: 486.1 | N35: 466.95 | O35: 1525 | P35: '+-+-+ | Q35: -422 | R35: 76 | S35: 1165 | T35: 28.19 | U35: 46132
A36: 3611 | B36: 鼎翰 | C36: 電腦及週邊設備業 | D36: 190 | E36: 3 | F36: 1.6 | G36: '-+--+ | H36: 1.07 | I36: 0 | J36: 53 | K36: 0.11 | L36: 187.8 | M36: 187.15 | N36: 186.97 | O36: -16 | P36: '---+- | Q36: 0 | R36: 1 | S36: 4 | T36: 7.55 | U36: 46132
A37: 6606 | B37: 建德工業 | C37: 電機機械 | D37: 24.7 | E37: 0.1 | F37: 0.41 | G37: '+++-+ | H37: 2.07 | I37: 0 | J37: 98 | K37: 0.09 | L37: 24.55 | M37: 24.35 | N37: 24.19 | O37: 19 | P37: '+++++ | Q37: 0 | R37: 1 | S37: 5 | T37: 5.1 | U37: 46132
A38: 8155 | B38: 博智 | C38: 電子零組件業 | D38: 401.5 | E38: 24 | F38: 6.36 | G38: '++-++ | H38: 25.32 | I38: 2 | J38: 4446 | K38: 7.27 | L38: 364 | M38: 333.55 | N38: 296.62 | O38: -449 | P38: '++--- | Q38: 0 | R38: -321 | S38: 2050 | T38: 46.11 | U38: 46132
A39: 2049 | B39: 上銀 | C39: 電機機械 | D39: 293.5 | E39: 2.5 | F39: 0.86 | G39: '++-++ | H39: 16.65 | I39: 1 | J39: 10124 | K39: 2.86 | L39: 284.1 | M39: 263.3 | N39: 247.3 | O39: 69 | P39: '-++++ | Q39: 0 | R39: -210 | S39: 4690 | T39: 46.33 | U39: 46132
A40: 3466 | B40: 德晉 | C40: 通信網路業 | D40: 43.75 | E40: 2.75 | F40: 6.71 | G40: '+++++ | H40: 16.33 | I40: 1 | J40: 2784 | K40: 3.57 | L40: 40.94 | M40: 37.98 | N40: 36.31 | O40: -22 | P40: '++-+- | Q40: 0 | R40: 0 | S40: 937 | T40: 33.66 | U40: 46132
A41: 1503 | B41: 士電 | C41: 電機機械 | D41: 194.5 | E41: -3 | F41: -1.52 | G41: '++++- | H41: 1.06 | I41: 0 | J41: 2351 | K41: 0.45 | L41: 195.1 | M41: 190.25 | N41: 189.62 | O41: -305 | P41: '--++- | Q41: 0 | R41: 15 | S41: 807 | T41: 34.33 | U41: 46132 | V41: 公告本公司發言人與代理發言人異動
A42: 1101 | B42: 台泥 | C42: 水泥工業 | D42: 24.8 | E42: -0.3 | F42: -1.2 | G42: '+-++- | H42: -1.74 | I42: 0 | J42: 15979 | K42: 0.21 | L42: 24.96 | M42: 24.99 | N42: 24.02 | O42: -1240 | P42: '--++- | Q42: 0 | R42: -66 | S42: 3383 | T42: 21.17 | U42: 46132
A43: 4956 | B43: 光鋐 | C43: 光電業 | D43: 54.7 | E43: 4.95 | F43: 9.95 | G43: '++-++ | H43: 38.3 | I43: 4 | J43: 1392 | K43: 1.39 | L43: 47.49 | M43: 41.89 | N43: 37.98 | O43: -19 | P43: '++++- | Q43: 0 | R43: 607 | S43: 21 | T43: 1.51 | U43: 46132
A44: 3057 | B44: 喬鼎 | C44: 電腦及週邊設備業 | D44: 18.5 | E44: -0.1 | F44: -0.54 | G44: '++-+- | H44: 7.19 | I44: 1 | J44: 451 | K44: 0.66 | L44: 18.59 | M44: 17.51 | N44: 16.98 | O44: 104 | P44: '++--+ | Q44: 0 | R44: 0 | S44: 0 | T44: 0 | U44: 46132
A45: 3236 | B45: 千如 | C45: 電子零組件業 | D45: 33.9 | E45: -1.35 | F45: -3.83 | G45: '-++-- | H45: -1.85 | I45: 0 | J45: 4251 | K45: 4.05 | L45: 34.66 | M45: 33.2 | N45: 32.04 | O45: 739 | P45: '+-+++ | Q45: 0 | R45: -6 | S45: 1485 | T45: 34.93 | U45: 46132
A46: 8222 | B46: 寶一 | C46: 電機機械 | D46: 37.85 | E46: 0 | F46: 0 | G46: '++++- | H46: 9.45 | I46: 0 | J46: 565 | K46: 0.82 | L46: 36.89 | M46: 35.61 | N46: 35.82 | O46: 61 | P46: '++-++ | Q46: 0 | R46: 0 | S46: 134 | T46: 23.72 | U46: 46132
A47: 3413 | B47: 京鼎 | C47: 半導體業 | D47: 327.5 | E47: 13 | F47: 4.13 | G47: '+-+-+ | H47: 3.22 | I47: 0 | J47: 3530 | K47: 3.19 | L47: 318.9 | M47: 313.05 | N47: 307.77 | O47: 556 | P47: '+-+++ | Q47: -23 | R47: 95 | S47: 1000 | T47: 28.33 | U47: 46132 | V47: 本公司董事會決議召開115年股東常會相關事宜 (修正討論事項) | W47: 46169
A48: 4528 | B48: 江興鍛 | C48: 電機機械 | D48: 15.9 | E48: -1.25 | F48: -7.29 | G48: '+--+- | H48: -5.82 | I48: 0 | J48: 267 | K48: 0.32 | L48: 16.92 | M48: 17.11 | N48: 17.36 | O48: 13 | P48: '+-+++ | Q48: 0 | R48: 0 | S48: 34 | T48: 12.73 | U48: 46132 | W48: 46128
A49: 6128 | B49: 上福 | C49: 電腦及週邊設備業 | D49: 21.05 | E49: 0 | F49: 0 | G49: '+--+- | H49: 0.03 | I49: 0 | J49: 68 | K49: 0.05 | L49: 21.06 | M49: 20.94 | N49: 21.15 | O49: 3 | P49: '+-+-+ | Q49: 0 | R49: -1 | S49: 4 | T49: 5.88 | U49: 46132
A50: 2640 | B50: 大車隊 | C50: 數位雲端 | D50: 188 | E50: 1 | F50: 0.53 | G50: '-++++ | H50: 3.85 | I50: 1 | J50: 100 | K50: 0.17 | L50: 183 | M50: 176.65 | N50: 176.6 | O50: -30 | P50: '--+-- | Q50: 0 | R50: 1 | S50: 24 | T50: 24 | U50: 46132
A51: 5523 | B51: 豐謙 | C51: 建材營造業 | D51: 30.5 | E51: 0 | F51: 0 | G51: '----- | H51: -0.33 | I51: 0 | J51: 71 | K51: 0.05 | L51: 30.5 | M51: 30.24 | N51: 29.79 | O51: -1 | P51: '---+- | Q51: 0 | R51: 0 | S51: 23 | T51: 32.39 | U51: 46132 | V51: 公告本公司115年第一季合併財務報告董事會預計召開日期 為115年4月28日。
A52: 5345 | B52: 馥鴻 | C52: 其他業 | D52: 23 | E52: -0.2 | F52: -0.86 | G52: '-+--- | H52: -2.13 | I52: 0 | J52: 16 | K52: 0.04 | L52: 23.35 | M52: 23.41 | N52: 23.11 | O52: 0 | P52: '----- | Q52: 0 | R52: 0 | S52: 0 | T52: 0 | U52: 46132
A53: 4568 | B53: 科際精密 | C53: 電機機械 | D53: 41.95 | E53: 0.45 | F53: 1.08 | G53: '++-++ | H53: 1.08 | I53: 0 | J53: 8 | K53: 0.03 | L53: 41.61 | M53: 41.84 | N53: 41.92 | O53: 1 | P53: '----+ | Q53: 0 | R53: 0 | S53: 0 | T53: 0 | U53: 46132
A54: 8937 | B54: 合騏* | C54: 其他業 | D54: 33.9 | E54: 3.05 | F54: 9.89 | G54: '----+ | H54: -10.34 | I54: 1 | J54: 196 | K54: 0.05 | L54: 33.07 | M54: 79.19 | N54: 117.09 | O54: 82 | P54: '-++-+ | Q54: 0 | R54: 8 | S54: 6 | T54: 3.06 | U54: 46132 | V54: 公告本公司股票面額由「新台幣10元」變更為「新台幣2.5元」
A55: 3306 | B55: 鼎天 | C55: 通信網路業 | D55: 47.85 | E55: 0.4 | F55: 0.84 | G55: '+---+ | H55: 1.69 | I55: 0 | J55: 304 | K55: 0.6 | L55: 47.53 | M55: 47.34 | N55: 47.36 | O55: 35 | P55: '+-+++ | Q55: 0 | R55: 0 | S55: 49 | T55: 16.12 | U55: 46132
A56: 3032 | B56: 偉訓 | C56: 電子零組件業 | D56: 61.1 | E56: -0.7 | F56: -1.13 | G56: '--+-- | H56: -0.88 | I56: 0 | J56: 565 | K56: 0.5 | L56: 61.46 | M56: 62.16 | N56: 63.08 | O56: -29 | P56: '--+-- | Q56: 0 | R56: 0 | S56: 90 | T56: 15.93 | U56: 46132
A57: 4989 | B57: 榮科 | C57: 電子零組件業 | D57: 107 | E57: 4.5 | F57: 4.39 | G57: '+++-+ | H57: 28.75 | I57: 4 | J57: 6183 | K57: 4.49 | L57: 100.44 | M57: 86.99 | N57: 76.8 | O57: -426 | P57: '+++-- | Q57: 0 | R57: 2 | S57: 0 | T57: 0 | U57: 46132
A58: 4540 | B58: 全球傳動 | C58: 電機機械 | D58: 58.8 | E58: 0.9 | F58: 1.55 | G58: '++-++ | H58: 22.91 | I58: 2 | J58: 13360 | K58: 11.6 | L58: 54.98 | M58: 49.45 | N58: 46.25 | O58: -1787 | P58: '++++- | Q58: 0 | R58: -2 | S58: 6277 | T58: 46.98 | U58: 46132 | V58: 係因本公司有價證券於集中交易市場達公布注意交易資訊標準， 故公布相關財務業務等重大訊息，以利投資人區別瞭解。
A59: 5443 | B59: 均豪 | C59: 半導體業 | D59: 119.5 | E59: 5.5 | F59: 4.82 | G59: '----+ | H59: 1.81 | I59: 0 | J59: 16965 | K59: 10.3 | L59: 115.9 | M59: 113.8 | N59: 107.95 | O59: 3300 | P59: '+--++ | Q59: 0 | R59: 285 | S59: 7959 | T59: 46.91 | U59: 46132
A60: 6762 | B60: 達亞 | C60: 生技醫療業 | D60: 170.5 | E60: 0 | F60: 0 | G60: '---+- | H60: 3.39 | I60: 0 | J60: 2 | K60: 0.01 | L60: 166 | M60: 165.5 | N60: 166.07 | O60: 0 | P60: '+-++- | Q60: 0 | R60: 0 | S60: 0 | T60: 0 | U60: 46132
A61: 5703 | B61: 亞都 | C61: 觀光餐旅 | D61: 14.75 | E61: -0.05 | F61: -0.34 | G61: '--+-- | H61: -4.15 | I61: 1 | J61: 6 | K61: 0.01 | L61: 14.84 | M61: 14.5 | N61: 14.09 | O61: 0 | P61: '+---- | Q61: 0 | R61: 0 | S61: 0 | T61: 0 | U61: 46132
A62: 6741 | B62: 91APP*-KY | C62: 數位雲端 | D62: 65.5 | E62: 1.8 | F62: 2.83 | G62: '--+++ | H62: 4.29 | I62: 0 | J62: 855 | K62: 0.71 | L62: 63.42 | M62: 62.58 | N62: 61.86 | O62: 118 | P62: '--+-+ | Q62: 0 | R62: 1 | S62: 116 | T62: 13.57 | U62: 46132
A63: 7734 | B63: 印能科技 | C63: 半導體業 | D63: 2605 | E63: 100 | F63: 3.99 | G63: '---++ | H63: -0.58 | I63: 4 | J63: 570 | K63: 2.04 | L63: 2462 | M63: 2486.5 | N63: 2224.25 | O63: 24 | P63: '+--++ | Q63: -39 | R63: 92 | S63: 0 | T63: 0 | U63: 46132
A64: 5547 | B64: 久舜 | C64: 建材營造業 | D64: 21.8 | E64: -0.1 | F64: -0.46 | G64: '--+-- | H64: -2.03 | I64: 0 | J64: 36 | K64: 0.08 | L64: 22.04 | M64: 22.18 | N64: 22.36 | O64: -2 | P64: '----- | Q64: 0 | R64: -3 | S64: 0 | T64: 0 | U64: 46132
A65: 9931 | B65: 欣高 | C65: 油電燃氣業 | D65: 36.05 | E65: 0.05 | F65: 0.14 | G65: '-+--+ | H65: -0.14 | I65: 1 | J65: 131 | K65: 0.11 | L65: 36.02 | M65: 36.02 | N65: 37.48 | O65: 20 | P65: '+++++ | Q65: 0 | R65: 0 | S65: 16 | T65: 12.21 | U65: 46132
A66: 3011 | B66: 今皓 | C66: 電子零組件業 | D66: 13.5 | E66: 0.25 | F66: 1.89 | G66: '+-+++ | H66: 5.06 | I66: 0 | J66: 1535 | K66: 1.18 | L66: 13.06 | M66: 12.78 | N66: 12.64 | O66: 221 | P66: '+-+-+ | Q66: 0 | R66: -1 | S66: 357 | T66: 23.26 | U66: 46132
A67: 6113 | B67: 亞矽 | C67: 電子通路業 | D67: 23.3 | E67: 0.4 | F67: 1.75 | G67: '++--+ | H67: 9.79 | I67: 3 | J67: 910 | K67: 1.73 | L67: 22.97 | M67: 21.75 | N67: 20.82 | O67: -115 | P67: '++--- | Q67: 0 | R67: 0 | S67: 265 | T67: 29.12 | U67: 46132
A68: 2395 | B68: 研華 | C68: 電腦及週邊設備業 | D68: 363.5 | E68: -2.5 | F68: -0.68 | G68: '++++- | H68: 6.03 | I68: 0 | J68: 3362 | K68: 0.39 | L68: 355.3 | M68: 348.4 | N68: 339.38 | O68: 540 | P68: '+++++ | Q68: -25 | R68: -3 | S68: 844 | T68: 25.1 | U68: 46132
A69: 3162 | B69: 精確 | C69: 電機機械 | D69: 69 | E69: 4.5 | F69: 6.98 | G69: '+--++ | H69: 3.85 | I69: 1 | J69: 6486 | K69: 4.2 | L69: 66.2 | M69: 65.62 | N69: 60.85 | O69: 1607 | P69: '---++ | Q69: 0 | R69: 0 | S69: 1697 | T69: 26.16 | U69: 46132 | V69: 公告本公司註銷收回之限制員工權利新股辦理 減資變更登記完成
A70: 6160 | B70: 欣技 | C70: 電腦及週邊設備業 | D70: 16.1 | E70: 0.35 | F70: 2.22 | G70: '+--++ | H70: 5.16 | I70: 0 | J70: 147 | K70: 0.21 | L70: 15.79 | M70: 15.64 | N70: 15.86 | O70: -4 | P70: '--++- | Q70: 0 | R70: 0 | S70: 0 | T70: 0 | U70: 46132
A71: 4129 | B71: 聯合 | C71: 生技醫療業 | D71: 103.5 | E71: -2 | F71: -1.9 | G71: '++-+- | H71: 2.06 | I71: 0 | J71: 320 | K71: 0.33 | L71: 104.9 | M71: 102.93 | N71: 102.28 | O71: -36 | P71: '+--+- | Q71: 0 | R71: 0 | S71: 36 | T71: 11.25 | U71: 46132
A72: 6134 | B72: 萬旭 | C72: 電子零組件業 | D72: 31.3 | E72: -0.05 | F72: -0.16 | G72: '-+--- | H72: -4.5 | I72: 1 | J72: 672 | K72: 0.82 | L72: 31.91 | M72: 31.66 | N72: 30.51 | O72: 297 | P72: '+++++ | Q72: 0 | R72: 0 | S72: 73 | T72: 10.86 | U72: 46132
A73: 8074 | B73: 鉅橡 | C73: 電子零組件業 | D73: 78.3 | E73: 7.1 | F73: 9.97 | G73: '+-+++ | H73: 13 | I73: 2 | J73: 24456 | K73: 30.2 | L73: 71.42 | M73: 67.43 | N73: 61.81 | O73: -604 | P73: '++-+- | Q73: 0 | R73: 191 | S73: 15135 | T73: 61.89 | U73: 46132
A74: 6196 | B74: 帆宣 | C74: 其他電子業 | D74: 394.5 | E74: 35.5 | F74: 9.89 | G74: '++-++ | H74: 21.73 | I74: 1 | J74: 2977 | K74: 1.35 | L74: 355.5 | M74: 333.6 | N74: 308.88 | O74: 120 | P74: '++-++ | Q74: -72 | R74: 156 | S74: 1011 | T74: 33.96 | U74: 46132
A75: 6527 | B75: 明達醫 | C75: 生技醫療業 | D75: 70 | E75: -0.5 | F75: -0.71 | G75: '---+- | H75: -0.7 | I75: 0 | J75: 118 | K75: 0.46 | L75: 70.28 | M75: 70.49 | N75: 71.23 | O75: -4 | P75: '-++-- | Q75: 0 | R75: 0 | S75: 0 | T75: 0 | U75: 46132
A76: 6124 | B76: 業強 | C76: 電子零組件業 | D76: 29.9 | E76: -1.15 | F76: -3.7 | G76: '+++-- | H76: -2.02 | I76: 1 | J76: 143 | K76: 0.08 | L76: 30.9 | M76: 30.98 | N76: 30.77 | O76: -33 | P76: '+-+-- | Q76: 0 | R76: 0 | S76: 11 | T76: 7.69 | U76: 46132
A77: 6838 | B77: 台新藥 | C77: 生技醫療業 | D77: 29.4 | E77: -1.1 | F77: -3.61 | G77: '+---- | H77: -7.7 | I77: 1 | J77: 320 | K77: 0.21 | L77: 31.08 | M77: 31.18 | N77: 28.98 | O77: 29 | P77: '+++-+ | Q77: 0 | R77: 0 | S77: 0 | T77: 0 | U77: 46132
A78: 6241 | B78: 易通展 | C78: 通信網路業 | D78: 10.1 | E78: 0 | F78: 0 | G78: '+-+-- | H78: 0.04 | I78: 0 | J78: 115 | K78: 0.24 | L78: 10.14 | M78: 10.38 | N78: 11.07 | O78: 7 | P78: '+---+ | Q78: 0 | R78: 0 | S78: 0 | T78: 0 | U78: 46132
A79: 6488 | B79: 環球晶 | C79: 半導體業 | D79: 551 | E79: 46 | F79: 9.11 | G79: '+++-+ | H79: 10.57 | I79: 2 | J79: 8570 | K79: 1.79 | L79: 522.6 | M79: 489.85 | N79: 463.65 | O79: 3023 | P79: '+++-+ | Q79: 75 | R79: 121 | S79: 2343 | T79: 27.34 | U79: 46132 | W79: 46219
A80: 4563 | B80: 百德 | C80: 電機機械 | D80: 40.75 | E80: 0.05 | F80: 0.12 | G80: '+-+-+ | H80: 1.28 | I80: 0 | J80: 86 | K80: 0.16 | L80: 41.01 | M80: 40.62 | N80: 41.29 | O80: 24 | P80: '+++-+ | Q80: 0 | R80: 0 | S80: 7 | T80: 8.14 | U80: 46132
A81: 2471 | B81: 資通 | C81: 資訊服務業 | D81: 53.2 | E81: -0.8 | F81: -1.48 | G81: '+++-- | H81: 4 | I81: 0 | J81: 230 | K81: 0.49 | L81: 53.12 | M81: 52.43 | N81: 52.1 | O81: -52 | P81: '--+-- | Q81: 0 | R81: -11 | S81: 15 | T81: 6.52 | U81: 46132
A82: 1514 | B82: 亞力 | C82: 電機機械 | D82: 113 | E82: -1 | F82: -0.88 | G82: '++++- | H82: 5.99 | I82: 0 | J82: 5278 | K82: 1.93 | L82: 111 | M82: 107.45 | N82: 107.9 | O82: -429 | P82: '+--+- | Q82: 0 | R82: -20 | S82: 2064 | T82: 39.11 | U82: 46132
A83: 3118 | B83: 進階 | C83: 生技醫療業 | D83: 33.5 | E83: 0.05 | F83: 0.15 | G83: '-+--+ | H83: 0 | I83: 0 | J83: 29 | K83: 0.09 | L83: 33.45 | M83: 33.52 | N83: 33.42 | O83: 0 | P83: '++--- | Q83: 0 | R83: 0 | S83: 0 | T83: 0 | U83: 46132
A84: 1709 | B84: 和益 | C84: 化學工業 | D84: 18.95 | E84: 0 | F84: 0 | G84: '+---- | H84: -1.3 | I84: 0 | J84: 640 | K84: 0.13 | L84: 19.09 | M84: 18.73 | N84: 18.39 | O84: 221 | P84: '-++++ | Q84: 0 | R84: -12 | S84: 67 | T84: 10.47 | U84: 46132
A85: 7705 | B85: 三商餐飲 | C85: 觀光餐旅 | D85: 34.6 | E85: -0.2 | F85: -0.57 | G85: '-++-- | H85: -1.14 | I85: 0 | J85: 47 | K85: 0.07 | L85: 34.9 | M85: 34.84 | N85: 34.83 | O85: 2 | P85: '-++-+ | Q85: 0 | R85: 0 | S85: 7 | T85: 14.89 | U85: 46132 | V85: 公告本公司向關係人取得使用權資產
A86: 6432 | B86: 今展科 | C86: 電子零組件業 | D86: 44.75 | E86: 4.05 | F86: 9.95 | G86: '+--++ | H86: 13.15 | I86: 3 | J86: 1521 | K86: 4.43 | L86: 40.93 | M86: 37.73 | N86: 35.88 | O86: 124 | P86: '+--++ | Q86: 0 | R86: 7 | S86: 151 | T86: 9.93 | U86: 46132
A87: 4907 | B87: 富宇 | C87: 建材營造業 | D87: 39.5 | E87: -0.25 | F87: -0.63 | G87: '-+--- | H87: -4.41 | I87: 0 | J87: 120 | K87: 0.1 | L87: 40.23 | M87: 40.71 | N87: 40.71 | O87: -11 | P87: '--+-- | Q87: 0 | R87: 0 | S87: 8 | T87: 6.67 | U87: 46132
A88: 4555 | B88: 氣立 | C88: 電機機械 | D88: 40.4 | E88: -0.65 | F88: -1.58 | G88: '++++- | H88: 9.26 | I88: 0 | J88: 544 | K88: 0.78 | L88: 39.65 | M88: 37.8 | N88: 36.77 | O88: -147 | P88: '----- | Q88: 0 | R88: 0 | S88: 94 | T88: 17.28 | U88: 46132
A89: 1736 | B89: 喬山 | C89: 運動休閒 | D89: 116 | E89: -2.5 | F89: -2.11 | G89: '--+-- | H89: -1.6 | I89: 0 | J89: 759 | K89: 0.25 | L89: 117.7 | M89: 119.6 | N89: 122.17 | O89: 146 | P89: '+++++ | Q89: -200 | R89: -1 | S89: 77 | T89: 10.14 | U89: 46132
A90: 2845 | B90: 遠東銀 | C90: 金融保險業 | D90: 12.6 | E90: -0.05 | F90: -0.4 | G90: '+-+-- | H90: 0.01 | I90: 0 | J90: 4767 | K90: 0.1 | L90: 12.65 | M90: 12.64 | N90: 12.54 | O90: 745 | P90: '+++++ | Q90: -2 | R90: 452 | S90: 725 | T90: 15.21 | U90: 46132
A91: 8929 | B91: 富堡 | C91: 其他業 | D91: 15.45 | E91: -0.1 | F91: -0.64 | G91: '--+-- | H91: -0.96 | I91: 0 | J91: 35 | K91: 0.07 | L91: 15.55 | M91: 15.71 | N91: 15.86 | O91: -4 | P91: '+-+-- | Q91: 0 | R91: 0 | S91: 0 | T91: 0 | U91: 46132
A92: 6846 | B92: 綠茵 | C92: 食品工業 | D92: 71 | E92: -0.1 | F92: -0.14 | G92: '+---- | H92: -0.42 | I92: 0 | J92: 11 | K92: 0.04 | L92: 71.2 | M92: 71.09 | N92: 70.99 | O92: 0 | P92: '+---- | Q92: 0 | R92: 0 | S92: 0 | T92: 0 | U92: 46132
A93: 3546 | B93: 宇峻 | C93: 文化創意業 | D93: 70.5 | E93: -0.9 | F93: -1.26 | G93: '-++-- | H93: 0.88 | I93: 0 | J93: 203 | K93: 0.35 | L93: 70.86 | M93: 70.13 | N93: 70.36 | O93: 65 | P93: '+++++ | Q93: 0 | R93: 0 | S93: 48 | T93: 23.65 | U93: 46132
A94: 4175 | B94: 杏一 | C94: 生技醫療業 | D94: 55.5 | E94: 0.1 | F94: 0.18 | G94: '+-+-+ | H94: 0.72 | I94: 0 | J94: 8 | K94: 0.02 | L94: 55.32 | M94: 55.54 | N94: 55.4 | O94: 0 | P94: '--++- | Q94: 0 | R94: 0 | S94: 1 | T94: 12.5 | U94: 46132
A95: 3665 | B95: 貿聯-KY | C95: 其他電子業 | D95: 2460 | E95: 95 | F95: 4.02 | G95: '+++-+ | H95: 10.23 | I95: 1 | J95: 2601 | K95: 1.33 | L95: 2373 | M95: 2242.5 | N95: 2033.75 | O95: 182 | P95: '--+++ | Q95: 124 | R95: 6 | S95: 1014 | T95: 38.99 | U95: 46132
A96: 4905 | B96: 台聯電 | C96: 通信網路業 | D96: 85.5 | E96: -5.2 | F96: -5.73 | G96: '-++-- | H96: 6.32 | I96: 4 | J96: 146 | K96: 0.5 | L96: 86.2 | M96: 84.69 | N96: 85.02 | O96: 22 | P96: '+++-+ | Q96: 0 | R96: 0 | S96: 30 | T96: 20.55 | U96: 46132
A97: 4906 | B97: 正文 | C97: 通信網路業 | D97: 38.5 | E97: 0.75 | F97: 1.99 | G97: '-+--+ | H97: -5.16 | I97: 3 | J97: 34873 | K97: 7.89 | L97: 38.83 | M97: 39.09 | N97: 37.21 | O97: -858 | P97: '-+-+- | Q97: 47 | R97: -244 | S97: 17248 | T97: 49.46 | U97: 46132
... A106: 4961 | B106: 天鈺 | C106: 半導體業 | D106: 155.5 | E106: 2.5 | F106: 1.63 | G106: '+-+-+ | H106: 2.04 | I106: 0 | J106: 1366 | K106: 1.13 | L106: 153.7 | M106: 152.75 | N106: 149.35 | O106: -354 | P106: '+-+-- | Q106: -6 | R106: 9 | S106: 428 | T106: 31.33 | U106: 46132
A107: 1315 | B107: 達新 | C107: 塑膠工業 | D107: 65.7 | E107: 0.8 | F107: 1.23 | G107: '+-+++ | H107: 2.47 | I107: 0 | J107: 44 | K107: 0.04 | L107: 64.8 | M107: 64.5 | N107: 63.88 | O107: 14 | P107: '+++++ | Q107: 0 | R107: 0 | S107: 2 | T107: 4.55 | U107: 46132 | W107: 46136
A108: 6155 | B108: 鈞寶 | C108: 電子零組件業 | D108: 49.8 | E108: -0.8 | F108: -1.58 | G108: '--+-- | H108: -0.62 | I108: 1 | J108: 1906 | K108: 2.17 | L108: 50.3 | M108: 47.7 | N108: 46.02 | O108: 80 | P108: '--+-+ | Q108: 0 | R108: 0 | S108: 843 | T108: 44.23 | U108: 46132
...

Sheet 持股
A1: 是否開始抓取: | B1: 1
A2: 此頁面為目前我手上實際持股 要跟單的每天記得來看狀況 由於後臺每晚9點才會有整體資料 所以必須晚上10點之後來看 (前提是我有更新資料過來) | V2: WIN: | W2: https://winvest.tw/Stock/Symbol/Comment/2330
A3: 此頁面資料永不刪除 只會往下增長 太長會用隱藏方式摺疊 如果要看資料就自己展開 | R3: 一般獲利先抓20%
A4: 規則: | D4: 我買入價 | E4: 手續費+稅 | J4: 依據"題材股" | K4: 買日 | Q4: 賣日 | R4: 開WIN看 | S4: 開WIN看 | T4: 開WIN看 | U4: 開WIN看 | V4: 8ZZ指標 | W4: 開處置王看 | X4: 公告 這是每天要看的重點 有新公告就更新到財報去
A5: =IF(ISBLANK(B5), "", IFERROR(VLOOKUP(B5, STOCKS!A:W, 2, FALSE), "")) | B5: 範例用 | C5: =IFERROR(__xludf.DUMMYFUNCTION("IF(ISBLANK(B5), """", IF(ISBLANK($B$1), """", IMPORTXML('公式表'!$A$2&B5&'公式表'!$A$3, '公式表'!$A$13)))"),"#N/A") -> #N/A | E5: =IF(ISBLANK(D5),"",D5*1.01) | F5: =IF(ISBLANK(B5), "", (C5/D5)-1) -> #N/A | G5: =IF(ISBLANK(B5), "", IFERROR(VLOOKUP(B5, STOCKS!A:W, 10, FALSE), "")) | H5: =IF(ISBLANK(B5), "", IFERROR(VLOOKUP(B5, STOCKS!A:W, 11, FALSE), "")) | I5: =IF(ISBLANK(B5), "", IFERROR(VLOOKUP(B5, STOCKS!A:W, 20, FALSE), "")) | J5: =IF(ISBLANK(B5), "", IFERROR(VLOOKUP(B5, category!A:C, 3, FALSE), "")) | K5: 46078 | O5: =IF(ISBLANK(B5), "", (N5/D5)-1) -> #DIV/0! | Q5: 46078 | X5: =IF(ISBLANK(B5), "", IFERROR(VLOOKUP(B5, STOCKS!A:W, 22, FALSE), ""))
A6: 股票名稱 | B6: 代碼(手填) | C6: 收盤價 | D6: 買進股價 (手填) | E6: 平損價 (1%) | F6: 目前漲幅 | G6: 交易量 (Stock) | H6: 周轉率% (Stock) | I6: 當沖(%) (Stock) | J6: 題材分類 | K6: 買進日期 | L6: 目標價 | M6: 停損價 | N6: 最終 賣出價 | O6: 結算漲幅 | P6: 公式 | Q6: 賣出日期 | R6: EPS比去年同季 增長率(%)(手填) | S6: 最新合併財報 EPS(政府)(手填) | T6: 營收比上月 月增率(%)(手填) | U6: 營收比去年同月 月增率(%)(手填) | V6: 女神操作 (目前)(手填) | W6: 處置風險 (手填) | X6: 最新公告
A7: =IF(ISBLANK(B7), "", IFERROR(VLOOKUP(B7, STOCKS!A:W, 2, FALSE), "")) -> 鈞寶 | B7: 6155 | C7: =IFERROR(__xludf.DUMMYFUNCTION("IF(ISBLANK(B7), """", IF(ISBLANK($B$1), """", IMPORTXML('公式表'!$A$2&B7&'公式表'!$A$3, '公式表'!$A$13)))"),48.0) -> 48 | D7: 57.5 | E7: =IF(ISBLANK(D7),"",D7*1.01) -> 58.075 | F7: =IF(ISBLANK(B7), "", (C7/D7)-1) -> -0.16521739 | G7: =IF(ISBLANK(B7), "", IFERROR(VLOOKUP(B7, STOCKS!A:W, 10, FALSE), "")) -> 1906 | H7: =IF(ISBLANK(B7), "", IFERROR(VLOOKUP(B7, STOCKS!A:W, 11, FALSE), "")) -> 2.17 | I7: =IF(ISBLANK(B7), "", IFERROR(VLOOKUP(B7, STOCKS!A:W, 20, FALSE), "")) -> 44.23 | J7: =IF(ISBLANK(B7), "", IFERROR(VLOOKUP(B7, category!A:C, 3, FALSE), "")) -> 被動元件-MLCC | K7: 46043 | O7: =IF(ISBLANK(B7), "", (N7/D7)-1) -> -1 | P7: 紅綠 | X7: =IF(ISBLANK(B7), "", IFERROR(VLOOKUP(B7, STOCKS!A:W, 22, FALSE), ""))
A8: =IF(ISBLANK(B8), "", IFERROR(VLOOKUP(B8, STOCKS!A:W, 2, FALSE), "")) -> 南茂 | B8: 8150 | C8: =IFERROR(__xludf.DUMMYFUNCTION("IF(ISBLANK(B8), """", IF(ISBLANK($B$1), """", IMPORTXML('公式表'!$A$2&B8&'公式表'!$A$3, '公式表'!$A$13)))"),79.8) -> 79.8 | D8: 69.4 | E8: =IF(ISBLANK(D8),"",D8*1.01) -> 70.094 | F8: =IF(ISBLANK(B8), "", (C8/D8)-1) -> 0.14985591 | G8: =IF(ISBLANK(B8), "", IFERROR(VLOOKUP(B8, STOCKS!A:W, 10, FALSE), "")) -> 43671 | H8: =IF(ISBLANK(B8), "", IFERROR(VLOOKUP(B8, STOCKS!A:W, 11, FALSE), "")) -> 6.2 | I8: =IF(ISBLANK(B8), "", IFERROR(VLOOKUP(B8, STOCKS!A:W, 20, FALSE), "")) -> 52.36 | J8: =IF(ISBLANK(B8), "", IFERROR(VLOOKUP(B8, category!A:C, 3, FALSE), "")) -> 封測 | K8: 46043 | L8: 85 | O8: =IF(ISBLANK(B8), "", (N8/D8)-1) -> -1 | P8: 紅綠 | R8: 0.45 | S8: 0.71 | T8: 0.0395 | U8: 0.3123 | X8: =IF(ISBLANK(B8), "", IFERROR(VLOOKUP(B8, STOCKS!A:W, 22, FALSE), ""))
A9: =IF(ISBLANK(B9), "", IFERROR(VLOOKUP(B9, STOCKS!A:W, 2, FALSE), "")) -> 世界 | B9: 5347 | C9: =IFERROR(__xludf.DUMMYFUNCTION("IF(ISBLANK(B9), """", IF(ISBLANK($B$1), """", IMPORTXML('公式表'!$A$2&B9&'公式表'!$A$3, '公式表'!$A$13)))"),145.0) -> 145 | D9: 148.5 | E9: =IF(ISBLANK(D9),"",D9*1.01) -> 149.985 | F9: =IF(ISBLANK(B9), "", (C9/D9)-1) -> -0.023569024 | G9: =IF(ISBLANK(B9), "", IFERROR(VLOOKUP(B9, STOCKS!A:W, 10, FALSE), "")) -> 68635 | H9: =IF(ISBLANK(B9), "", IFERROR(VLOOKUP(B9, STOCKS!A:W, 11, FALSE), "")) -> 3.68 | I9: =IF(ISBLANK(B9), "", IFERROR(VLOOKUP(B9, STOCKS!A:W, 20, FALSE), "")) -> 53 | J9: =IF(ISBLANK(B9), "", IFERROR(VLOOKUP(B9, category!A:C, 3, FALSE), "")) | K9: 46043 | O9: =IF(ISBLANK(B9), "", (N9/D9)-1) -> -1 | P9: 紅綠 | X9: =IF(ISBLANK(B9), "", IFERROR(VLOOKUP(B9, STOCKS!A:W, 22, FALSE), ""))
A10: =IF(ISBLANK(B10), "", IFERROR(VLOOKUP(B10, STOCKS!A:W, 2, FALSE), "")) -> 華邦電 | B10: 2344 | C10: =IFERROR(__xludf.DUMMYFUNCTION("IF(ISBLANK(B10), """", IF(ISBLANK($B$1), """", IMPORTXML('公式表'!$A$2&B10&'公式表'!$A$3, '公式表'!$A$13)))"),90.6) -> 90.6 | D10: 130 | E10: =IF(ISBLANK(D10),"",D10*1.01) -> 131.3 | F10: =IF(ISBLANK(B10), "", (C10/D10)-1) -> -0.30307692 | G10: =IF(ISBLANK(B10), "", IFERROR(VLOOKUP(B10, STOCKS!A:W, 10, FALSE), "")) -> 164660 | H10: =IF(ISBLANK(B10), "", IFERROR(VLOOKUP(B10, STOCKS!A:W, 11, FALSE), "")) -> 3.66 | I10: =IF(ISBLANK(B10), "", IFERROR(VLOOKUP(B10, STOCKS!A:W, 20, FALSE), "")) -> 37.03 | J10: =IF(ISBLANK(B10), "", IFERROR(VLOOKUP(B10, category!A:C, 3, FALSE), "")) -> DIMM/DRAM | K10: 46052 | M10: 80 | N10: 89.5 | O10: =IF(ISBLANK(B10), "", (N10/D10)-1) -> -0.31153846 | P10: 紅綠 | V10: 已賣出 | X10: =IF(ISBLANK(B10), "", IFERROR(VLOOKUP(B10, STOCKS!A:W, 22, FALSE), ""))
A11: =IF(ISBLANK(B11), "", IFERROR(VLOOKUP(B11, STOCKS!A:W, 2, FALSE), "")) -> 景碩 | B11: 3189 | C11: =IFERROR(__xludf.DUMMYFUNCTION("IF(ISBLANK(B11), """", IF(ISBLANK($B$1), """", IMPORTXML('公式表'!$A$2&B11&'公式表'!$A$3, '公式表'!$A$13)))"),491.5) -> 491.5 | D11: 312.5 | E11: =IF(ISBLANK(D11),"",D11*1.01) -> 315.625 | F11: =IF(ISBLANK(B11), "", (C11/D11)-1) -> 0.5728 | G11: =IF(ISBLANK(B11), "", IFERROR(VLOOKUP(B11, STOCKS!A:W, 10, FALSE), "")) -> 33909 | H11: =IF(ISBLANK(B11), "", IFERROR(VLOOKUP(B11, STOCKS!A:W, 11, FALSE), "")) -> 6.44 | I11: =IF(ISBLANK(B11), "", IFERROR(VLOOKUP(B11, STOCKS!A:W, 20, FALSE), "")) -> 44.08 | J11: =IF(ISBLANK(B11), "", IFERROR(VLOOKUP(B11, category!A:C, 3, FALSE), "")) -> PCB/ABF載板 | K11: 46084 | N11: 348 | O11: =IF(ISBLANK(B11), "", (N11/D11)-1) -> 0.1136 | P11: 紅綠 | Q11: 46099 | X11: =IF(ISBLANK(B11), "", IFERROR(VLOOKUP(B11, STOCKS!A:W, 22, FALSE), ""))
A12: =IF(ISBLANK(B12), "", IFERROR(VLOOKUP(B12, STOCKS!A:W, 2, FALSE), "")) -> 元晶 | B12: 6443 | C12: =IFERROR(__xludf.DUMMYFUNCTION("IF(ISBLANK(B12), """", IF(ISBLANK($B$1), """", IMPORTXML('公式表'!$A$2&B12&'公式表'!$A$3, '公式表'!$A$13)))"),39.5) -> 39.5 | D12: 45.95 | E12: =IF(ISBLANK(D12),"",D12*1.01) -> 46.4095 | F12: =IF(ISBLANK(B12), "", (C12/D12)-1) -> -0.14036997 | G12: =IF(ISBLANK(B12), "", IFERROR(VLOOKUP(B12, STOCKS!A:W, 10, FALSE), "")) -> 7788 | H12: =IF(ISBLANK(B12), "", IFERROR(VLOOKUP(B12, STOCKS!A:W, 11, FALSE), "")) -> 1.52 | I12: =IF(ISBLANK(B12), "", IFERROR(VLOOKUP(B12, STOCKS!A:W, 20, FALSE), "")) -> 0 | J12: =IF(ISBLANK(B12), "", IFERROR(VLOOKUP(B12, category!A:C, 3, FALSE), "")) -> 低軌衛星 | K12: 46104 | N12: 41.3 | O12: =IF(ISBLANK(B12), "", (N12/D12)-1) -> -0.10119695 | P12: 紅綠 | Q12: 46114 | X12: =IF(ISBLANK(B12), "", IFERROR(VLOOKUP(B12, STOCKS!A:W, 22, FALSE), ""))
A13: =IF(ISBLANK(B13), "", IFERROR(VLOOKUP(B13, STOCKS!A:W, 2, FALSE), "")) -> 茂矽 | B13: 2342 | C13: =IFERROR(__xludf.DUMMYFUNCTION("IF(ISBLANK(B13), """", IF(ISBLANK($B$1), """", IMPORTXML('公式表'!$A$2&B13&'公式表'!$A$3, '公式表'!$A$13)))"),33.3) -> 33.3 | D13: 29 | E13: =IF(ISBLANK(D13),"",D13*1.01) -> 29.29 | F13: =IF(ISBLANK(B13), "", (C13/D13)-1) -> 0.14827586 | G13: =IF(ISBLANK(B13), "", IFERROR(VLOOKUP(B13, STOCKS!A:W, 10, FALSE), "")) -> 2493 | H13: =IF(ISBLANK(B13), "", IFERROR(VLOOKUP(B13, STOCKS!A:W, 11, FALSE), "")) -> 1.58 | I13: =IF(ISBLANK(B13), "", IFERROR(VLOOKUP(B13, STOCKS!A:W, 20, FALSE), "")) -> 37.87 | J13: =IF(ISBLANK(B13), "", IFERROR(VLOOKUP(B13, category!A:C, 3, FALSE), "")) -> 矽-sic | K13: 46125 | L13: 36 | O13: =IF(ISBLANK(B13), "", (N13/D13)-1) -> -1 | P13: 循環股 | X13: =IF(ISBLANK(B13), "", IFERROR(VLOOKUP(B13, STOCKS!A:W, 22, FALSE), ""))
A14: =IF(ISBLANK(B14), "", IFERROR(VLOOKUP(B14, STOCKS!A:W, 2, FALSE), "")) -> 大銀微系統 | B14: 4576 | C14: =IFERROR(__xludf.DUMMYFUNCTION("IF(ISBLANK(B14), """", IF(ISBLANK($B$1), """", IMPORTXML('公式表'!$A$2&B14&'公式表'!$A$3, '公式表'!$A$13)))"),198.0) -> 198 | D14: 189.5 | E14: =IF(ISBLANK(D14),"",D14*1.01) -> 191.395 | F14: =IF(ISBLANK(B14), "", (C14/D14)-1) -> 0.044854881 | G14: =IF(ISBLANK(B14), "", IFERROR(VLOOKUP(B14, STOCKS!A:W, 10, FALSE), "")) -> 1696 | H14: =IF(ISBLANK(B14), "", IFERROR(VLOOKUP(B14, STOCKS!A:W, 11, FALSE), "")) -> 1.42 | I14: =IF(ISBLANK(B14), "", IFERROR(VLOOKUP(B14, STOCKS!A:W, 20, FALSE), "")) -> 0 | J14: =IF(ISBLANK(B14), "", IFERROR(VLOOKUP(B14, category!A:C, 3, FALSE), "")) | K14: 46126 | L14: 1200 | O14: =IF(ISBLANK(B14), "", (N14/D14)-1) -> -1 | P14: 外部消息 | X14: =IF(ISBLANK(B14), "", IFERROR(VLOOKUP(B14, STOCKS!A:W, 22, FALSE), ""))

Sheet 紅綠
A1: 更新日期 | B1: 45951 | D1: Note: | E1: 請注意平日成交量
C2: 選股符合打V | D2: 參考 | G2: V | I2: 參考 | J2: V | K2: V | L2: 參考 | N2: 參考 | P2: V | S2: 參考
C3: 選股策略: | D3: <150 | G3: -- | I3: >=3 | J3: >2000 | K3: >5 SORT | L3: MA5逼近MA10 | N3: D<N | P3: 最後兩天++ | S3: >成交*50%
A4: ID | B4: Name | C4: Type | D4: 收盤價 | E4: 價差 | F4: 漲幅 (%) | G4: 五日+- | H4: 五日漲幅 (%) | I4: 漲停 歷史 | J4: 交易量 (張) | K4: 周轉率 (%) | L4: MA5 | M4: MA10 | N4: MA20 | O4: 外資 (張) | P4: 外資 五日+- | Q4: 投信 (張) | R4: 自營 (張) | S4: 當沖 (張) | T4: 當沖 (%) | U4: Date | V4: News | W4: ExDate
A5: 2485 | B5: 兆赫 | C5: 通信網路業 | D5: 71 | E5: -6.7 | F5: -8.62 | G5: '-+--- | H5: -12.44 | I5: 1 | J5: 39738 | K5: 12.51 | L5: 77.2 | M5: 75.63 | N5: 77.09 | O5: 390 | P5: -+--+ | Q5: 139 | R5: -601 | S5: 16965 | T5: 42.69 | U5: 46132
A6: 6127 | B6: 九豪 | C6: 電子零組件業 | D6: 48 | E6: -2.3 | F6: -4.57 | G6: '+-+-- | H6: 9.58 | I6: 2 | J6: 13193 | K6: 12.21 | L6: 49.03 | M6: 44.96 | N6: 43.7 | O6: -43 | P6: +-+-- | Q6: 0 | R6: -19 | S6: 3896 | T6: 29.53 | U6: 46132
A7: 1528 | B7: 恩德 | C7: 電機機械 | D7: 28.2 | E7: -1 | F7: -3.42 | G7: '++--- | H7: 3.63 | I7: 3 | J7: 17835 | K7: 9.32 | L7: 29.03 | M7: 28.08 | N7: 26.07 | O7: 374 | P7: ++-++ | Q7: -22 | R7: 4 | S7: 6903 | T7: 38.7 | U7: 46132
A8: 2367 | B8: 燿華 | C8: 電子零組件業 | D8: 65.6 | E8: -2.9 | F8: -4.23 | G8: '-+--- | H8: -11.85 | I8: 1 | J8: 61759 | K8: 8.74 | L8: 69.72 | M8: 72.11 | N8: 72.91 | O8: 6083 | P8: -+--+ | Q8: -431 | R8: -808 | S8: 24374 | T8: 39.47 | U8: 46132
A9: 2337 | B9: 旺宏 | C9: 半導體業 | D9: 120.5 | E9: -10.5 | F9: -8.02 | G9: '+---- | H9: -19.15 | I9: 2 | J9: 170786 | K9: 8.62 | L9: 137.6 | M9: 141 | N9: 137.47 | O9: 1245 | P9: +-+-+ | Q9: -5950 | R9: -482 | S9: 82406 | T9: 48.25 | U9: 46132

Sheet 紅綠-績優股
C1: 選股符合打V | D1: 參考 | G1: V | I1: 參考 | J1: V | K1: V | L1: 參考 | N1: 參考 | P1: V | S1: 參考 | V1: https://mops.twse.com.tw/mops/#/web/t05sr01_1
C2: 條件: | D2: <150 | G2: 為 - - | I2: >=3 | J2: >2000 | K2: >5 | L2: MA5逼近MA10 | N2: D<N | P2: 為 + + | S2: >成交*50%
A3: ID | B3: Name | C3: Type | D3: 收盤價 | E3: 價差 | F3: 漲幅(%) | G3: 五日+- | H3: 五日漲幅 (%) | I3: 漲停歷史 | J3: 交易量 (張) | K3: 周轉率 (%) | L3: MA5 | M3: MA10 | N3: MA20 | O3: 外資 (張) | P3: 外資 五日+- | Q3: 投信 (張) | R3: 自營 (張) | S3: 當沖 (張) | T3: 當沖 (%) | U3: Date | V3: 公告 | W3: 第 2 欄 | X3: 第 3 欄 | Y3: 第 4 欄 | Z3: 第 26 欄
A4: 1528 | B4: =IF(ISBLANK(A4), "", IFERROR(VLOOKUP(A4, STOCKS!A:W, 2, FALSE), "")) -> 恩德 | C4: =IF(ISBLANK(A4), "", IFERROR(VLOOKUP(A4, STOCKS!A:W, 3, FALSE), "")) -> 電機機械 | D4: =IF(ISBLANK(A4), "", IFERROR(VLOOKUP(A4, STOCKS!A:W, 4, FALSE), "")) -> 28.2 | E4: =IF(ISBLANK(A4), "", IFERROR(VLOOKUP(A4, STOCKS!A:W, 5, FALSE), "")) -> -1 | F4: =IF(ISBLANK(A4), "", IFERROR(VLOOKUP(A4, STOCKS!A:W, 6, FALSE), "")) -> -3.42 | G4: =IF(ISBLANK(A4), "", IFERROR(VLOOKUP(A4, STOCKS!A:W, 7, FALSE), "")) -> '++--- | H4: =IF(ISBLANK(A4), "", IFERROR(VLOOKUP(A4, STOCKS!A:W, 8, FALSE), "")) -> 3.63 | I4: =IF(ISBLANK(A4), "", IFERROR(VLOOKUP(A4, STOCKS!A:W, 9, FALSE), "")) -> 3 | J4: =IF(ISBLANK(A4), "", IFERROR(VLOOKUP(A4, STOCKS!A:W, 10, FALSE), "")) -> 17835 | K4: =IF(ISBLANK(A4), "", IFERROR(VLOOKUP(A4, STOCKS!A:W, 11, FALSE), "")) -> 9.32 | L4: =IF(ISBLANK(A4), "", IFERROR(VLOOKUP(A4, STOCKS!A:W, 12, FALSE), "")) -> 29.03 | M4: =IF(ISBLANK(A4), "", IFERROR(VLOOKUP(A4, STOCKS!A:W, 13, FALSE), "")) -> 28.08 | N4: =IF(ISBLANK(A4), "", IFERROR(VLOOKUP(A4, STOCKS!A:W, 14, FALSE), "")) -> 26.07 | O4: =IF(ISBLANK(A4), "", IFERROR(VLOOKUP(A4, STOCKS!A:W, 15, FALSE), "")) -> 374 | P4: =IF(ISBLANK(A4), "", IFERROR(VLOOKUP(A4, STOCKS!A:W, 16, FALSE), "")) -> '++-++ | Q4: =IF(ISBLANK(A4), "", IFERROR(VLOOKUP(A4, STOCKS!A:W, 17, FALSE), "")) -> -22 | R4: =IF(ISBLANK(A4), "", IFERROR(VLOOKUP(A4, STOCKS!A:W, 18, FALSE), "")) -> 4 | S4: =IF(ISBLANK(A4), "", IFERROR(VLOOKUP(A4, STOCKS!A:W, 19, FALSE), "")) -> 6903 | T4: =IF(ISBLANK(A4), "", IFERROR(VLOOKUP(A4, STOCKS!A:W, 20, FALSE), "")) -> 38.7 | U4: =IF(ISBLANK(A4), "", IFERROR(VLOOKUP(A4, STOCKS!A:W, 21, FALSE), "")) -> 46132 | V4: =IF(ISBLANK(A4), "", IFERROR(VLOOKUP(A4, STOCKS!A:W, 22, FALSE), ""))
A5: 1569 | B5: =IF(ISBLANK(A5), "", IFERROR(VLOOKUP(A5, STOCKS!A:W, 2, FALSE), "")) -> 濱川 | C5: =IF(ISBLANK(A5), "", IFERROR(VLOOKUP(A5, STOCKS!A:W, 3, FALSE), "")) -> 電腦及週邊設備業 | D5: =IF(ISBLANK(A5), "", IFERROR(VLOOKUP(A5, STOCKS!A:W, 4, FALSE), "")) -> 52.3 | E5: =IF(ISBLANK(A5), "", IFERROR(VLOOKUP(A5, STOCKS!A:W, 5, FALSE), "")) -> -0.2 | F5: =IF(ISBLANK(A5), "", IFERROR(VLOOKUP(A5, STOCKS!A:W, 6, FALSE), "")) -> -0.38 | G5: =IF(ISBLANK(A5), "", IFERROR(VLOOKUP(A5, STOCKS!A:W, 7, FALSE), "")) -> '----- | H5: =IF(ISBLANK(A5), "", IFERROR(VLOOKUP(A5, STOCKS!A:W, 8, FALSE), "")) -> -5.89 | I5: =IF(ISBLANK(A5), "", IFERROR(VLOOKUP(A5, STOCKS!A:W, 9, FALSE), "")) -> 1 | J5: =IF(ISBLANK(A5), "", IFERROR(VLOOKUP(A5, STOCKS!A:W, 10, FALSE), "")) -> 815 | K5: =IF(ISBLANK(A5), "", IFERROR(VLOOKUP(A5, STOCKS!A:W, 11, FALSE), "")) -> 0.57 | L5: =IF(ISBLANK(A5), "", IFERROR(VLOOKUP(A5, STOCKS!A:W, 12, FALSE), "")) -> 53.14 | M5: =IF(ISBLANK(A5), "", IFERROR(VLOOKUP(A5, STOCKS!A:W, 13, FALSE), "")) -> 53.12 | N5: =IF(ISBLANK(A5), "", IFERROR(VLOOKUP(A5, STOCKS!A:W, 14, FALSE), "")) -> 51.56 | O5: =IF(ISBLANK(A5), "", IFERROR(VLOOKUP(A5, STOCKS!A:W, 15, FALSE), "")) -> 38 | P5: =IF(ISBLANK(A5), "", IFERROR(VLOOKUP(A5, STOCKS!A:W, 16, FALSE), "")) -> '----+ | Q5: =IF(ISBLANK(A5), "", IFERROR(VLOOKUP(A5, STOCKS!A:W, 17, FALSE), "")) -> 0 | R5: =IF(ISBLANK(A5), "", IFERROR(VLOOKUP(A5, STOCKS!A:W, 18, FALSE), "")) -> 0 | S5: =IF(ISBLANK(A5), "", IFERROR(VLOOKUP(A5, STOCKS!A:W, 19, FALSE), "")) -> 163 | T5: =IF(ISBLANK(A5), "", IFERROR(VLOOKUP(A5, STOCKS!A:W, 20, FALSE), "")) -> 20 | U5: =IF(ISBLANK(A5), "", IFERROR(VLOOKUP(A5, STOCKS!A:W, 21, FALSE), "")) -> 46132 | V5: =IF(ISBLANK(A5), "", IFERROR(VLOOKUP(A5, STOCKS!A:W, 22, FALSE), ""))
A6: 2615 | B6: =IF(ISBLANK(A6), "", IFERROR(VLOOKUP(A6, STOCKS!A:W, 2, FALSE), "")) -> 萬海 | C6: =IF(ISBLANK(A6), "", IFERROR(VLOOKUP(A6, STOCKS!A:W, 3, FALSE), "")) -> 航運業 | D6: =IF(ISBLANK(A6), "", IFERROR(VLOOKUP(A6, STOCKS!A:W, 4, FALSE), "")) -> 73.7 | E6: =IF(ISBLANK(A6), "", IFERROR(VLOOKUP(A6, STOCKS!A:W, 5, FALSE), "")) -> -1.6 | F6: =IF(ISBLANK(A6), "", IFERROR(VLOOKUP(A6, STOCKS!A:W, 6, FALSE), "")) -> -2.12 | G6: =IF(ISBLANK(A6), "", IFERROR(VLOOKUP(A6, STOCKS!A:W, 7, FALSE), "")) -> '-+--- | H6: =IF(ISBLANK(A6), "", IFERROR(VLOOKUP(A6, STOCKS!A:W, 8, FALSE), "")) -> -3.65 | I6: =IF(ISBLANK(A6), "", IFERROR(VLOOKUP(A6, STOCKS!A:W, 9, FALSE), "")) -> 0 | J6: =IF(ISBLANK(A6), "", IFERROR(VLOOKUP(A6, STOCKS!A:W, 10, FALSE), "")) -> 8584 | K6: =IF(ISBLANK(A6), "", IFERROR(VLOOKUP(A6, STOCKS!A:W, 11, FALSE), "")) -> 0.31 | L6: =IF(ISBLANK(A6), "", IFERROR(VLOOKUP(A6, STOCKS!A:W, 12, FALSE), "")) -> 75.94 | M6: =IF(ISBLANK(A6), "", IFERROR(VLOOKUP(A6, STOCKS!A:W, 13, FALSE), "")) -> 76.98 | N6: =IF(ISBLANK(A6), "", IFERROR(VLOOKUP(A6, STOCKS!A:W, 14, FALSE), "")) -> 76.79 | O6: =IF(ISBLANK(A6), "", IFERROR(VLOOKUP(A6, STOCKS!A:W, 15, FALSE), "")) -> -1134 | P6: =IF(ISBLANK(A6), "", IFERROR(VLOOKUP(A6, STOCKS!A:W, 16, FALSE), "")) -> '+++-- | Q6: =IF(ISBLANK(A6), "", IFERROR(VLOOKUP(A6, STOCKS!A:W, 17, FALSE), "")) -> -490 | R6: =IF(ISBLANK(A6), "", IFERROR(VLOOKUP(A6, STOCKS!A:W, 18, FALSE), "")) -> -58 | S6: =IF(ISBLANK(A6), "", IFERROR(VLOOKUP(A6, STOCKS!A:W, 19, FALSE), "")) -> 1552 | T6: =IF(ISBLANK(A6), "", IFERROR(VLOOKUP(A6, STOCKS!A:W, 20, FALSE), "")) -> 18.08 | U6: =IF(ISBLANK(A6), "", IFERROR(VLOOKUP(A6, STOCKS!A:W, 21, FALSE), "")) -> 46132 | V6: =IF(ISBLANK(A6), "", IFERROR(VLOOKUP(A6, STOCKS!A:W, 22, FALSE), ""))
A7: 2316 | B7: =IF(ISBLANK(A7), "", IFERROR(VLOOKUP(A7, STOCKS!A:W, 2, FALSE), "")) -> 楠梓電 | C7: =IF(ISBLANK(A7), "", IFERROR(VLOOKUP(A7, STOCKS!A:W, 3, FALSE), "")) -> 電子零組件業 | D7: =IF(ISBLANK(A7), "", IFERROR(VLOOKUP(A7, STOCKS!A:W, 4, FALSE), "")) -> 112 | E7: =IF(ISBLANK(A7), "", IFERROR(VLOOKUP(A7, STOCKS!A:W, 5, FALSE), "")) -> -2.5 | F7: =IF(ISBLANK(A7), "", IFERROR(VLOOKUP(A7, STOCKS!A:W, 6, FALSE), "")) -> -2.18 | G7: =IF(ISBLANK(A7), "", IFERROR(VLOOKUP(A7, STOCKS!A:W, 7, FALSE), "")) -> '+---- | H7: =IF(ISBLANK(A7), "", IFERROR(VLOOKUP(A7, STOCKS!A:W, 8, FALSE), "")) -> -0.71 | I7: =IF(ISBLANK(A7), "", IFERROR(VLOOKUP(A7, STOCKS!A:W, 9, FALSE), "")) -> 2 | J7: =IF(ISBLANK(A7), "", IFERROR(VLOOKUP(A7, STOCKS!A:W, 10, FALSE), "")) -> 8250 | K7: =IF(ISBLANK(A7), "", IFERROR(VLOOKUP(A7, STOCKS!A:W, 11, FALSE), "")) -> 4.51 | L7: =IF(ISBLANK(A7), "", IFERROR(VLOOKUP(A7, STOCKS!A:W, 12, FALSE), "")) -> 115 | M7: =IF(ISBLANK(A7), "", IFERROR(VLOOKUP(A7, STOCKS!A:W, 13, FALSE), "")) -> 110.42 | N7: =IF(ISBLANK(A7), "", IFERROR(VLOOKUP(A7, STOCKS!A:W, 14, FALSE), "")) -> 106.35 | O7: =IF(ISBLANK(A7), "", IFERROR(VLOOKUP(A7, STOCKS!A:W, 15, FALSE), "")) -> -2343 | P7: =IF(ISBLANK(A7), "", IFERROR(VLOOKUP(A7, STOCKS!A:W, 16, FALSE), "")) -> '--+-- | Q7: =IF(ISBLANK(A7), "", IFERROR(VLOOKUP(A7, STOCKS!A:W, 17, FALSE), "")) -> -56 | R7: =IF(ISBLANK(A7), "", IFERROR(VLOOKUP(A7, STOCKS!A:W, 18, FALSE), "")) -> -99 | S7: =IF(ISBLANK(A7), "", IFERROR(VLOOKUP(A7, STOCKS!A:W, 19, FALSE), "")) -> 3276 | T7: =IF(ISBLANK(A7), "", IFERROR(VLOOKUP(A7, STOCKS!A:W, 20, FALSE), "")) -> 39.71 | U7: =IF(ISBLANK(A7), "", IFERROR(VLOOKUP(A7, STOCKS!A:W, 21, FALSE), "")) -> 46132 | V7: =IF(ISBLANK(A7), "", IFERROR(VLOOKUP(A7, STOCKS!A:W, 22, FALSE), ""))
A8: 3379 | B8: =IF(ISBLANK(A8), "", IFERROR(VLOOKUP(A8, STOCKS!A:W, 2, FALSE), "")) -> 彬台 | C8: =IF(ISBLANK(A8), "", IFERROR(VLOOKUP(A8, STOCKS!A:W, 3, FALSE), "")) -> 電機機械 | D8: =IF(ISBLANK(A8), "", IFERROR(VLOOKUP(A8, STOCKS!A:W, 4, FALSE), "")) -> 37.8 | E8: =IF(ISBLANK(A8), "", IFERROR(VLOOKUP(A8, STOCKS!A:W, 5, FALSE), "")) -> 0.5 | F8: =IF(ISBLANK(A8), "", IFERROR(VLOOKUP(A8, STOCKS!A:W, 6, FALSE), "")) -> 1.34 | G8: =IF(ISBLANK(A8), "", IFERROR(VLOOKUP(A8, STOCKS!A:W, 7, FALSE), "")) -> '+++++ | H8: =IF(ISBLANK(A8), "", IFERROR(VLOOKUP(A8, STOCKS!A:W, 8, FALSE), "")) -> 7.38 | I8: =IF(ISBLANK(A8), "", IFERROR(VLOOKUP(A8, STOCKS!A:W, 9, FALSE), "")) -> 0 | J8: =IF(ISBLANK(A8), "", IFERROR(VLOOKUP(A8, STOCKS!A:W, 10, FALSE), "")) -> 307 | K8: =IF(ISBLANK(A8), "", IFERROR(VLOOKUP(A8, STOCKS!A:W, 11, FALSE), "")) -> 0.81 | L8: =IF(ISBLANK(A8), "", IFERROR(VLOOKUP(A8, STOCKS!A:W, 12, FALSE), "")) -> 37.21 | M8: =IF(ISBLANK(A8), "", IFERROR(VLOOKUP(A8, STOCKS!A:W, 13, FALSE), "")) -> 37.01 | N8: =IF(ISBLANK(A8), "", IFERROR(VLOOKUP(A8, STOCKS!A:W, 14, FALSE), "")) -> 37.47 | O8: =IF(ISBLANK(A8), "", IFERROR(VLOOKUP(A8, STOCKS!A:W, 15, FALSE), "")) -> 60 | P8: =IF(ISBLANK(A8), "", IFERROR(VLOOKUP(A8, STOCKS!A:W, 16, FALSE), "")) -> '+-+++ | Q8: =IF(ISBLANK(A8), "", IFERROR(VLOOKUP(A8, STOCKS!A:W, 17, FALSE), "")) -> 0 | R8: =IF(ISBLANK(A8), "", IFERROR(VLOOKUP(A8, STOCKS!A:W, 18, FALSE), "")) -> -11 | S8: =IF(ISBLANK(A8), "", IFERROR(VLOOKUP(A8, STOCKS!A:W, 19, FALSE), "")) -> 73 | T8: =IF(ISBLANK(A8), "", IFERROR(VLOOKUP(A8, STOCKS!A:W, 20, FALSE), "")) -> 23.78 | U8: =IF(ISBLANK(A8), "", IFERROR(VLOOKUP(A8, STOCKS!A:W, 21, FALSE), "")) -> 46132 | V8: =IF(ISBLANK(A8), "", IFERROR(VLOOKUP(A8, STOCKS!A:W, 22, FALSE), ""))
A9: 3528 | B9: =IF(ISBLANK(A9), "", IFERROR(VLOOKUP(A9, STOCKS!A:W, 2, FALSE), "")) -> 安馳 | C9: =IF(ISBLANK(A9), "", IFERROR(VLOOKUP(A9, STOCKS!A:W, 3, FALSE), "")) -> 電子通路業 | D9: =IF(ISBLANK(A9), "", IFERROR(VLOOKUP(A9, STOCKS!A:W, 4, FALSE), "")) -> 72 | E9: =IF(ISBLANK(A9), "", IFERROR(VLOOKUP(A9, STOCKS!A:W, 5, FALSE), "")) -> -0.3 | F9: =IF(ISBLANK(A9), "", IFERROR(VLOOKUP(A9, STOCKS!A:W, 6, FALSE), "")) -> -0.41 | G9: =IF(ISBLANK(A9), "", IFERROR(VLOOKUP(A9, STOCKS!A:W, 7, FALSE), "")) -> '+--+- | H9: =IF(ISBLANK(A9), "", IFERROR(VLOOKUP(A9, STOCKS!A:W, 8, FALSE), "")) -> 2.74 | I9: =IF(ISBLANK(A9), "", IFERROR(VLOOKUP(A9, STOCKS!A:W, 9, FALSE), "")) -> 0 | J9: =IF(ISBLANK(A9), "", IFERROR(VLOOKUP(A9, STOCKS!A:W, 10, FALSE), "")) -> 264 | K9: =IF(ISBLANK(A9), "", IFERROR(VLOOKUP(A9, STOCKS!A:W, 11, FALSE), "")) -> 0.4 | L9: =IF(ISBLANK(A9), "", IFERROR(VLOOKUP(A9, STOCKS!A:W, 12, FALSE), "")) -> 71.3 | M9: =IF(ISBLANK(A9), "", IFERROR(VLOOKUP(A9, STOCKS!A:W, 13, FALSE), "")) -> 69.43 | N9: =IF(ISBLANK(A9), "", IFERROR(VLOOKUP(A9, STOCKS!A:W, 14, FALSE), "")) -> 66.32 | O9: =IF(ISBLANK(A9), "", IFERROR(VLOOKUP(A9, STOCKS!A:W, 15, FALSE), "")) -> -48 | P9: =IF(ISBLANK(A9), "", IFERROR(VLOOKUP(A9, STOCKS!A:W, 16, FALSE), "")) -> '++++- | Q9: =IF(ISBLANK(A9), "", IFERROR(VLOOKUP(A9, STOCKS!A:W, 17, FALSE), "")) -> 0 | R9: =IF(ISBLANK(A9), "", IFERROR(VLOOKUP(A9, STOCKS!A:W, 18, FALSE), "")) -> 0 | S9: =IF(ISBLANK(A9), "", IFERROR(VLOOKUP(A9, STOCKS!A:W, 19, FALSE), "")) -> 39 | T9: =IF(ISBLANK(A9), "", IFERROR(VLOOKUP(A9, STOCKS!A:W, 20, FALSE), "")) -> 14.77 | U9: =IF(ISBLANK(A9), "", IFERROR(VLOOKUP(A9, STOCKS!A:W, 21, FALSE), "")) -> 46132 | V9: =IF(ISBLANK(A9), "", IFERROR(VLOOKUP(A9, STOCKS!A:W, 22, FALSE), ""))
A10: 3645 | B10: =IF(ISBLANK(A10), "", IFERROR(VLOOKUP(A10, STOCKS!A:W, 2, FALSE), "")) -> 達邁 | C10: =IF(ISBLANK(A10), "", IFERROR(VLOOKUP(A10, STOCKS!A:W, 3, FALSE), "")) -> 電子零組件業 | D10: =IF(ISBLANK(A10), "", IFERROR(VLOOKUP(A10, STOCKS!A:W, 4, FALSE), "")) -> 114.5 | E10: =IF(ISBLANK(A10), "", IFERROR(VLOOKUP(A10, STOCKS!A:W, 5, FALSE), "")) -> 10 | F10: =IF(ISBLANK(A10), "", IFERROR(VLOOKUP(A10, STOCKS!A:W, 6, FALSE), "")) -> 9.57 | G10: =IF(ISBLANK(A10), "", IFERROR(VLOOKUP(A10, STOCKS!A:W, 7, FALSE), "")) -> '-++++ | H10: =IF(ISBLANK(A10), "", IFERROR(VLOOKUP(A10, STOCKS!A:W, 8, FALSE), "")) -> 24.55 | I10: =IF(ISBLANK(A10), "", IFERROR(VLOOKUP(A10, STOCKS!A:W, 9, FALSE), "")) -> 4 | J10: =IF(ISBLANK(A10), "", IFERROR(VLOOKUP(A10, STOCKS!A:W, 10, FALSE), "")) -> 19720 | K10: =IF(ISBLANK(A10), "", IFERROR(VLOOKUP(A10, STOCKS!A:W, 11, FALSE), "")) -> 14.42 | L10: =IF(ISBLANK(A10), "", IFERROR(VLOOKUP(A10, STOCKS!A:W, 12, FALSE), "")) -> 100.38 | M10: =IF(ISBLANK(A10), "", IFERROR(VLOOKUP(A10, STOCKS!A:W, 13, FALSE), "")) -> 89.52 | N10: =IF(ISBLANK(A10), "", IFERROR(VLOOKUP(A10, STOCKS!A:W, 14, FALSE), "")) -> 82.4 | O10: =IF(ISBLANK(A10), "", IFERROR(VLOOKUP(A10, STOCKS!A:W, 15, FALSE), "")) -> -1499 | P10: =IF(ISBLANK(A10), "", IFERROR(VLOOKUP(A10, STOCKS!A:W, 16, FALSE), "")) -> '+---- | Q10: =IF(ISBLANK(A10), "", IFERROR(VLOOKUP(A10, STOCKS!A:W, 17, FALSE), "")) -> 0 | R10: =IF(ISBLANK(A10), "", IFERROR(VLOOKUP(A10, STOCKS!A:W, 18, FALSE), "")) -> 117 | S10: =IF(ISBLANK(A10), "", IFERROR(VLOOKUP(A10, STOCKS!A:W, 19, FALSE), "")) -> 9410 | T10: =IF(ISBLANK(A10), "", IFERROR(VLOOKUP(A10, STOCKS!A:W, 20, FALSE), "")) -> 47.72 | U10: =IF(ISBLANK(A10), "", IFERROR(VLOOKUP(A10, STOCKS!A:W, 21, FALSE), "")) -> 46132 | V10: =IF(ISBLANK(A10), "", IFERROR(VLOOKUP(A10, STOCKS!A:W, 22, FALSE), ""))
A11: 3709 | B11: =IF(ISBLANK(A11), "", IFERROR(VLOOKUP(A11, STOCKS!A:W, 2, FALSE), "")) -> 鑫聯大投控 | C11: =IF(ISBLANK(A11), "", IFERROR(VLOOKUP(A11, STOCKS!A:W, 3, FALSE), "")) -> 電腦及週邊設備業 | D11: =IF(ISBLANK(A11), "", IFERROR(VLOOKUP(A11, STOCKS!A:W, 4, FALSE), "")) -> 70.3 | E11: =IF(ISBLANK(A11), "", IFERROR(VLOOKUP(A11, STOCKS!A:W, 5, FALSE), "")) -> -1 | F11: =IF(ISBLANK(A11), "", IFERROR(VLOOKUP(A11, STOCKS!A:W, 6, FALSE), "")) -> -1.4 | G11: =IF(ISBLANK(A11), "", IFERROR(VLOOKUP(A11, STOCKS!A:W, 7, FALSE), "")) -> '+--+- | H11: =IF(ISBLANK(A11), "", IFERROR(VLOOKUP(A11, STOCKS!A:W, 8, FALSE), "")) -> 2.79 | I11: =IF(ISBLANK(A11), "", IFERROR(VLOOKUP(A11, STOCKS!A:W, 9, FALSE), "")) -> 0 | J11: =IF(ISBLANK(A11), "", IFERROR(VLOOKUP(A11, STOCKS!A:W, 10, FALSE), "")) -> 2732 | K11: =IF(ISBLANK(A11), "", IFERROR(VLOOKUP(A11, STOCKS!A:W, 11, FALSE), "")) -> 2.18 | L11: =IF(ISBLANK(A11), "", IFERROR(VLOOKUP(A11, STOCKS!A:W, 12, FALSE), "")) -> 71.12 | M11: =IF(ISBLANK(A11), "", IFERROR(VLOOKUP(A11, STOCKS!A:W, 13, FALSE), "")) -> 69.48 | N11: =IF(ISBLANK(A11), "", IFERROR(VLOOKUP(A11, STOCKS!A:W, 14, FALSE), "")) -> 67.94 | O11: =IF(ISBLANK(A11), "", IFERROR(VLOOKUP(A11, STOCKS!A:W, 15, FALSE), "")) -> -672 | P11: =IF(ISBLANK(A11), "", IFERROR(VLOOKUP(A11, STOCKS!A:W, 16, FALSE), "")) -> '+--+- | Q11: =IF(ISBLANK(A11), "", IFERROR(VLOOKUP(A11, STOCKS!A:W, 17, FALSE), "")) -> 0 | R11: =IF(ISBLANK(A11), "", IFERROR(VLOOKUP(A11, STOCKS!A:W, 18, FALSE), "")) -> -2 | S11: =IF(ISBLANK(A11), "", IFERROR(VLOOKUP(A11, STOCKS!A:W, 19, FALSE), "")) -> 1063 | T11: =IF(ISBLANK(A11), "", IFERROR(VLOOKUP(A11, STOCKS!A:W, 20, FALSE), "")) -> 38.91 | U11: =IF(ISBLANK(A11), "", IFERROR(VLOOKUP(A11, STOCKS!A:W, 21, FALSE), "")) -> 46132 | V11: =IF(ISBLANK(A11), "", IFERROR(VLOOKUP(A11, STOCKS!A:W, 22, FALSE), "")) -> 公告本公司董事會決議修訂115年股東常會召集事由 (修訂其他事項)
A12: 4541 | B12: =IF(ISBLANK(A12), "", IFERROR(VLOOKUP(A12, STOCKS!A:W, 2, FALSE), "")) -> 晟田 | C12: =IF(ISBLANK(A12), "", IFERROR(VLOOKUP(A12, STOCKS!A:W, 3, FALSE), "")) -> 其他業 | D12: =IF(ISBLANK(A12), "", IFERROR(VLOOKUP(A12, STOCKS!A:W, 4, FALSE), "")) -> 49.35 | E12: =IF(ISBLANK(A12), "", IFERROR(VLOOKUP(A12, STOCKS!A:W, 5, FALSE), "")) -> 1.05 | F12: =IF(ISBLANK(A12), "", IFERROR(VLOOKUP(A12, STOCKS!A:W, 6, FALSE), "")) -> 2.17 | G12: =IF(ISBLANK(A12), "", IFERROR(VLOOKUP(A12, STOCKS!A:W, 7, FALSE), "")) -> '+-+++ | H12: =IF(ISBLANK(A12), "", IFERROR(VLOOKUP(A12, STOCKS!A:W, 8, FALSE), "")) -> 6.37 | I12: =IF(ISBLANK(A12), "", IFERROR(VLOOKUP(A12, STOCKS!A:W, 9, FALSE), "")) -> 1 | J12: =IF(ISBLANK(A12), "", IFERROR(VLOOKUP(A12, STOCKS!A:W, 10, FALSE), "")) -> 3379 | K12: =IF(ISBLANK(A12), "", IFERROR(VLOOKUP(A12, STOCKS!A:W, 11, FALSE), "")) -> 5 | L12: =IF(ISBLANK(A12), "", IFERROR(VLOOKUP(A12, STOCKS!A:W, 12, FALSE), "")) -> 47.72 | M12: =IF(ISBLANK(A12), "", IFERROR(VLOOKUP(A12, STOCKS!A:W, 13, FALSE), "")) -> 45.71 | N12: =IF(ISBLANK(A12), "", IFERROR(VLOOKUP(A12, STOCKS!A:W, 14, FALSE), "")) -> 43.71 | O12: =IF(ISBLANK(A12), "", IFERROR(VLOOKUP(A12, STOCKS!A:W, 15, FALSE), "")) -> 438 | P12: =IF(ISBLANK(A12), "", IFERROR(VLOOKUP(A12, STOCKS!A:W, 16, FALSE), "")) -> '+++++ | Q12: =IF(ISBLANK(A12), "", IFERROR(VLOOKUP(A12, STOCKS!A:W, 17, FALSE), "")) -> 0 | R12: =IF(ISBLANK(A12), "", IFERROR(VLOOKUP(A12, STOCKS!A:W, 18, FALSE), "")) -> 2 | S12: =IF(ISBLANK(A12), "", IFERROR(VLOOKUP(A12, STOCKS!A:W, 19, FALSE), "")) -> 1176 | T12: =IF(ISBLANK(A12), "", IFERROR(VLOOKUP(A12, STOCKS!A:W, 20, FALSE), "")) -> 34.8 | U12: =IF(ISBLANK(A12), "", IFERROR(VLOOKUP(A12, STOCKS!A:W, 21, FALSE), "")) -> 46132 | V12: =IF(ISBLANK(A12), "", IFERROR(VLOOKUP(A12, STOCKS!A:W, 22, FALSE), ""))
A13: 5201 | B13: =IF(ISBLANK(A13), "", IFERROR(VLOOKUP(A13, STOCKS!A:W, 2, FALSE), "")) -> 凱衛 | C13: =IF(ISBLANK(A13), "", IFERROR(VLOOKUP(A13, STOCKS!A:W, 3, FALSE), "")) -> 資訊服務業 | D13: =IF(ISBLANK(A13), "", IFERROR(VLOOKUP(A13, STOCKS!A:W, 4, FALSE), "")) -> 37.15 | E13: =IF(ISBLANK(A13), "", IFERROR(VLOOKUP(A13, STOCKS!A:W, 5, FALSE), "")) -> -1.95 | F13: =IF(ISBLANK(A13), "", IFERROR(VLOOKUP(A13, STOCKS!A:W, 6, FALSE), "")) -> -4.99 | G13: =IF(ISBLANK(A13), "", IFERROR(VLOOKUP(A13, STOCKS!A:W, 7, FALSE), "")) -> '++--- | H13: =IF(ISBLANK(A13), "", IFERROR(VLOOKUP(A13, STOCKS!A:W, 8, FALSE), "")) -> -4.21 | I13: =IF(ISBLANK(A13), "", IFERROR(VLOOKUP(A13, STOCKS!A:W, 9, FALSE), "")) -> 0 | J13: =IF(ISBLANK(A13), "", IFERROR(VLOOKUP(A13, STOCKS!A:W, 10, FALSE), "")) -> 237 | K13: =IF(ISBLANK(A13), "", IFERROR(VLOOKUP(A13, STOCKS!A:W, 11, FALSE), "")) -> 0.61 | L13: =IF(ISBLANK(A13), "", IFERROR(VLOOKUP(A13, STOCKS!A:W, 12, FALSE), "")) -> 38.86 | M13: =IF(ISBLANK(A13), "", IFERROR(VLOOKUP(A13, STOCKS!A:W, 13, FALSE), "")) -> 38.87 | N13: =IF(ISBLANK(A13), "", IFERROR(VLOOKUP(A13, STOCKS!A:W, 14, FALSE), "")) -> 39.08 | O13: =IF(ISBLANK(A13), "", IFERROR(VLOOKUP(A13, STOCKS!A:W, 15, FALSE), "")) -> -102 | P13: =IF(ISBLANK(A13), "", IFERROR(VLOOKUP(A13, STOCKS!A:W, 16, FALSE), "")) -> '----- | Q13: =IF(ISBLANK(A13), "", IFERROR(VLOOKUP(A13, STOCKS!A:W, 17, FALSE), "")) -> 0 | R13: =IF(ISBLANK(A13), "", IFERROR(VLOOKUP(A13, STOCKS!A:W, 18, FALSE), "")) -> 0 | S13: =IF(ISBLANK(A13), "", IFERROR(VLOOKUP(A13, STOCKS!A:W, 19, FALSE), "")) -> 29 | T13: =IF(ISBLANK(A13), "", IFERROR(VLOOKUP(A13, STOCKS!A:W, 20, FALSE), "")) -> 12.24 | U13: =IF(ISBLANK(A13), "", IFERROR(VLOOKUP(A13, STOCKS!A:W, 21, FALSE), "")) -> 46132 | V13: =IF(ISBLANK(A13), "", IFERROR(VLOOKUP(A13, STOCKS!A:W, 22, FALSE), ""))
A14: 1721 | B14: =IF(ISBLANK(A14), "", IFERROR(VLOOKUP(A14, STOCKS!A:W, 2, FALSE), "")) -> 三晃 | C14: =IF(ISBLANK(A14), "", IFERROR(VLOOKUP(A14, STOCKS!A:W, 3, FALSE), "")) -> 化學工業 | D14: =IF(ISBLANK(A14), "", IFERROR(VLOOKUP(A14, STOCKS!A:W, 4, FALSE), "")) -> 22.55 | E14: =IF(ISBLANK(A14), "", IFERROR(VLOOKUP(A14, STOCKS!A:W, 5, FALSE), "")) -> 2.05 | F14: =IF(ISBLANK(A14), "", IFERROR(VLOOKUP(A14, STOCKS!A:W, 6, FALSE), "")) -> 10 | G14: =IF(ISBLANK(A14), "", IFERROR(VLOOKUP(A14, STOCKS!A:W, 7, FALSE), "")) -> '+--++ | H14: =IF(ISBLANK(A14), "", IFERROR(VLOOKUP(A14, STOCKS!A:W, 8, FALSE), "")) -> 22.94 | I14: =IF(ISBLANK(A14), "", IFERROR(VLOOKUP(A14, STOCKS!A:W, 9, FALSE), "")) -> 3 | J14: =IF(ISBLANK(A14), "", IFERROR(VLOOKUP(A14, STOCKS!A:W, 10, FALSE), "")) -> 6786 | K14: =IF(ISBLANK(A14), "", IFERROR(VLOOKUP(A14, STOCKS!A:W, 11, FALSE), "")) -> 3.67 | L14: =IF(ISBLANK(A14), "", IFERROR(VLOOKUP(A14, STOCKS!A:W, 12, FALSE), "")) -> 20.2 | M14: =IF(ISBLANK(A14), "", IFERROR(VLOOKUP(A14, STOCKS!A:W, 13, FALSE), "")) -> 18.86 | N14: =IF(ISBLANK(A14), "", IFERROR(VLOOKUP(A14, STOCKS!A:W, 14, FALSE), "")) -> 18.47 | O14: =IF(ISBLANK(A14), "", IFERROR(VLOOKUP(A14, STOCKS!A:W, 15, FALSE), "")) -> 640 | P14: =IF(ISBLANK(A14), "", IFERROR(VLOOKUP(A14, STOCKS!A:W, 16, FALSE), "")) -> '++-++ | Q14: =IF(ISBLANK(A14), "", IFERROR(VLOOKUP(A14, STOCKS!A:W, 17, FALSE), "")) -> 0 | R14: =IF(ISBLANK(A14), "", IFERROR(VLOOKUP(A14, STOCKS!A:W, 18, FALSE), "")) -> 41 | S14: =IF(ISBLANK(A14), "", IFERROR(VLOOKUP(A14, STOCKS!A:W, 19, FALSE), "")) -> 0 | T14: =IF(ISBLANK(A14), "", IFERROR(VLOOKUP(A14, STOCKS!A:W, 20, FALSE), "")) -> 0 | U14: =IF(ISBLANK(A14), "", IFERROR(VLOOKUP(A14, STOCKS!A:W, 21, FALSE), "")) -> 46132 | V14: =IF(ISBLANK(A14), "", IFERROR(VLOOKUP(A14, STOCKS!A:W, 22, FALSE), ""))
A15: 6112 | B15: =IF(ISBLANK(A15), "", IFERROR(VLOOKUP(A15, STOCKS!A:W, 2, FALSE), "")) -> 邁達特 | C15: =IF(ISBLANK(A15), "", IFERROR(VLOOKUP(A15, STOCKS!A:W, 3, FALSE), "")) -> 資訊服務業 | D15: =IF(ISBLANK(A15), "", IFERROR(VLOOKUP(A15, STOCKS!A:W, 4, FALSE), "")) -> 47.9 | E15: =IF(ISBLANK(A15), "", IFERROR(VLOOKUP(A15, STOCKS!A:W, 5, FALSE), "")) -> -0.15 | F15: =IF(ISBLANK(A15), "", IFERROR(VLOOKUP(A15, STOCKS!A:W, 6, FALSE), "")) -> -0.31 | G15: =IF(ISBLANK(A15), "", IFERROR(VLOOKUP(A15, STOCKS!A:W, 7, FALSE), "")) -> '++++- | H15: =IF(ISBLANK(A15), "", IFERROR(VLOOKUP(A15, STOCKS!A:W, 8, FALSE), "")) -> 3.86 | I15: =IF(ISBLANK(A15), "", IFERROR(VLOOKUP(A15, STOCKS!A:W, 9, FALSE), "")) -> 0 | J15: =IF(ISBLANK(A15), "", IFERROR(VLOOKUP(A15, STOCKS!A:W, 10, FALSE), "")) -> 548 | K15: =IF(ISBLANK(A15), "", IFERROR(VLOOKUP(A15, STOCKS!A:W, 11, FALSE), "")) -> 0.29 | L15: =IF(ISBLANK(A15), "", IFERROR(VLOOKUP(A15, STOCKS!A:W, 12, FALSE), "")) -> 47.47 | M15: =IF(ISBLANK(A15), "", IFERROR(VLOOKUP(A15, STOCKS!A:W, 13, FALSE), "")) -> 46.89 | N15: =IF(ISBLANK(A15), "", IFERROR(VLOOKUP(A15, STOCKS!A:W, 14, FALSE), "")) -> 45.67 | O15: =IF(ISBLANK(A15), "", IFERROR(VLOOKUP(A15, STOCKS!A:W, 15, FALSE), "")) -> 78 | P15: =IF(ISBLANK(A15), "", IFERROR(VLOOKUP(A15, STOCKS!A:W, 16, FALSE), "")) -> '+++++ | Q15: =IF(ISBLANK(A15), "", IFERROR(VLOOKUP(A15, STOCKS!A:W, 17, FALSE), "")) -> 0 | R15: =IF(ISBLANK(A15), "", IFERROR(VLOOKUP(A15, STOCKS!A:W, 18, FALSE), "")) -> -8 | S15: =IF(ISBLANK(A15), "", IFERROR(VLOOKUP(A15, STOCKS!A:W, 19, FALSE), "")) -> 126 | T15: =IF(ISBLANK(A15), "", IFERROR(VLOOKUP(A15, STOCKS!A:W, 20, FALSE), "")) -> 22.99 | U15: =IF(ISBLANK(A15), "", IFERROR(VLOOKUP(A15, STOCKS!A:W, 21, FALSE), "")) -> 46132 | V15: =IF(ISBLANK(A15), "", IFERROR(VLOOKUP(A15, STOCKS!A:W, 22, FALSE), ""))
... A29: 2344 | B29: =IF(ISBLANK(A29), "", IFERROR(VLOOKUP(A29, STOCKS!A:W, 2, FALSE), "")) -> 華邦電 | C29: =IF(ISBLANK(A29), "", IFERROR(VLOOKUP(A29, STOCKS!A:W, 3, FALSE), "")) -> 半導體業 | D29: =IF(ISBLANK(A29), "", IFERROR(VLOOKUP(A29, STOCKS!A:W, 4, FALSE), "")) -> 85.7 | E29: =IF(ISBLANK(A29), "", IFERROR(VLOOKUP(A29, STOCKS!A:W, 5, FALSE), "")) -> -2.1 | F29: =IF(ISBLANK(A29), "", IFERROR(VLOOKUP(A29, STOCKS!A:W, 6, FALSE), "")) -> -2.39 | G29: =IF(ISBLANK(A29), "", IFERROR(VLOOKUP(A29, STOCKS!A:W, 7, FALSE), "")) -> '----- | H29: =IF(ISBLANK(A29), "", IFERROR(VLOOKUP(A29, STOCKS!A:W, 8, FALSE), "")) -> -9.55 | I29: =IF(ISBLANK(A29), "", IFERROR(VLOOKUP(A29, STOCKS!A:W, 9, FALSE), "")) -> 0 | J29: =IF(ISBLANK(A29), "", IFERROR(VLOOKUP(A29, STOCKS!A:W, 10, FALSE), "")) -> 164660 | K29: =IF(ISBLANK(A29), "", IFERROR(VLOOKUP(A29, STOCKS!A:W, 11, FALSE), "")) -> 3.66 | L29: =IF(ISBLANK(A29), "", IFERROR(VLOOKUP(A29, STOCKS!A:W, 12, FALSE), "")) -> 89.36 | M29: =IF(ISBLANK(A29), "", IFERROR(VLOOKUP(A29, STOCKS!A:W, 13, FALSE), "")) -> 91.07 | N29: =IF(ISBLANK(A29), "", IFERROR(VLOOKUP(A29, STOCKS!A:W, 14, FALSE), "")) -> 94.12 | O29: =IF(ISBLANK(A29), "", IFERROR(VLOOKUP(A29, STOCKS!A:W, 15, FALSE), "")) -> 49497 | P29: =IF(ISBLANK(A29), "", IFERROR(VLOOKUP(A29, STOCKS!A:W, 16, FALSE), "")) -> '--+++ | Q29: =IF(ISBLANK(A29), "", IFERROR(VLOOKUP(A29, STOCKS!A:W, 17, FALSE), "")) -> -7986 | R29: =IF(ISBLANK(A29), "", IFERROR(VLOOKUP(A29, STOCKS!A:W, 18, FALSE), "")) -> 1331 | S29: =IF(ISBLANK(A29), "", IFERROR(VLOOKUP(A29, STOCKS!A:W, 19, FALSE), "")) -> 60976 | T29: =IF(ISBLANK(A29), "", IFERROR(VLOOKUP(A29, STOCKS!A:W, 20, FALSE), "")) -> 37.03 | U29: =IF(ISBLANK(A29), "", IFERROR(VLOOKUP(A29, STOCKS!A:W, 21, FALSE), "")) -> 46132 | V29: =IF(ISBLANK(A29), "", IFERROR(VLOOKUP(A29, STOCKS!A:W, 22, FALSE), ""))

Sheet 紅綠-題材股
C1: 選股符合打V | E1: 參考 | H1: V | J1: 參考 | K1: V | L1: V | M1: 參考 | O1: 參考 | Q1: V | T1: 參考
C2: 條件: | E2: <150 | H2: 為 - - | J2: >=3 | K2: >2000 | L2: >5 | M2: MA5逼近MA10 | O2: D<N | Q2: 為 + + | T2: >成交*50% | W2: https://mops.twse.com.tw/mops/#/web/home
A3: ID | B3: Name | C3: Type | D3: 題材類型 | E3: 收盤價 | F3: 價差 | G3: 漲幅(%) | H3: 五日+- | I3: 五日漲幅 (%) | J3: 漲停歷史 | K3: 交易量 (張) | L3: 周轉率 (%) | M3: MA5 | N3: MA10 | O3: MA20 | P3: 外資 (張) | Q3: 外資 五日+- | R3: 投信 (張) | S3: 自營 (張) | T3: 當沖 (張) | U3: 當沖 (%) | V3: Date | W3: 第 1 欄 | X3: 第 2 欄 | Y3: 第 3 欄 | Z3: 第 4 欄 | AA3: 第 26 欄
A4: 題材-軍工
A5: 2634 | B5: =IF(ISBLANK(A5), "", IFERROR(VLOOKUP(A5, STOCKS!A:W, 2, FALSE), "")) -> 漢翔 | C5: =IF(ISBLANK(A5), "", IFERROR(VLOOKUP(A5, STOCKS!A:W, 3, FALSE), "")) -> 航運業 | D5: =IF(ISBLANK(A5), "", IFERROR(VLOOKUP(A5, category!A:C, 3, FALSE), "")) -> 軍工/航太 | E5: =IF(ISBLANK(A5), "", IFERROR(VLOOKUP(A5, STOCKS!A:W, 4, FALSE), "")) -> 50.4 | F5: =IF(ISBLANK(A5), "", IFERROR(VLOOKUP(A5, STOCKS!A:W, 5, FALSE), "")) -> 0 | G5: =IF(ISBLANK(A5), "", IFERROR(VLOOKUP(A5, STOCKS!A:W, 6, FALSE), "")) -> 0 | H5: =IF(ISBLANK(A5), "", IFERROR(VLOOKUP(A5, STOCKS!A:W, 7, FALSE), "")) -> '++++- | I5: =IF(ISBLANK(A5), "", IFERROR(VLOOKUP(A5, STOCKS!A:W, 8, FALSE), "")) -> 7.19 | J5: =IF(ISBLANK(A5), "", IFERROR(VLOOKUP(A5, STOCKS!A:W, 9, FALSE), "")) -> 0 | K5: =IF(ISBLANK(A5), "", IFERROR(VLOOKUP(A5, STOCKS!A:W, 10, FALSE), "")) -> 6483 | L5: =IF(ISBLANK(A5), "", IFERROR(VLOOKUP(A5, STOCKS!A:W, 11, FALSE), "")) -> 0.69 | M5: =IF(ISBLANK(A5), "", IFERROR(VLOOKUP(A5, STOCKS!A:W, 12, FALSE), "")) -> 49.14 | N5: =IF(ISBLANK(A5), "", IFERROR(VLOOKUP(A5, STOCKS!A:W, 13, FALSE), "")) -> 47.93 | O5: =IF(ISBLANK(A5), "", IFERROR(VLOOKUP(A5, STOCKS!A:W, 14, FALSE), "")) -> 48.3 | P5: =IF(ISBLANK(A5), "", IFERROR(VLOOKUP(A5, STOCKS!A:W, 15, FALSE), "")) -> -799 | Q5: =IF(ISBLANK(A5), "", IFERROR(VLOOKUP(A5, STOCKS!A:W, 16, FALSE), "")) -> '+-++- | R5: =IF(ISBLANK(A5), "", IFERROR(VLOOKUP(A5, STOCKS!A:W, 17, FALSE), "")) -> -6 | S5: =IF(ISBLANK(A5), "", IFERROR(VLOOKUP(A5, STOCKS!A:W, 18, FALSE), "")) -> 4 | T5: =IF(ISBLANK(A5), "", IFERROR(VLOOKUP(A5, STOCKS!A:W, 19, FALSE), "")) -> 1976 | U5: =IF(ISBLANK(A5), "", IFERROR(VLOOKUP(A5, STOCKS!A:W, 20, FALSE), "")) -> 30.48 | V5: =IF(ISBLANK(A5), "", IFERROR(VLOOKUP(A5, STOCKS!A:W, 21, FALSE), "")) -> 46132 | W5: =IF(ISBLANK(A5), "", IFERROR(VLOOKUP(A5, STOCKS!A:W, 22, FALSE), ""))
A6: 2645 | B6: =IF(ISBLANK(A6), "", IFERROR(VLOOKUP(A6, STOCKS!A:W, 2, FALSE), "")) -> 長榮航太 | C6: =IF(ISBLANK(A6), "", IFERROR(VLOOKUP(A6, STOCKS!A:W, 3, FALSE), "")) -> 航運業 | D6: =IF(ISBLANK(A6), "", IFERROR(VLOOKUP(A6, category!A:C, 3, FALSE), "")) -> 軍工/航太 | E6: =IF(ISBLANK(A6), "", IFERROR(VLOOKUP(A6, STOCKS!A:W, 4, FALSE), "")) -> 166 | F6: =IF(ISBLANK(A6), "", IFERROR(VLOOKUP(A6, STOCKS!A:W, 5, FALSE), "")) -> 5.5 | G6: =IF(ISBLANK(A6), "", IFERROR(VLOOKUP(A6, STOCKS!A:W, 6, FALSE), "")) -> 3.43 | H6: =IF(ISBLANK(A6), "", IFERROR(VLOOKUP(A6, STOCKS!A:W, 7, FALSE), "")) -> '+++++ | I6: =IF(ISBLANK(A6), "", IFERROR(VLOOKUP(A6, STOCKS!A:W, 8, FALSE), "")) -> 9.93 | J6: =IF(ISBLANK(A6), "", IFERROR(VLOOKUP(A6, STOCKS!A:W, 9, FALSE), "")) -> 0 | K6: =IF(ISBLANK(A6), "", IFERROR(VLOOKUP(A6, STOCKS!A:W, 10, FALSE), "")) -> 2331 | L6: =IF(ISBLANK(A6), "", IFERROR(VLOOKUP(A6, STOCKS!A:W, 11, FALSE), "")) -> 0.62 | M6: =IF(ISBLANK(A6), "", IFERROR(VLOOKUP(A6, STOCKS!A:W, 12, FALSE), "")) -> 157.6 | N6: =IF(ISBLANK(A6), "", IFERROR(VLOOKUP(A6, STOCKS!A:W, 13, FALSE), "")) -> 153.55 | O6: =IF(ISBLANK(A6), "", IFERROR(VLOOKUP(A6, STOCKS!A:W, 14, FALSE), "")) -> 151.78 | P6: =IF(ISBLANK(A6), "", IFERROR(VLOOKUP(A6, STOCKS!A:W, 15, FALSE), "")) -> 893 | Q6: =IF(ISBLANK(A6), "", IFERROR(VLOOKUP(A6, STOCKS!A:W, 16, FALSE), "")) -> '+++++ | R6: =IF(ISBLANK(A6), "", IFERROR(VLOOKUP(A6, STOCKS!A:W, 17, FALSE), "")) -> -3 | S6: =IF(ISBLANK(A6), "", IFERROR(VLOOKUP(A6, STOCKS!A:W, 18, FALSE), "")) -> 74 | T6: =IF(ISBLANK(A6), "", IFERROR(VLOOKUP(A6, STOCKS!A:W, 19, FALSE), "")) -> 656 | U6: =IF(ISBLANK(A6), "", IFERROR(VLOOKUP(A6, STOCKS!A:W, 20, FALSE), "")) -> 28.14 | V6: =IF(ISBLANK(A6), "", IFERROR(VLOOKUP(A6, STOCKS!A:W, 21, FALSE), "")) -> 46132 | W6: =IF(ISBLANK(A6), "", IFERROR(VLOOKUP(A6, STOCKS!A:W, 22, FALSE), ""))
A7: 4541 | B7: =IF(ISBLANK(A7), "", IFERROR(VLOOKUP(A7, STOCKS!A:W, 2, FALSE), "")) -> 晟田 | C7: =IF(ISBLANK(A7), "", IFERROR(VLOOKUP(A7, STOCKS!A:W, 3, FALSE), "")) -> 其他業 | D7: =IF(ISBLANK(A7), "", IFERROR(VLOOKUP(A7, category!A:C, 3, FALSE), "")) -> 軍工/航太 | E7: =IF(ISBLANK(A7), "", IFERROR(VLOOKUP(A7, STOCKS!A:W, 4, FALSE), "")) -> 49.35 | F7: =IF(ISBLANK(A7), "", IFERROR(VLOOKUP(A7, STOCKS!A:W, 5, FALSE), "")) -> 1.05 | G7: =IF(ISBLANK(A7), "", IFERROR(VLOOKUP(A7, STOCKS!A:W, 6, FALSE), "")) -> 2.17 | H7: =IF(ISBLANK(A7), "", IFERROR(VLOOKUP(A7, STOCKS!A:W, 7, FALSE), "")) -> '+-+++ | I7: =IF(ISBLANK(A7), "", IFERROR(VLOOKUP(A7, STOCKS!A:W, 8, FALSE), "")) -> 6.37 | J7: =IF(ISBLANK(A7), "", IFERROR(VLOOKUP(A7, STOCKS!A:W, 9, FALSE), "")) -> 1 | K7: =IF(ISBLANK(A7), "", IFERROR(VLOOKUP(A7, STOCKS!A:W, 10, FALSE), "")) -> 3379 | L7: =IF(ISBLANK(A7), "", IFERROR(VLOOKUP(A7, STOCKS!A:W, 11, FALSE), "")) -> 5 | M7: =IF(ISBLANK(A7), "", IFERROR(VLOOKUP(A7, STOCKS!A:W, 12, FALSE), "")) -> 47.72 | N7: =IF(ISBLANK(A7), "", IFERROR(VLOOKUP(A7, STOCKS!A:W, 13, FALSE), "")) -> 45.71 | O7: =IF(ISBLANK(A7), "", IFERROR(VLOOKUP(A7, STOCKS!A:W, 14, FALSE), "")) -> 43.71 | P7: =IF(ISBLANK(A7), "", IFERROR(VLOOKUP(A7, STOCKS!A:W, 15, FALSE), "")) -> 438 | Q7: =IF(ISBLANK(A7), "", IFERROR(VLOOKUP(A7, STOCKS!A:W, 16, FALSE), "")) -> '+++++ | R7: =IF(ISBLANK(A7), "", IFERROR(VLOOKUP(A7, STOCKS!A:W, 17, FALSE), "")) -> 0 | S7: =IF(ISBLANK(A7), "", IFERROR(VLOOKUP(A7, STOCKS!A:W, 18, FALSE), "")) -> 2 | T7: =IF(ISBLANK(A7), "", IFERROR(VLOOKUP(A7, STOCKS!A:W, 19, FALSE), "")) -> 1176 | U7: =IF(ISBLANK(A7), "", IFERROR(VLOOKUP(A7, STOCKS!A:W, 20, FALSE), "")) -> 34.8 | V7: =IF(ISBLANK(A7), "", IFERROR(VLOOKUP(A7, STOCKS!A:W, 21, FALSE), "")) -> 46132 | W7: =IF(ISBLANK(A7), "", IFERROR(VLOOKUP(A7, STOCKS!A:W, 22, FALSE), ""))
A8: 4572 | B8: =IF(ISBLANK(A8), "", IFERROR(VLOOKUP(A8, STOCKS!A:W, 2, FALSE), "")) -> 駐龍 | C8: =IF(ISBLANK(A8), "", IFERROR(VLOOKUP(A8, STOCKS!A:W, 3, FALSE), "")) -> 電機機械 | D8: =IF(ISBLANK(A8), "", IFERROR(VLOOKUP(A8, category!A:C, 3, FALSE), "")) -> 軍工/航太 | E8: =IF(ISBLANK(A8), "", IFERROR(VLOOKUP(A8, STOCKS!A:W, 4, FALSE), "")) -> 148 | F8: =IF(ISBLANK(A8), "", IFERROR(VLOOKUP(A8, STOCKS!A:W, 5, FALSE), "")) -> 1.5 | G8: =IF(ISBLANK(A8), "", IFERROR(VLOOKUP(A8, STOCKS!A:W, 6, FALSE), "")) -> 1.02 | H8: =IF(ISBLANK(A8), "", IFERROR(VLOOKUP(A8, STOCKS!A:W, 7, FALSE), "")) -> '+++++ | I8: =IF(ISBLANK(A8), "", IFERROR(VLOOKUP(A8, STOCKS!A:W, 8, FALSE), "")) -> 4.51 | J8: =IF(ISBLANK(A8), "", IFERROR(VLOOKUP(A8, STOCKS!A:W, 9, FALSE), "")) -> 0 | K8: =IF(ISBLANK(A8), "", IFERROR(VLOOKUP(A8, STOCKS!A:W, 10, FALSE), "")) -> 49 | L8: =IF(ISBLANK(A8), "", IFERROR(VLOOKUP(A8, STOCKS!A:W, 11, FALSE), "")) -> 0.12 | M8: =IF(ISBLANK(A8), "", IFERROR(VLOOKUP(A8, STOCKS!A:W, 12, FALSE), "")) -> 145.6 | N8: =IF(ISBLANK(A8), "", IFERROR(VLOOKUP(A8, STOCKS!A:W, 13, FALSE), "")) -> 143.55 | O8: =IF(ISBLANK(A8), "", IFERROR(VLOOKUP(A8, STOCKS!A:W, 14, FALSE), "")) -> 143 | P8: =IF(ISBLANK(A8), "", IFERROR(VLOOKUP(A8, STOCKS!A:W, 15, FALSE), "")) -> 20 | Q8: =IF(ISBLANK(A8), "", IFERROR(VLOOKUP(A8, STOCKS!A:W, 16, FALSE), "")) -> '+++++ | R8: =IF(ISBLANK(A8), "", IFERROR(VLOOKUP(A8, STOCKS!A:W, 17, FALSE), "")) -> 0 | S8: =IF(ISBLANK(A8), "", IFERROR(VLOOKUP(A8, STOCKS!A:W, 18, FALSE), "")) -> 0 | T8: =IF(ISBLANK(A8), "", IFERROR(VLOOKUP(A8, STOCKS!A:W, 19, FALSE), "")) -> 11 | U8: =IF(ISBLANK(A8), "", IFERROR(VLOOKUP(A8, STOCKS!A:W, 20, FALSE), "")) -> 22.45 | V8: =IF(ISBLANK(A8), "", IFERROR(VLOOKUP(A8, STOCKS!A:W, 21, FALSE), "")) -> 46132 | W8: =IF(ISBLANK(A8), "", IFERROR(VLOOKUP(A8, STOCKS!A:W, 22, FALSE), ""))
A9: 6829 | B9: =IF(ISBLANK(A9), "", IFERROR(VLOOKUP(A9, STOCKS!A:W, 2, FALSE), "")) -> 千附精密 | C9: =IF(ISBLANK(A9), "", IFERROR(VLOOKUP(A9, STOCKS!A:W, 3, FALSE), "")) -> 半導體業 | D9: =IF(ISBLANK(A9), "", IFERROR(VLOOKUP(A9, category!A:C, 3, FALSE), "")) -> 軍工/航太 | E9: =IF(ISBLANK(A9), "", IFERROR(VLOOKUP(A9, STOCKS!A:W, 4, FALSE), "")) -> 216.5 | F9: =IF(ISBLANK(A9), "", IFERROR(VLOOKUP(A9, STOCKS!A:W, 5, FALSE), "")) -> 19.5 | G9: =IF(ISBLANK(A9), "", IFERROR(VLOOKUP(A9, STOCKS!A:W, 6, FALSE), "")) -> 9.9 | H9: =IF(ISBLANK(A9), "", IFERROR(VLOOKUP(A9, STOCKS!A:W, 7, FALSE), "")) -> '+++++ | I9: =IF(ISBLANK(A9), "", IFERROR(VLOOKUP(A9, STOCKS!A:W, 8, FALSE), "")) -> 46.36 | J9: =IF(ISBLANK(A9), "", IFERROR(VLOOKUP(A9, STOCKS!A:W, 9, FALSE), "")) -> 5 | K9: =IF(ISBLANK(A9), "", IFERROR(VLOOKUP(A9, STOCKS!A:W, 10, FALSE), "")) -> 742 | L9: =IF(ISBLANK(A9), "", IFERROR(VLOOKUP(A9, STOCKS!A:W, 11, FALSE), "")) -> 1.25 | M9: =IF(ISBLANK(A9), "", IFERROR(VLOOKUP(A9, STOCKS!A:W, 12, FALSE), "")) -> 181.1 | N9: =IF(ISBLANK(A9), "", IFERROR(VLOOKUP(A9, STOCKS!A:W, 13, FALSE), "")) -> 154.35 | O9: =IF(ISBLANK(A9), "", IFERROR(VLOOKUP(A9, STOCKS!A:W, 14, FALSE), "")) -> 134.55 | P9: =IF(ISBLANK(A9), "", IFERROR(VLOOKUP(A9, STOCKS!A:W, 15, FALSE), "")) -> -21 | Q9: =IF(ISBLANK(A9), "", IFERROR(VLOOKUP(A9, STOCKS!A:W, 16, FALSE), "")) -> '+--+- | R9: =IF(ISBLANK(A9), "", IFERROR(VLOOKUP(A9, STOCKS!A:W, 17, FALSE), "")) -> 0 | S9: =IF(ISBLANK(A9), "", IFERROR(VLOOKUP(A9, STOCKS!A:W, 18, FALSE), "")) -> 0 | T9: =IF(ISBLANK(A9), "", IFERROR(VLOOKUP(A9, STOCKS!A:W, 19, FALSE), "")) -> 0 | U9: =IF(ISBLANK(A9), "", IFERROR(VLOOKUP(A9, STOCKS!A:W, 20, FALSE), "")) -> 0 | V9: =IF(ISBLANK(A9), "", IFERROR(VLOOKUP(A9, STOCKS!A:W, 21, FALSE), "")) -> 46132 | W9: =IF(ISBLANK(A9), "", IFERROR(VLOOKUP(A9, STOCKS!A:W, 22, FALSE), "")) -> 本公司有價證券近期多次達公佈注意交易資訊標準， 故公告相關訊息，以利投資人區別瞭解。
A10: 8222 | B10: =IF(ISBLANK(A10), "", IFERROR(VLOOKUP(A10, STOCKS!A:W, 2, FALSE), "")) -> 寶一 | C10: =IF(ISBLANK(A10), "", IFERROR(VLOOKUP(A10, STOCKS!A:W, 3, FALSE), "")) -> 電機機械 | D10: =IF(ISBLANK(A10), "", IFERROR(VLOOKUP(A10, category!A:C, 3, FALSE), "")) -> 軍工/航太 | E10: =IF(ISBLANK(A10), "", IFERROR(VLOOKUP(A10, STOCKS!A:W, 4, FALSE), "")) -> 37.85 | F10: =IF(ISBLANK(A10), "", IFERROR(VLOOKUP(A10, STOCKS!A:W, 5, FALSE), "")) -> 0 | G10: =IF(ISBLANK(A10), "", IFERROR(VLOOKUP(A10, STOCKS!A:W, 6, FALSE), "")) -> 0 | H10: =IF(ISBLANK(A10), "", IFERROR(VLOOKUP(A10, STOCKS!A:W, 7, FALSE), "")) -> '++++- | I10: =IF(ISBLANK(A10), "", IFERROR(VLOOKUP(A10, STOCKS!A:W, 8, FALSE), "")) -> 9.45 | J10: =IF(ISBLANK(A10), "", IFERROR(VLOOKUP(A10, STOCKS!A:W, 9, FALSE), "")) -> 0 | K10: =IF(ISBLANK(A10), "", IFERROR(VLOOKUP(A10, STOCKS!A:W, 10, FALSE), "")) -> 565 | L10: =IF(ISBLANK(A10), "", IFERROR(VLOOKUP(A10, STOCKS!A:W, 11, FALSE), "")) -> 0.82 | M10: =IF(ISBLANK(A10), "", IFERROR(VLOOKUP(A10, STOCKS!A:W, 12, FALSE), "")) -> 36.89 | N10: =IF(ISBLANK(A10), "", IFERROR(VLOOKUP(A10, STOCKS!A:W, 13, FALSE), "")) -> 35.61 | O10: =IF(ISBLANK(A10), "", IFERROR(VLOOKUP(A10, STOCKS!A:W, 14, FALSE), "")) -> 35.82 | P10: =IF(ISBLANK(A10), "", IFERROR(VLOOKUP(A10, STOCKS!A:W, 15, FALSE), "")) -> 61 | Q10: =IF(ISBLANK(A10), "", IFERROR(VLOOKUP(A10, STOCKS!A:W, 16, FALSE), "")) -> '++-++ | R10: =IF(ISBLANK(A10), "", IFERROR(VLOOKUP(A10, STOCKS!A:W, 17, FALSE), "")) -> 0 | S10: =IF(ISBLANK(A10), "", IFERROR(VLOOKUP(A10, STOCKS!A:W, 18, FALSE), "")) -> 0 | T10: =IF(ISBLANK(A10), "", IFERROR(VLOOKUP(A10, STOCKS!A:W, 19, FALSE), "")) -> 134 | U10: =IF(ISBLANK(A10), "", IFERROR(VLOOKUP(A10, STOCKS!A:W, 20, FALSE), "")) -> 23.72 | V10: =IF(ISBLANK(A10), "", IFERROR(VLOOKUP(A10, STOCKS!A:W, 21, FALSE), "")) -> 46132 | W10: =IF(ISBLANK(A10), "", IFERROR(VLOOKUP(A10, STOCKS!A:W, 22, FALSE), ""))
A11: 8033 | B11: =IF(ISBLANK(A11), "", IFERROR(VLOOKUP(A11, STOCKS!A:W, 2, FALSE), "")) -> 雷虎 | C11: =IF(ISBLANK(A11), "", IFERROR(VLOOKUP(A11, STOCKS!A:W, 3, FALSE), "")) -> 其他業 | D11: =IF(ISBLANK(A11), "", IFERROR(VLOOKUP(A11, category!A:C, 3, FALSE), "")) -> 軍工/航太 | E11: =IF(ISBLANK(A11), "", IFERROR(VLOOKUP(A11, STOCKS!A:W, 4, FALSE), "")) -> 154.5 | F11: =IF(ISBLANK(A11), "", IFERROR(VLOOKUP(A11, STOCKS!A:W, 5, FALSE), "")) -> 6.5 | G11: =IF(ISBLANK(A11), "", IFERROR(VLOOKUP(A11, STOCKS!A:W, 6, FALSE), "")) -> 4.39 | H11: =IF(ISBLANK(A11), "", IFERROR(VLOOKUP(A11, STOCKS!A:W, 7, FALSE), "")) -> '+-+++ | I11: =IF(ISBLANK(A11), "", IFERROR(VLOOKUP(A11, STOCKS!A:W, 8, FALSE), "")) -> 17.68 | J11: =IF(ISBLANK(A11), "", IFERROR(VLOOKUP(A11, STOCKS!A:W, 9, FALSE), "")) -> 0 | K11: =IF(ISBLANK(A11), "", IFERROR(VLOOKUP(A11, STOCKS!A:W, 10, FALSE), "")) -> 9290 | L11: =IF(ISBLANK(A11), "", IFERROR(VLOOKUP(A11, STOCKS!A:W, 11, FALSE), "")) -> 6.09 | M11: =IF(ISBLANK(A11), "", IFERROR(VLOOKUP(A11, STOCKS!A:W, 12, FALSE), "")) -> 144.3 | N11: =IF(ISBLANK(A11), "", IFERROR(VLOOKUP(A11, STOCKS!A:W, 13, FALSE), "")) -> 138.35 | O11: =IF(ISBLANK(A11), "", IFERROR(VLOOKUP(A11, STOCKS!A:W, 14, FALSE), "")) -> 140.82 | P11: =IF(ISBLANK(A11), "", IFERROR(VLOOKUP(A11, STOCKS!A:W, 15, FALSE), "")) -> 1794 | Q11: =IF(ISBLANK(A11), "", IFERROR(VLOOKUP(A11, STOCKS!A:W, 16, FALSE), "")) -> '+++++ | R11: =IF(ISBLANK(A11), "", IFERROR(VLOOKUP(A11, STOCKS!A:W, 17, FALSE), "")) -> 0 | S11: =IF(ISBLANK(A11), "", IFERROR(VLOOKUP(A11, STOCKS!A:W, 18, FALSE), "")) -> 136 | T11: =IF(ISBLANK(A11), "", IFERROR(VLOOKUP(A11, STOCKS!A:W, 19, FALSE), "")) -> 3863 | U11: =IF(ISBLANK(A11), "", IFERROR(VLOOKUP(A11, STOCKS!A:W, 20, FALSE), "")) -> 41.58 | V11: =IF(ISBLANK(A11), "", IFERROR(VLOOKUP(A11, STOCKS!A:W, 21, FALSE), "")) -> 46132 | W11: =IF(ISBLANK(A11), "", IFERROR(VLOOKUP(A11, STOCKS!A:W, 22, FALSE), ""))
A12: 7402 | B12: =IF(ISBLANK(A12), "", IFERROR(VLOOKUP(A12, STOCKS!A:W, 2, FALSE), "")) -> 邑錡 | C12: =IF(ISBLANK(A12), "", IFERROR(VLOOKUP(A12, STOCKS!A:W, 3, FALSE), "")) -> 光電業 | D12: =IF(ISBLANK(A12), "", IFERROR(VLOOKUP(A12, category!A:C, 3, FALSE), "")) -> 軍工/航太 | E12: =IF(ISBLANK(A12), "", IFERROR(VLOOKUP(A12, STOCKS!A:W, 4, FALSE), "")) -> 133.5 | F12: =IF(ISBLANK(A12), "", IFERROR(VLOOKUP(A12, STOCKS!A:W, 5, FALSE), "")) -> 8 | G12: =IF(ISBLANK(A12), "", IFERROR(VLOOKUP(A12, STOCKS!A:W, 6, FALSE), "")) -> 6.37 | H12: =IF(ISBLANK(A12), "", IFERROR(VLOOKUP(A12, STOCKS!A:W, 7, FALSE), "")) -> '+++++ | I12: =IF(ISBLANK(A12), "", IFERROR(VLOOKUP(A12, STOCKS!A:W, 8, FALSE), "")) -> 10.91 | J12: =IF(ISBLANK(A12), "", IFERROR(VLOOKUP(A12, STOCKS!A:W, 9, FALSE), "")) -> 0 | K12: =IF(ISBLANK(A12), "", IFERROR(VLOOKUP(A12, STOCKS!A:W, 10, FALSE), "")) -> 1906 | L12: =IF(ISBLANK(A12), "", IFERROR(VLOOKUP(A12, STOCKS!A:W, 11, FALSE), "")) -> 5.4 | M12: =IF(ISBLANK(A12), "", IFERROR(VLOOKUP(A12, STOCKS!A:W, 12, FALSE), "")) -> 125.1 | N12: =IF(ISBLANK(A12), "", IFERROR(VLOOKUP(A12, STOCKS!A:W, 13, FALSE), "")) -> 121 | O12: =IF(ISBLANK(A12), "", IFERROR(VLOOKUP(A12, STOCKS!A:W, 14, FALSE), "")) -> 120.97 | P12: =IF(ISBLANK(A12), "", IFERROR(VLOOKUP(A12, STOCKS!A:W, 15, FALSE), "")) -> 82 | Q12: =IF(ISBLANK(A12), "", IFERROR(VLOOKUP(A12, STOCKS!A:W, 16, FALSE), "")) -> '+---+ | R12: =IF(ISBLANK(A12), "", IFERROR(VLOOKUP(A12, STOCKS!A:W, 17, FALSE), "")) -> 0 | S12: =IF(ISBLANK(A12), "", IFERROR(VLOOKUP(A12, STOCKS!A:W, 18, FALSE), "")) -> -10 | T12: =IF(ISBLANK(A12), "", IFERROR(VLOOKUP(A12, STOCKS!A:W, 19, FALSE), "")) -> 830 | U12: =IF(ISBLANK(A12), "", IFERROR(VLOOKUP(A12, STOCKS!A:W, 20, FALSE), "")) -> 43.55 | V12: =IF(ISBLANK(A12), "", IFERROR(VLOOKUP(A12, STOCKS!A:W, 21, FALSE), "")) -> 46132 | W12: =IF(ISBLANK(A12), "", IFERROR(VLOOKUP(A12, STOCKS!A:W, 22, FALSE), ""))
A13: 5371 | B13: =IF(ISBLANK(A13), "", IFERROR(VLOOKUP(A13, STOCKS!A:W, 2, FALSE), "")) -> 中光電 | C13: =IF(ISBLANK(A13), "", IFERROR(VLOOKUP(A13, STOCKS!A:W, 3, FALSE), "")) -> 光電業 | D13: =IF(ISBLANK(A13), "", IFERROR(VLOOKUP(A13, category!A:C, 3, FALSE), "")) -> 軍工/航太/ | E13: =IF(ISBLANK(A13), "", IFERROR(VLOOKUP(A13, STOCKS!A:W, 4, FALSE), "")) -> 79 | F13: =IF(ISBLANK(A13), "", IFERROR(VLOOKUP(A13, STOCKS!A:W, 5, FALSE), "")) -> 0.7 | G13: =IF(ISBLANK(A13), "", IFERROR(VLOOKUP(A13, STOCKS!A:W, 6, FALSE), "")) -> 0.89 | H13: =IF(ISBLANK(A13), "", IFERROR(VLOOKUP(A13, STOCKS!A:W, 7, FALSE), "")) -> '+++-+ | I13: =IF(ISBLANK(A13), "", IFERROR(VLOOKUP(A13, STOCKS!A:W, 8, FALSE), "")) -> 7.19 | J13: =IF(ISBLANK(A13), "", IFERROR(VLOOKUP(A13, STOCKS!A:W, 9, FALSE), "")) -> 0 | K13: =IF(ISBLANK(A13), "", IFERROR(VLOOKUP(A13, STOCKS!A:W, 10, FALSE), "")) -> 6795 | L13: =IF(ISBLANK(A13), "", IFERROR(VLOOKUP(A13, STOCKS!A:W, 11, FALSE), "")) -> 1.74 | M13: =IF(ISBLANK(A13), "", IFERROR(VLOOKUP(A13, STOCKS!A:W, 12, FALSE), "")) -> 77.08 | N13: =IF(ISBLANK(A13), "", IFERROR(VLOOKUP(A13, STOCKS!A:W, 13, FALSE), "")) -> 75.35 | O13: =IF(ISBLANK(A13), "", IFERROR(VLOOKUP(A13, STOCKS!A:W, 14, FALSE), "")) -> 75.28 | P13: =IF(ISBLANK(A13), "", IFERROR(VLOOKUP(A13, STOCKS!A:W, 15, FALSE), "")) -> 398 | Q13: =IF(ISBLANK(A13), "", IFERROR(VLOOKUP(A13, STOCKS!A:W, 16, FALSE), "")) -> '++--+ | R13: =IF(ISBLANK(A13), "", IFERROR(VLOOKUP(A13, STOCKS!A:W, 17, FALSE), "")) -> 0 | S13: =IF(ISBLANK(A13), "", IFERROR(VLOOKUP(A13, STOCKS!A:W, 18, FALSE), "")) -> -130 | T13: =IF(ISBLANK(A13), "", IFERROR(VLOOKUP(A13, STOCKS!A:W, 19, FALSE), "")) -> 3115 | U13: =IF(ISBLANK(A13), "", IFERROR(VLOOKUP(A13, STOCKS!A:W, 20, FALSE), "")) -> 45.84 | V13: =IF(ISBLANK(A13), "", IFERROR(VLOOKUP(A13, STOCKS!A:W, 21, FALSE), "")) -> 46132 | W13: =IF(ISBLANK(A13), "", IFERROR(VLOOKUP(A13, STOCKS!A:W, 22, FALSE), ""))
A14: 5314 | B14: =IF(ISBLANK(A14), "", IFERROR(VLOOKUP(A14, STOCKS!A:W, 2, FALSE), "")) -> 世紀* | C14: =IF(ISBLANK(A14), "", IFERROR(VLOOKUP(A14, STOCKS!A:W, 3, FALSE), "")) -> 其他業 | D14: =IF(ISBLANK(A14), "", IFERROR(VLOOKUP(A14, category!A:C, 3, FALSE), "")) -> 機器人/軍工 | E14: =IF(ISBLANK(A14), "", IFERROR(VLOOKUP(A14, STOCKS!A:W, 4, FALSE), "")) -> 78.1 | F14: =IF(ISBLANK(A14), "", IFERROR(VLOOKUP(A14, STOCKS!A:W, 5, FALSE), "")) -> -2.1 | G14: =IF(ISBLANK(A14), "", IFERROR(VLOOKUP(A14, STOCKS!A:W, 6, FALSE), "")) -> -2.62 | H14: =IF(ISBLANK(A14), "", IFERROR(VLOOKUP(A14, STOCKS!A:W, 7, FALSE), "")) -> '-++-- | I14: =IF(ISBLANK(A14), "", IFERROR(VLOOKUP(A14, STOCKS!A:W, 8, FALSE), "")) -> 0.63 | J14: =IF(ISBLANK(A14), "", IFERROR(VLOOKUP(A14, STOCKS!A:W, 9, FALSE), "")) -> 0 | K14: =IF(ISBLANK(A14), "", IFERROR(VLOOKUP(A14, STOCKS!A:W, 10, FALSE), "")) -> 4482 | L14: =IF(ISBLANK(A14), "", IFERROR(VLOOKUP(A14, STOCKS!A:W, 11, FALSE), "")) -> 1.53 | M14: =IF(ISBLANK(A14), "", IFERROR(VLOOKUP(A14, STOCKS!A:W, 12, FALSE), "")) -> 78.94 | N14: =IF(ISBLANK(A14), "", IFERROR(VLOOKUP(A14, STOCKS!A:W, 13, FALSE), "")) -> 78.84 | O14: =IF(ISBLANK(A14), "", IFERROR(VLOOKUP(A14, STOCKS!A:W, 14, FALSE), "")) -> 77.21 | P14: =IF(ISBLANK(A14), "", IFERROR(VLOOKUP(A14, STOCKS!A:W, 15, FALSE), "")) -> -435 | Q14: =IF(ISBLANK(A14), "", IFERROR(VLOOKUP(A14, STOCKS!A:W, 16, FALSE), "")) -> '+++-- | R14: =IF(ISBLANK(A14), "", IFERROR(VLOOKUP(A14, STOCKS!A:W, 17, FALSE), "")) -> 7 | S14: =IF(ISBLANK(A14), "", IFERROR(VLOOKUP(A14, STOCKS!A:W, 18, FALSE), "")) -> -22 | T14: =IF(ISBLANK(A14), "", IFERROR(VLOOKUP(A14, STOCKS!A:W, 19, FALSE), "")) -> 1014 | U14: =IF(ISBLANK(A14), "", IFERROR(VLOOKUP(A14, STOCKS!A:W, 20, FALSE), "")) -> 22.62 | V14: =IF(ISBLANK(A14), "", IFERROR(VLOOKUP(A14, STOCKS!A:W, 21, FALSE), "")) -> 46132 | W14: =IF(ISBLANK(A14), "", IFERROR(VLOOKUP(A14, STOCKS!A:W, 22, FALSE), ""))
A15: 2630 | B15: =IF(ISBLANK(A15), "", IFERROR(VLOOKUP(A15, STOCKS!A:W, 2, FALSE), "")) -> 亞航 | C15: =IF(ISBLANK(A15), "", IFERROR(VLOOKUP(A15, STOCKS!A:W, 3, FALSE), "")) -> 航運業 | D15: =IF(ISBLANK(A15), "", IFERROR(VLOOKUP(A15, category!A:C, 3, FALSE), "")) -> 軍工 | E15: =IF(ISBLANK(A15), "", IFERROR(VLOOKUP(A15, STOCKS!A:W, 4, FALSE), "")) -> 50.1 | F15: =IF(ISBLANK(A15), "", IFERROR(VLOOKUP(A15, STOCKS!A:W, 5, FALSE), "")) -> 0.8 | G15: =IF(ISBLANK(A15), "", IFERROR(VLOOKUP(A15, STOCKS!A:W, 6, FALSE), "")) -> 1.62 | H15: =IF(ISBLANK(A15), "", IFERROR(VLOOKUP(A15, STOCKS!A:W, 7, FALSE), "")) -> '+++++ | I15: =IF(ISBLANK(A15), "", IFERROR(VLOOKUP(A15, STOCKS!A:W, 8, FALSE), "")) -> 10.55 | J15: =IF(ISBLANK(A15), "", IFERROR(VLOOKUP(A15, STOCKS!A:W, 9, FALSE), "")) -> 0 | K15: =IF(ISBLANK(A15), "", IFERROR(VLOOKUP(A15, STOCKS!A:W, 10, FALSE), "")) -> 1545 | L15: =IF(ISBLANK(A15), "", IFERROR(VLOOKUP(A15, STOCKS!A:W, 11, FALSE), "")) -> 0.74 | M15: =IF(ISBLANK(A15), "", IFERROR(VLOOKUP(A15, STOCKS!A:W, 12, FALSE), "")) -> 48.21 | N15: =IF(ISBLANK(A15), "", IFERROR(VLOOKUP(A15, STOCKS!A:W, 13, FALSE), "")) -> 47.23 | O15: =IF(ISBLANK(A15), "", IFERROR(VLOOKUP(A15, STOCKS!A:W, 14, FALSE), "")) -> 47.83 | P15: =IF(ISBLANK(A15), "", IFERROR(VLOOKUP(A15, STOCKS!A:W, 15, FALSE), "")) -> 416 | Q15: =IF(ISBLANK(A15), "", IFERROR(VLOOKUP(A15, STOCKS!A:W, 16, FALSE), "")) -> '+-+++ | R15: =IF(ISBLANK(A15), "", IFERROR(VLOOKUP(A15, STOCKS!A:W, 17, FALSE), "")) -> 0 | S15: =IF(ISBLANK(A15), "", IFERROR(VLOOKUP(A15, STOCKS!A:W, 18, FALSE), "")) -> -17 | T15: =IF(ISBLANK(A15), "", IFERROR(VLOOKUP(A15, STOCKS!A:W, 19, FALSE), "")) -> 494 | U15: =IF(ISBLANK(A15), "", IFERROR(VLOOKUP(A15, STOCKS!A:W, 20, FALSE), "")) -> 31.97 | V15: =IF(ISBLANK(A15), "", IFERROR(VLOOKUP(A15, STOCKS!A:W, 21, FALSE), "")) -> 46132 | W15: =IF(ISBLANK(A15), "", IFERROR(VLOOKUP(A15, STOCKS!A:W, 22, FALSE), ""))
A16: 6753 | B16: =IF(ISBLANK(A16), "", IFERROR(VLOOKUP(A16, STOCKS!A:W, 2, FALSE), "")) -> 龍德造船 | C16: =IF(ISBLANK(A16), "", IFERROR(VLOOKUP(A16, STOCKS!A:W, 3, FALSE), "")) -> 航運業 | D16: =IF(ISBLANK(A16), "", IFERROR(VLOOKUP(A16, category!A:C, 3, FALSE), "")) -> 軍工 | E16: =IF(ISBLANK(A16), "", IFERROR(VLOOKUP(A16, STOCKS!A:W, 4, FALSE), "")) -> 144 | F16: =IF(ISBLANK(A16), "", IFERROR(VLOOKUP(A16, STOCKS!A:W, 5, FALSE), "")) -> 5.5 | G16: =IF(ISBLANK(A16), "", IFERROR(VLOOKUP(A16, STOCKS!A:W, 6, FALSE), "")) -> 3.97 | H16: =IF(ISBLANK(A16), "", IFERROR(VLOOKUP(A16, STOCKS!A:W, 7, FALSE), "")) -> '+++-+ | I16: =IF(ISBLANK(A16), "", IFERROR(VLOOKUP(A16, STOCKS!A:W, 8, FALSE), "")) -> 14.62 | J16: =IF(ISBLANK(A16), "", IFERROR(VLOOKUP(A16, STOCKS!A:W, 9, FALSE), "")) -> 0 | K16: =IF(ISBLANK(A16), "", IFERROR(VLOOKUP(A16, STOCKS!A:W, 10, FALSE), "")) -> 2714 | L16: =IF(ISBLANK(A16), "", IFERROR(VLOOKUP(A16, STOCKS!A:W, 11, FALSE), "")) -> 2.31 | M16: =IF(ISBLANK(A16), "", IFERROR(VLOOKUP(A16, STOCKS!A:W, 12, FALSE), "")) -> 138.6 | N16: =IF(ISBLANK(A16), "", IFERROR(VLOOKUP(A16, STOCKS!A:W, 13, FALSE), "")) -> 132.75 | O16: =IF(ISBLANK(A16), "", IFERROR(VLOOKUP(A16, STOCKS!A:W, 14, FALSE), "")) -> 130.88 | P16: =IF(ISBLANK(A16), "", IFERROR(VLOOKUP(A16, STOCKS!A:W, 15, FALSE), "")) -> 343 | Q16: =IF(ISBLANK(A16), "", IFERROR(VLOOKUP(A16, STOCKS!A:W, 16, FALSE), "")) -> '+++++ | R16: =IF(ISBLANK(A16), "", IFERROR(VLOOKUP(A16, STOCKS!A:W, 17, FALSE), "")) -> 0 | S16: =IF(ISBLANK(A16), "", IFERROR(VLOOKUP(A16, STOCKS!A:W, 18, FALSE), "")) -> 191 | T16: =IF(ISBLANK(A16), "", IFERROR(VLOOKUP(A16, STOCKS!A:W, 19, FALSE), "")) -> 1149 | U16: =IF(ISBLANK(A16), "", IFERROR(VLOOKUP(A16, STOCKS!A:W, 20, FALSE), "")) -> 42.34 | V16: =IF(ISBLANK(A16), "", IFERROR(VLOOKUP(A16, STOCKS!A:W, 21, FALSE), "")) -> 46132 | W16: =IF(ISBLANK(A16), "", IFERROR(VLOOKUP(A16, STOCKS!A:W, 22, FALSE), ""))
A17: 題材-生醫
A18: 1734 | B18: =IF(ISBLANK(A18), "", IFERROR(VLOOKUP(A18, STOCKS!A:W, 2, FALSE), "")) -> 杏輝 | C18: =IF(ISBLANK(A18), "", IFERROR(VLOOKUP(A18, STOCKS!A:W, 3, FALSE), "")) -> 生技醫療業 | D18: =IF(ISBLANK(A18), "", IFERROR(VLOOKUP(A18, category!A:C, 3, FALSE), "")) -> 生醫 | E18: =IF(ISBLANK(A18), "", IFERROR(VLOOKUP(A18, STOCKS!A:W, 4, FALSE), "")) -> 32.2 | F18: =IF(ISBLANK(A18), "", IFERROR(VLOOKUP(A18, STOCKS!A:W, 5, FALSE), "")) -> 0.05 | G18: =IF(ISBLANK(A18), "", IFERROR(VLOOKUP(A18, STOCKS!A:W, 6, FALSE), "")) -> 0.16 | H18: =IF(ISBLANK(A18), "", IFERROR(VLOOKUP(A18, STOCKS!A:W, 7, FALSE), "")) -> '+++++ | I18: =IF(ISBLANK(A18), "", IFERROR(VLOOKUP(A18, STOCKS!A:W, 8, FALSE), "")) -> 1.58 | J18: =IF(ISBLANK(A18), "", IFERROR(VLOOKUP(A18, STOCKS!A:W, 9, FALSE), "")) -> 0 | K18: =IF(ISBLANK(A18), "", IFERROR(VLOOKUP(A18, STOCKS!A:W, 10, FALSE), "")) -> 313 | L18: =IF(ISBLANK(A18), "", IFERROR(VLOOKUP(A18, STOCKS!A:W, 11, FALSE), "")) -> 0.16 | M18: =IF(ISBLANK(A18), "", IFERROR(VLOOKUP(A18, STOCKS!A:W, 12, FALSE), "")) -> 32.04 | N18: =IF(ISBLANK(A18), "", IFERROR(VLOOKUP(A18, STOCKS!A:W, 13, FALSE), "")) -> 31.84 | O18: =IF(ISBLANK(A18), "", IFERROR(VLOOKUP(A18, STOCKS!A:W, 14, FALSE), "")) -> 31.46 | P18: =IF(ISBLANK(A18), "", IFERROR(VLOOKUP(A18, STOCKS!A:W, 15, FALSE), "")) -> 0 | Q18: =IF(ISBLANK(A18), "", IFERROR(VLOOKUP(A18, STOCKS!A:W, 16, FALSE), "")) -> '++++- | R18: =IF(ISBLANK(A18), "", IFERROR(VLOOKUP(A18, STOCKS!A:W, 17, FALSE), "")) -> 0 | S18: =IF(ISBLANK(A18), "", IFERROR(VLOOKUP(A18, STOCKS!A:W, 18, FALSE), "")) -> 5 | T18: =IF(ISBLANK(A18), "", IFERROR(VLOOKUP(A18, STOCKS!A:W, 19, FALSE), "")) -> 22 | U18: =IF(ISBLANK(A18), "", IFERROR(VLOOKUP(A18, STOCKS!A:W, 20, FALSE), "")) -> 7.03 | V18: =IF(ISBLANK(A18), "", IFERROR(VLOOKUP(A18, STOCKS!A:W, 21, FALSE), "")) -> 46132 | W18: =IF(ISBLANK(A18), "", IFERROR(VLOOKUP(A18, STOCKS!A:W, 22, FALSE), ""))
A19: 1760 | B19: =IF(ISBLANK(A19), "", IFERROR(VLOOKUP(A19, STOCKS!A:W, 2, FALSE), "")) -> 寶齡富錦 | C19: =IF(ISBLANK(A19), "", IFERROR(VLOOKUP(A19, STOCKS!A:W, 3, FALSE), "")) -> 生技醫療業 | D19: =IF(ISBLANK(A19), "", IFERROR(VLOOKUP(A19, category!A:C, 3, FALSE), "")) -> 生醫 | E19: =IF(ISBLANK(A19), "", IFERROR(VLOOKUP(A19, STOCKS!A:W, 4, FALSE), "")) -> 65.1 | F19: =IF(ISBLANK(A19), "", IFERROR(VLOOKUP(A19, STOCKS!A:W, 5, FALSE), "")) -> 0.6 | G19: =IF(ISBLANK(A19), "", IFERROR(VLOOKUP(A19, STOCKS!A:W, 6, FALSE), "")) -> 0.93 | H19: =IF(ISBLANK(A19), "", IFERROR(VLOOKUP(A19, STOCKS!A:W, 7, FALSE), "")) -> '-++-+ | I19: =IF(ISBLANK(A19), "", IFERROR(VLOOKUP(A19, STOCKS!A:W, 8, FALSE), "")) -> 1.89 | J19: =IF(ISBLANK(A19), "", IFERROR(VLOOKUP(A19, STOCKS!A:W, 9, FALSE), "")) -> 0 | K19: =IF(ISBLANK(A19), "", IFERROR(VLOOKUP(A19, STOCKS!A:W, 10, FALSE), "")) -> 236 | L19: =IF(ISBLANK(A19), "", IFERROR(VLOOKUP(A19, STOCKS!A:W, 11, FALSE), "")) -> 0.28 | M19: =IF(ISBLANK(A19), "", IFERROR(VLOOKUP(A19, STOCKS!A:W, 12, FALSE), "")) -> 64.3 | N19: =IF(ISBLANK(A19), "", IFERROR(VLOOKUP(A19, STOCKS!A:W, 13, FALSE), "")) -> 64.26 | O19: =IF(ISBLANK(A19), "", IFERROR(VLOOKUP(A19, STOCKS!A:W, 14, FALSE), "")) -> 63.85 | P19: =IF(ISBLANK(A19), "", IFERROR(VLOOKUP(A19, STOCKS!A:W, 15, FALSE), "")) -> 65 | Q19: =IF(ISBLANK(A19), "", IFERROR(VLOOKUP(A19, STOCKS!A:W, 16, FALSE), "")) -> '-++++ | R19: =IF(ISBLANK(A19), "", IFERROR(VLOOKUP(A19, STOCKS!A:W, 17, FALSE), "")) -> 0 | S19: =IF(ISBLANK(A19), "", IFERROR(VLOOKUP(A19, STOCKS!A:W, 18, FALSE), "")) -> 0 | T19: =IF(ISBLANK(A19), "", IFERROR(VLOOKUP(A19, STOCKS!A:W, 19, FALSE), "")) -> 22 | U19: =IF(ISBLANK(A19), "", IFERROR(VLOOKUP(A19, STOCKS!A:W, 20, FALSE), "")) -> 9.32 | V19: =IF(ISBLANK(A19), "", IFERROR(VLOOKUP(A19, STOCKS!A:W, 21, FALSE), "")) -> 46132 | W19: =IF(ISBLANK(A19), "", IFERROR(VLOOKUP(A19, STOCKS!A:W, 22, FALSE), ""))
A20: 1795 | B20: =IF(ISBLANK(A20), "", IFERROR(VLOOKUP(A20, STOCKS!A:W, 2, FALSE), "")) -> 美時 | C20: =IF(ISBLANK(A20), "", IFERROR(VLOOKUP(A20, STOCKS!A:W, 3, FALSE), "")) -> 生技醫療業 | D20: =IF(ISBLANK(A20), "", IFERROR(VLOOKUP(A20, category!A:C, 3, FALSE), "")) -> 生醫 | E20: =IF(ISBLANK(A20), "", IFERROR(VLOOKUP(A20, STOCKS!A:W, 4, FALSE), "")) -> 226 | F20: =IF(ISBLANK(A20), "", IFERROR(VLOOKUP(A20, STOCKS!A:W, 5, FALSE), "")) -> -8.5 | G20: =IF(ISBLANK(A20), "", IFERROR(VLOOKUP(A20, STOCKS!A:W, 6, FALSE), "")) -> -3.62 | H20: =IF(ISBLANK(A20), "", IFERROR(VLOOKUP(A20, STOCKS!A:W, 7, FALSE), "")) -> '-++-- | I20: =IF(ISBLANK(A20), "", IFERROR(VLOOKUP(A20, STOCKS!A:W, 8, FALSE), "")) -> -4.67 | J20: =IF(ISBLANK(A20), "", IFERROR(VLOOKUP(A20, STOCKS!A:W, 9, FALSE), "")) -> 1 | K20: =IF(ISBLANK(A20), "", IFERROR(VLOOKUP(A20, STOCKS!A:W, 10, FALSE), "")) -> 4548 | L20: =IF(ISBLANK(A20), "", IFERROR(VLOOKUP(A20, STOCKS!A:W, 11, FALSE), "")) -> 1.7 | M20: =IF(ISBLANK(A20), "", IFERROR(VLOOKUP(A20, STOCKS!A:W, 12, FALSE), "")) -> 233.2 | N20: =IF(ISBLANK(A20), "", IFERROR(VLOOKUP(A20, STOCKS!A:W, 13, FALSE), "")) -> 226.05 | O20: =IF(ISBLANK(A20), "", IFERROR(VLOOKUP(A20, STOCKS!A:W, 14, FALSE), "")) -> 218.38 | P20: =IF(ISBLANK(A20), "", IFERROR(VLOOKUP(A20, STOCKS!A:W, 15, FALSE), "")) -> -179 | Q20: =IF(ISBLANK(A20), "", IFERROR(VLOOKUP(A20, STOCKS!A:W, 16, FALSE), "")) -> '----- | R20: =IF(ISBLANK(A20), "", IFERROR(VLOOKUP(A20, STOCKS!A:W, 17, FALSE), "")) -> -82 | S20: =IF(ISBLANK(A20), "", IFERROR(VLOOKUP(A20, STOCKS!A:W, 18, FALSE), "")) -> -134 | T20: =IF(ISBLANK(A20), "", IFERROR(VLOOKUP(A20, STOCKS!A:W, 19, FALSE), "")) -> 832 | U20: =IF(ISBLANK(A20), "", IFERROR(VLOOKUP(A20, STOCKS!A:W, 20, FALSE), "")) -> 18.29 | V20: =IF(ISBLANK(A20), "", IFERROR(VLOOKUP(A20, STOCKS!A:W, 21, FALSE), "")) -> 46132 | W20: =IF(ISBLANK(A20), "", IFERROR(VLOOKUP(A20, STOCKS!A:W, 22, FALSE), ""))
A21: 4128 | B21: =IF(ISBLANK(A21), "", IFERROR(VLOOKUP(A21, STOCKS!A:W, 2, FALSE), "")) -> 中天 | C21: =IF(ISBLANK(A21), "", IFERROR(VLOOKUP(A21, STOCKS!A:W, 3, FALSE), "")) -> 生技醫療業 | D21: =IF(ISBLANK(A21), "", IFERROR(VLOOKUP(A21, category!A:C, 3, FALSE), "")) -> 生醫 | E21: =IF(ISBLANK(A21), "", IFERROR(VLOOKUP(A21, STOCKS!A:W, 4, FALSE), "")) -> 16.75 | F21: =IF(ISBLANK(A21), "", IFERROR(VLOOKUP(A21, STOCKS!A:W, 5, FALSE), "")) -> -0.4 | G21: =IF(ISBLANK(A21), "", IFERROR(VLOOKUP(A21, STOCKS!A:W, 6, FALSE), "")) -> -2.33 | H21: =IF(ISBLANK(A21), "", IFERROR(VLOOKUP(A21, STOCKS!A:W, 7, FALSE), "")) -> '-++-- | I21: =IF(ISBLANK(A21), "", IFERROR(VLOOKUP(A21, STOCKS!A:W, 8, FALSE), "")) -> -1.02 | J21: =IF(ISBLANK(A21), "", IFERROR(VLOOKUP(A21, STOCKS!A:W, 9, FALSE), "")) -> 0 | K21: =IF(ISBLANK(A21), "", IFERROR(VLOOKUP(A21, STOCKS!A:W, 10, FALSE), "")) -> 1795 | L21: =IF(ISBLANK(A21), "", IFERROR(VLOOKUP(A21, STOCKS!A:W, 11, FALSE), "")) -> 0.31 | M21: =IF(ISBLANK(A21), "", IFERROR(VLOOKUP(A21, STOCKS!A:W, 12, FALSE), "")) -> 17.17 | N21: =IF(ISBLANK(A21), "", IFERROR(VLOOKUP(A21, STOCKS!A:W, 13, FALSE), "")) -> 17.07 | O21: =IF(ISBLANK(A21), "", IFERROR(VLOOKUP(A21, STOCKS!A:W, 14, FALSE), "")) -> 17.01 | P21: =IF(ISBLANK(A21), "", IFERROR(VLOOKUP(A21, STOCKS!A:W, 15, FALSE), "")) -> -423 | Q21: =IF(ISBLANK(A21), "", IFERROR(VLOOKUP(A21, STOCKS!A:W, 16, FALSE), "")) -> '--+-- | R21: =IF(ISBLANK(A21), "", IFERROR(VLOOKUP(A21, STOCKS!A:W, 17, FALSE), "")) -> 0 | S21: =IF(ISBLANK(A21), "", IFERROR(VLOOKUP(A21, STOCKS!A:W, 18, FALSE), "")) -> -2 | T21: =IF(ISBLANK(A21), "", IFERROR(VLOOKUP(A21, STOCKS!A:W, 19, FALSE), "")) -> 355 | U21: =IF(ISBLANK(A21), "", IFERROR(VLOOKUP(A21, STOCKS!A:W, 20, FALSE), "")) -> 19.78 | V21: =IF(ISBLANK(A21), "", IFERROR(VLOOKUP(A21, STOCKS!A:W, 21, FALSE), "")) -> 46132 | W21: =IF(ISBLANK(A21), "", IFERROR(VLOOKUP(A21, STOCKS!A:W, 22, FALSE), ""))
A22: 4142 | B22: =IF(ISBLANK(A22), "", IFERROR(VLOOKUP(A22, STOCKS!A:W, 2, FALSE), "")) -> 國光生 | C22: =IF(ISBLANK(A22), "", IFERROR(VLOOKUP(A22, STOCKS!A:W, 3, FALSE), "")) -> 生技醫療業 | D22: =IF(ISBLANK(A22), "", IFERROR(VLOOKUP(A22, category!A:C, 3, FALSE), "")) -> 生醫 | E22: =IF(ISBLANK(A22), "", IFERROR(VLOOKUP(A22, STOCKS!A:W, 4, FALSE), "")) -> 18.05 | F22: =IF(ISBLANK(A22), "", IFERROR(VLOOKUP(A22, STOCKS!A:W, 5, FALSE), "")) -> -0.45 | G22: =IF(ISBLANK(A22), "", IFERROR(VLOOKUP(A22, STOCKS!A:W, 6, FALSE), "")) -> -2.43 | H22: =IF(ISBLANK(A22), "", IFERROR(VLOOKUP(A22, STOCKS!A:W, 7, FALSE), "")) -> '-++-- | I22: =IF(ISBLANK(A22), "", IFERROR(VLOOKUP(A22, STOCKS!A:W, 8, FALSE), "")) -> -1.86 | J22: =IF(ISBLANK(A22), "", IFERROR(VLOOKUP(A22, STOCKS!A:W, 9, FALSE), "")) -> 0 | K22: =IF(ISBLANK(A22), "", IFERROR(VLOOKUP(A22, STOCKS!A:W, 10, FALSE), "")) -> 1491 | L22: =IF(ISBLANK(A22), "", IFERROR(VLOOKUP(A22, STOCKS!A:W, 11, FALSE), "")) -> 0.35 | M22: =IF(ISBLANK(A22), "", IFERROR(VLOOKUP(A22, STOCKS!A:W, 12, FALSE), "")) -> 18.38 | N22: =IF(ISBLANK(A22), "", IFERROR(VLOOKUP(A22, STOCKS!A:W, 13, FALSE), "")) -> 18.32 | O22: =IF(ISBLANK(A22), "", IFERROR(VLOOKUP(A22, STOCKS!A:W, 14, FALSE), "")) -> 18.41 | P22: =IF(ISBLANK(A22), "", IFERROR(VLOOKUP(A22, STOCKS!A:W, 15, FALSE), "")) -> -696 | Q22: =IF(ISBLANK(A22), "", IFERROR(VLOOKUP(A22, STOCKS!A:W, 16, FALSE), "")) -> '-++-- | R22: =IF(ISBLANK(A22), "", IFERROR(VLOOKUP(A22, STOCKS!A:W, 17, FALSE), "")) -> 0 | S22: =IF(ISBLANK(A22), "", IFERROR(VLOOKUP(A22, STOCKS!A:W, 18, FALSE), "")) -> -1 | T22: =IF(ISBLANK(A22), "", IFERROR(VLOOKUP(A22, STOCKS!A:W, 19, FALSE), "")) -> 157 | U22: =IF(ISBLANK(A22), "", IFERROR(VLOOKUP(A22, STOCKS!A:W, 20, FALSE), "")) -> 10.53 | V22: =IF(ISBLANK(A22), "", IFERROR(VLOOKUP(A22, STOCKS!A:W, 21, FALSE), "")) -> 46132 | W22: =IF(ISBLANK(A22), "", IFERROR(VLOOKUP(A22, STOCKS!A:W, 22, FALSE), ""))
A23: 4736 | B23: =IF(ISBLANK(A23), "", IFERROR(VLOOKUP(A23, STOCKS!A:W, 2, FALSE), "")) -> 泰博 | C23: =IF(ISBLANK(A23), "", IFERROR(VLOOKUP(A23, STOCKS!A:W, 3, FALSE), "")) -> 生技醫療業 | D23: =IF(ISBLANK(A23), "", IFERROR(VLOOKUP(A23, category!A:C, 3, FALSE), "")) -> 生醫 | E23: =IF(ISBLANK(A23), "", IFERROR(VLOOKUP(A23, STOCKS!A:W, 4, FALSE), "")) -> 124 | F23: =IF(ISBLANK(A23), "", IFERROR(VLOOKUP(A23, STOCKS!A:W, 5, FALSE), "")) -> -1.5 | G23: =IF(ISBLANK(A23), "", IFERROR(VLOOKUP(A23, STOCKS!A:W, 6, FALSE), "")) -> -1.2 | H23: =IF(ISBLANK(A23), "", IFERROR(VLOOKUP(A23, STOCKS!A:W, 7, FALSE), "")) -> '+-+-- | I23: =IF(ISBLANK(A23), "", IFERROR(VLOOKUP(A23, STOCKS!A:W, 8, FALSE), "")) -> -0.79 | J23: =IF(ISBLANK(A23), "", IFERROR(VLOOKUP(A23, STOCKS!A:W, 9, FALSE), "")) -> 0 | K23: =IF(ISBLANK(A23), "", IFERROR(VLOOKUP(A23, STOCKS!A:W, 10, FALSE), "")) -> 377 | L23: =IF(ISBLANK(A23), "", IFERROR(VLOOKUP(A23, STOCKS!A:W, 11, FALSE), "")) -> 0.4 | M23: =IF(ISBLANK(A23), "", IFERROR(VLOOKUP(A23, STOCKS!A:W, 12, FALSE), "")) -> 125.5 | N23: =IF(ISBLANK(A23), "", IFERROR(VLOOKUP(A23, STOCKS!A:W, 13, FALSE), "")) -> 124.8 | O23: =IF(ISBLANK(A23), "", IFERROR(VLOOKUP(A23, STOCKS!A:W, 14, FALSE), "")) -> 124.03 | P23: =IF(ISBLANK(A23), "", IFERROR(VLOOKUP(A23, STOCKS!A:W, 15, FALSE), "")) -> -26 | Q23: =IF(ISBLANK(A23), "", IFERROR(VLOOKUP(A23, STOCKS!A:W, 16, FALSE), "")) -> '+-+-- | R23: =IF(ISBLANK(A23), "", IFERROR(VLOOKUP(A23, STOCKS!A:W, 17, FALSE), "")) -> -29 | S23: =IF(ISBLANK(A23), "", IFERROR(VLOOKUP(A23, STOCKS!A:W, 18, FALSE), "")) -> 1 | T23: =IF(ISBLANK(A23), "", IFERROR(VLOOKUP(A23, STOCKS!A:W, 19, FALSE), "")) -> 11 | U23: =IF(ISBLANK(A23), "", IFERROR(VLOOKUP(A23, STOCKS!A:W, 20, FALSE), "")) -> 2.92 | V23: =IF(ISBLANK(A23), "", IFERROR(VLOOKUP(A23, STOCKS!A:W, 21, FALSE), "")) -> 46132 | W23: =IF(ISBLANK(A23), "", IFERROR(VLOOKUP(A23, STOCKS!A:W, 22, FALSE), ""))
A24: 4743 | B24: =IF(ISBLANK(A24), "", IFERROR(VLOOKUP(A24, STOCKS!A:W, 2, FALSE), "")) -> 合一 | C24: =IF(ISBLANK(A24), "", IFERROR(VLOOKUP(A24, STOCKS!A:W, 3, FALSE), "")) -> 生技醫療業 | D24: =IF(ISBLANK(A24), "", IFERROR(VLOOKUP(A24, category!A:C, 3, FALSE), "")) -> 生醫 | E24: =IF(ISBLANK(A24), "", IFERROR(VLOOKUP(A24, STOCKS!A:W, 4, FALSE), "")) -> 52.4 | F24: =IF(ISBLANK(A24), "", IFERROR(VLOOKUP(A24, STOCKS!A:W, 5, FALSE), "")) -> -2 | G24: =IF(ISBLANK(A24), "", IFERROR(VLOOKUP(A24, STOCKS!A:W, 6, FALSE), "")) -> -3.68 | H24: =IF(ISBLANK(A24), "", IFERROR(VLOOKUP(A24, STOCKS!A:W, 7, FALSE), "")) -> '-++-- | I24: =IF(ISBLANK(A24), "", IFERROR(VLOOKUP(A24, STOCKS!A:W, 8, FALSE), "")) -> -1.37 | J24: =IF(ISBLANK(A24), "", IFERROR(VLOOKUP(A24, STOCKS!A:W, 9, FALSE), "")) -> 0 | K24: =IF(ISBLANK(A24), "", IFERROR(VLOOKUP(A24, STOCKS!A:W, 10, FALSE), "")) -> 2132 | L24: =IF(ISBLANK(A24), "", IFERROR(VLOOKUP(A24, STOCKS!A:W, 11, FALSE), "")) -> 0.44 | M24: =IF(ISBLANK(A24), "", IFERROR(VLOOKUP(A24, STOCKS!A:W, 12, FALSE), "")) -> 54.04 | N24: =IF(ISBLANK(A24), "", IFERROR(VLOOKUP(A24, STOCKS!A:W, 13, FALSE), "")) -> 53.85 | O24: =IF(ISBLANK(A24), "", IFERROR(VLOOKUP(A24, STOCKS!A:W, 14, FALSE), "")) -> 53.17 | P24: =IF(ISBLANK(A24), "", IFERROR(VLOOKUP(A24, STOCKS!A:W, 15, FALSE), "")) -> -565 | Q24: =IF(ISBLANK(A24), "", IFERROR(VLOOKUP(A24, STOCKS!A:W, 16, FALSE), "")) -> '+++-- | R24: =IF(ISBLANK(A24), "", IFERROR(VLOOKUP(A24, STOCKS!A:W, 17, FALSE), "")) -> 0 | S24: =IF(ISBLANK(A24), "", IFERROR(VLOOKUP(A24, STOCKS!A:W, 18, FALSE), "")) -> 4 | T24: =IF(ISBLANK(A24), "", IFERROR(VLOOKUP(A24, STOCKS!A:W, 19, FALSE), "")) -> 425 | U24: =IF(ISBLANK(A24), "", IFERROR(VLOOKUP(A24, STOCKS!A:W, 20, FALSE), "")) -> 19.93 | V24: =IF(ISBLANK(A24), "", IFERROR(VLOOKUP(A24, STOCKS!A:W, 21, FALSE), "")) -> 46132 | W24: =IF(ISBLANK(A24), "", IFERROR(VLOOKUP(A24, STOCKS!A:W, 22, FALSE), ""))
A25: 6446 | B25: =IF(ISBLANK(A25), "", IFERROR(VLOOKUP(A25, STOCKS!A:W, 2, FALSE), "")) -> 藥華藥 | C25: =IF(ISBLANK(A25), "", IFERROR(VLOOKUP(A25, STOCKS!A:W, 3, FALSE), "")) -> 生技醫療業 | D25: =IF(ISBLANK(A25), "", IFERROR(VLOOKUP(A25, category!A:C, 3, FALSE), "")) -> 生醫 | E25: =IF(ISBLANK(A25), "", IFERROR(VLOOKUP(A25, STOCKS!A:W, 4, FALSE), "")) -> 658 | F25: =IF(ISBLANK(A25), "", IFERROR(VLOOKUP(A25, STOCKS!A:W, 5, FALSE), "")) -> 5 | G25: =IF(ISBLANK(A25), "", IFERROR(VLOOKUP(A25, STOCKS!A:W, 6, FALSE), "")) -> 0.77 | H25: =IF(ISBLANK(A25), "", IFERROR(VLOOKUP(A25, STOCKS!A:W, 7, FALSE), "")) -> '-++-+ | I25: =IF(ISBLANK(A25), "", IFERROR(VLOOKUP(A25, STOCKS!A:W, 8, FALSE), "")) -> 1.73 | J25: =IF(ISBLANK(A25), "", IFERROR(VLOOKUP(A25, STOCKS!A:W, 9, FALSE), "")) -> 0 | K25: =IF(ISBLANK(A25), "", IFERROR(VLOOKUP(A25, STOCKS!A:W, 10, FALSE), "")) -> 2282 | L25: =IF(ISBLANK(A25), "", IFERROR(VLOOKUP(A25, STOCKS!A:W, 11, FALSE), "")) -> 0.6 | M25: =IF(ISBLANK(A25), "", IFERROR(VLOOKUP(A25, STOCKS!A:W, 12, FALSE), "")) -> 652.6 | N25: =IF(ISBLANK(A25), "", IFERROR(VLOOKUP(A25, STOCKS!A:W, 13, FALSE), "")) -> 647.3 | O25: =IF(ISBLANK(A25), "", IFERROR(VLOOKUP(A25, STOCKS!A:W, 14, FALSE), "")) -> 637.6 | P25: =IF(ISBLANK(A25), "", IFERROR(VLOOKUP(A25, STOCKS!A:W, 15, FALSE), "")) -> 200 | Q25: =IF(ISBLANK(A25), "", IFERROR(VLOOKUP(A25, STOCKS!A:W, 16, FALSE), "")) -> '-++-+ | R25: =IF(ISBLANK(A25), "", IFERROR(VLOOKUP(A25, STOCKS!A:W, 17, FALSE), "")) -> 116 | S25: =IF(ISBLANK(A25), "", IFERROR(VLOOKUP(A25, STOCKS!A:W, 18, FALSE), "")) -> 19 | T25: =IF(ISBLANK(A25), "", IFERROR(VLOOKUP(A25, STOCKS!A:W, 19, FALSE), "")) -> 802 | U25: =IF(ISBLANK(A25), "", IFERROR(VLOOKUP(A25, STOCKS!A:W, 20, FALSE), "")) -> 35.14 | V25: =IF(ISBLANK(A25), "", IFERROR(VLOOKUP(A25, STOCKS!A:W, 21, FALSE), "")) -> 46132 | W25: =IF(ISBLANK(A25), "", IFERROR(VLOOKUP(A25, STOCKS!A:W, 22, FALSE), ""))
A26: 6547 | B26: =IF(ISBLANK(A26), "", IFERROR(VLOOKUP(A26, STOCKS!A:W, 2, FALSE), "")) -> 高端疫苗 | C26: =IF(ISBLANK(A26), "", IFERROR(VLOOKUP(A26, STOCKS!A:W, 3, FALSE), "")) -> 生技醫療業 | D26: =IF(ISBLANK(A26), "", IFERROR(VLOOKUP(A26, category!A:C, 3, FALSE), "")) -> 生醫 | E26: =IF(ISBLANK(A26), "", IFERROR(VLOOKUP(A26, STOCKS!A:W, 4, FALSE), "")) -> 48.5 | F26: =IF(ISBLANK(A26), "", IFERROR(VLOOKUP(A26, STOCKS!A:W, 5, FALSE), "")) -> 0.5 | G26: =IF(ISBLANK(A26), "", IFERROR(VLOOKUP(A26, STOCKS!A:W, 6, FALSE), "")) -> 1.04 | H26: =IF(ISBLANK(A26), "", IFERROR(VLOOKUP(A26, STOCKS!A:W, 7, FALSE), "")) -> '----+ | I26: =IF(ISBLANK(A26), "", IFERROR(VLOOKUP(A26, STOCKS!A:W, 8, FALSE), "")) -> -13.22 | J26: =IF(ISBLANK(A26), "", IFERROR(VLOOKUP(A26, STOCKS!A:W, 9, FALSE), "")) -> 2 | K26: =IF(ISBLANK(A26), "", IFERROR(VLOOKUP(A26, STOCKS!A:W, 10, FALSE), "")) -> 2590 | L26: =IF(ISBLANK(A26), "", IFERROR(VLOOKUP(A26, STOCKS!A:W, 11, FALSE), "")) -> 0.79 | M26: =IF(ISBLANK(A26), "", IFERROR(VLOOKUP(A26, STOCKS!A:W, 12, FALSE), "")) -> 49.92 | N26: =IF(ISBLANK(A26), "", IFERROR(VLOOKUP(A26, STOCKS!A:W, 13, FALSE), "")) -> 54.05 | O26: =IF(ISBLANK(A26), "", IFERROR(VLOOKUP(A26, STOCKS!A:W, 14, FALSE), "")) -> 54.95 | P26: =IF(ISBLANK(A26), "", IFERROR(VLOOKUP(A26, STOCKS!A:W, 15, FALSE), "")) -> 59 | Q26: =IF(ISBLANK(A26), "", IFERROR(VLOOKUP(A26, STOCKS!A:W, 16, FALSE), "")) -> '-+--+ | R26: =IF(ISBLANK(A26), "", IFERROR(VLOOKUP(A26, STOCKS!A:W, 17, FALSE), "")) -> 0 | S26: =IF(ISBLANK(A26), "", IFERROR(VLOOKUP(A26, STOCKS!A:W, 18, FALSE), "")) -> -50 | T26: =IF(ISBLANK(A26), "", IFERROR(VLOOKUP(A26, STOCKS!A:W, 19, FALSE), "")) -> 952 | U26: =IF(ISBLANK(A26), "", IFERROR(VLOOKUP(A26, STOCKS!A:W, 20, FALSE), "")) -> 36.76 | V26: =IF(ISBLANK(A26), "", IFERROR(VLOOKUP(A26, STOCKS!A:W, 21, FALSE), "")) -> 46132 | W26: =IF(ISBLANK(A26), "", IFERROR(VLOOKUP(A26, STOCKS!A:W, 22, FALSE), ""))
A27: 6550 | B27: =IF(ISBLANK(A27), "", IFERROR(VLOOKUP(A27, STOCKS!A:W, 2, FALSE), "")) -> 北極星藥業-KY | C27: =IF(ISBLANK(A27), "", IFERROR(VLOOKUP(A27, STOCKS!A:W, 3, FALSE), "")) -> 生技醫療業 | D27: =IF(ISBLANK(A27), "", IFERROR(VLOOKUP(A27, category!A:C, 3, FALSE), "")) -> 生醫 | E27: =IF(ISBLANK(A27), "", IFERROR(VLOOKUP(A27, STOCKS!A:W, 4, FALSE), "")) -> 18.8 | F27: =IF(ISBLANK(A27), "", IFERROR(VLOOKUP(A27, STOCKS!A:W, 5, FALSE), "")) -> 0 | G27: =IF(ISBLANK(A27), "", IFERROR(VLOOKUP(A27, STOCKS!A:W, 6, FALSE), "")) -> 0 | H27: =IF(ISBLANK(A27), "", IFERROR(VLOOKUP(A27, STOCKS!A:W, 7, FALSE), "")) -> '+-++- | I27: =IF(ISBLANK(A27), "", IFERROR(VLOOKUP(A27, STOCKS!A:W, 8, FALSE), "")) -> 4.98 | J27: =IF(ISBLANK(A27), "", IFERROR(VLOOKUP(A27, STOCKS!A:W, 9, FALSE), "")) -> 0 | K27: =IF(ISBLANK(A27), "", IFERROR(VLOOKUP(A27, STOCKS!A:W, 10, FALSE), "")) -> 1142 | L27: =IF(ISBLANK(A27), "", IFERROR(VLOOKUP(A27, STOCKS!A:W, 11, FALSE), "")) -> 0.13 | M27: =IF(ISBLANK(A27), "", IFERROR(VLOOKUP(A27, STOCKS!A:W, 12, FALSE), "")) -> 18.35 | N27: =IF(ISBLANK(A27), "", IFERROR(VLOOKUP(A27, STOCKS!A:W, 13, FALSE), "")) -> 18.56 | O27: =IF(ISBLANK(A27), "", IFERROR(VLOOKUP(A27, STOCKS!A:W, 14, FALSE), "")) -> 19.18 | P27: =IF(ISBLANK(A27), "", IFERROR(VLOOKUP(A27, STOCKS!A:W, 15, FALSE), "")) -> 157 | Q27: =IF(ISBLANK(A27), "", IFERROR(VLOOKUP(A27, STOCKS!A:W, 16, FALSE), "")) -> '+++++ | R27: =IF(ISBLANK(A27), "", IFERROR(VLOOKUP(A27, STOCKS!A:W, 17, FALSE), "")) -> 0 | S27: =IF(ISBLANK(A27), "", IFERROR(VLOOKUP(A27, STOCKS!A:W, 18, FALSE), "")) -> 6 | T27: =IF(ISBLANK(A27), "", IFERROR(VLOOKUP(A27, STOCKS!A:W, 19, FALSE), "")) -> 0 | U27: =IF(ISBLANK(A27), "", IFERROR(VLOOKUP(A27, STOCKS!A:W, 20, FALSE), "")) -> 0 | V27: =IF(ISBLANK(A27), "", IFERROR(VLOOKUP(A27, STOCKS!A:W, 21, FALSE), "")) -> 46132 | W27: =IF(ISBLANK(A27), "", IFERROR(VLOOKUP(A27, STOCKS!A:W, 22, FALSE), ""))
A28: 1325 | B28: =IF(ISBLANK(A28), "", IFERROR(VLOOKUP(A28, STOCKS!A:W, 2, FALSE), "")) -> 恆大 | C28: =IF(ISBLANK(A28), "", IFERROR(VLOOKUP(A28, STOCKS!A:W, 3, FALSE), "")) -> 塑膠工業 | D28: =IF(ISBLANK(A28), "", IFERROR(VLOOKUP(A28, category!A:C, 3, FALSE), "")) -> 生醫 | E28: =IF(ISBLANK(A28), "", IFERROR(VLOOKUP(A28, STOCKS!A:W, 4, FALSE), "")) -> 26.9 | F28: =IF(ISBLANK(A28), "", IFERROR(VLOOKUP(A28, STOCKS!A:W, 5, FALSE), "")) -> -0.15 | G28: =IF(ISBLANK(A28), "", IFERROR(VLOOKUP(A28, STOCKS!A:W, 6, FALSE), "")) -> -0.55 | H28: =IF(ISBLANK(A28), "", IFERROR(VLOOKUP(A28, STOCKS!A:W, 7, FALSE), "")) -> '-+++- | I28: =IF(ISBLANK(A28), "", IFERROR(VLOOKUP(A28, STOCKS!A:W, 8, FALSE), "")) -> 1.34 | J28: =IF(ISBLANK(A28), "", IFERROR(VLOOKUP(A28, STOCKS!A:W, 9, FALSE), "")) -> 0 | K28: =IF(ISBLANK(A28), "", IFERROR(VLOOKUP(A28, STOCKS!A:W, 10, FALSE), "")) -> 150 | L28: =IF(ISBLANK(A28), "", IFERROR(VLOOKUP(A28, STOCKS!A:W, 11, FALSE), "")) -> 0.18 | M28: =IF(ISBLANK(A28), "", IFERROR(VLOOKUP(A28, STOCKS!A:W, 12, FALSE), "")) -> 26.88 | N28: =IF(ISBLANK(A28), "", IFERROR(VLOOKUP(A28, STOCKS!A:W, 13, FALSE), "")) -> 26.93 | O28: =IF(ISBLANK(A28), "", IFERROR(VLOOKUP(A28, STOCKS!A:W, 14, FALSE), "")) -> 27.14 | P28: =IF(ISBLANK(A28), "", IFERROR(VLOOKUP(A28, STOCKS!A:W, 15, FALSE), "")) -> -23 | Q28: =IF(ISBLANK(A28), "", IFERROR(VLOOKUP(A28, STOCKS!A:W, 16, FALSE), "")) -> '-++-- | R28: =IF(ISBLANK(A28), "", IFERROR(VLOOKUP(A28, STOCKS!A:W, 17, FALSE), "")) -> 0 | S28: =IF(ISBLANK(A28), "", IFERROR(VLOOKUP(A28, STOCKS!A:W, 18, FALSE), "")) -> 0 | T28: =IF(ISBLANK(A28), "", IFERROR(VLOOKUP(A28, STOCKS!A:W, 19, FALSE), "")) -> 18 | U28: =IF(ISBLANK(A28), "", IFERROR(VLOOKUP(A28, STOCKS!A:W, 20, FALSE), "")) -> 12 | V28: =IF(ISBLANK(A28), "", IFERROR(VLOOKUP(A28, STOCKS!A:W, 21, FALSE), "")) -> 46132 | W28: =IF(ISBLANK(A28), "", IFERROR(VLOOKUP(A28, STOCKS!A:W, 22, FALSE), ""))
A29: 8409 | B29: =IF(ISBLANK(A29), "", IFERROR(VLOOKUP(A29, STOCKS!A:W, 2, FALSE), "")) -> 商之器 | C29: =IF(ISBLANK(A29), "", IFERROR(VLOOKUP(A29, STOCKS!A:W, 3, FALSE), "")) -> 生技醫療業 | D29: =IF(ISBLANK(A29), "", IFERROR(VLOOKUP(A29, category!A:C, 3, FALSE), "")) -> 生醫 | E29: =IF(ISBLANK(A29), "", IFERROR(VLOOKUP(A29, STOCKS!A:W, 4, FALSE), "")) -> 20.5 | F29: =IF(ISBLANK(A29), "", IFERROR(VLOOKUP(A29, STOCKS!A:W, 5, FALSE), "")) -> -0.3 | G29: =IF(ISBLANK(A29), "", IFERROR(VLOOKUP(A29, STOCKS!A:W, 6, FALSE), "")) -> -1.44 | H29: =IF(ISBLANK(A29), "", IFERROR(VLOOKUP(A29, STOCKS!A:W, 7, FALSE), "")) -> '-+--- | I29: =IF(ISBLANK(A29), "", IFERROR(VLOOKUP(A29, STOCKS!A:W, 8, FALSE), "")) -> -1.44 | J29: =IF(ISBLANK(A29), "", IFERROR(VLOOKUP(A29, STOCKS!A:W, 9, FALSE), "")) -> 0 | K29: =IF(ISBLANK(A29), "", IFERROR(VLOOKUP(A29, STOCKS!A:W, 10, FALSE), "")) -> 37 | L29: =IF(ISBLANK(A29), "", IFERROR(VLOOKUP(A29, STOCKS!A:W, 11, FALSE), "")) -> 0.12 | M29: =IF(ISBLANK(A29), "", IFERROR(VLOOKUP(A29, STOCKS!A:W, 12, FALSE), "")) -> 20.76 | N29: =IF(ISBLANK(A29), "", IFERROR(VLOOKUP(A29, STOCKS!A:W, 13, FALSE), "")) -> 20.77 | O29: =IF(ISBLANK(A29), "", IFERROR(VLOOKUP(A29, STOCKS!A:W, 14, FALSE), "")) -> 20.73 | P29: =IF(ISBLANK(A29), "", IFERROR(VLOOKUP(A29, STOCKS!A:W, 15, FALSE), "")) -> 5 | Q29: =IF(ISBLANK(A29), "", IFERROR(VLOOKUP(A29, STOCKS!A:W, 16, FALSE), "")) -> '----+ | R29: =IF(ISBLANK(A29), "", IFERROR(VLOOKUP(A29, STOCKS!A:W, 17, FALSE), "")) -> 0 | S29: =IF(ISBLANK(A29), "", IFERROR(VLOOKUP(A29, STOCKS!A:W, 18, FALSE), "")) -> 0 | T29: =IF(ISBLANK(A29), "", IFERROR(VLOOKUP(A29, STOCKS!A:W, 19, FALSE), "")) -> 0 | U29: =IF(ISBLANK(A29), "", IFERROR(VLOOKUP(A29, STOCKS!A:W, 20, FALSE), "")) -> 0 | V29: =IF(ISBLANK(A29), "", IFERROR(VLOOKUP(A29, STOCKS!A:W, 21, FALSE), "")) -> 46132 | W29: =IF(ISBLANK(A29), "", IFERROR(VLOOKUP(A29, STOCKS!A:W, 22, FALSE), ""))
... A36: 4137 | B36: =IF(ISBLANK(A36), "", IFERROR(VLOOKUP(A36, STOCKS!A:W, 2, FALSE), "")) -> 麗豐-KY | C36: =IF(ISBLANK(A36), "", IFERROR(VLOOKUP(A36, STOCKS!A:W, 3, FALSE), "")) -> 生技醫療業 | D36: =IF(ISBLANK(A36), "", IFERROR(VLOOKUP(A36, category!A:C, 3, FALSE), "")) -> 生醫 | E36: =IF(ISBLANK(A36), "", IFERROR(VLOOKUP(A36, STOCKS!A:W, 4, FALSE), "")) -> 109 | F36: =IF(ISBLANK(A36), "", IFERROR(VLOOKUP(A36, STOCKS!A:W, 5, FALSE), "")) -> -1.5 | G36: =IF(ISBLANK(A36), "", IFERROR(VLOOKUP(A36, STOCKS!A:W, 6, FALSE), "")) -> -1.36 | H36: =IF(ISBLANK(A36), "", IFERROR(VLOOKUP(A36, STOCKS!A:W, 7, FALSE), "")) -> '-+++- | I36: =IF(ISBLANK(A36), "", IFERROR(VLOOKUP(A36, STOCKS!A:W, 8, FALSE), "")) -> -0.44 | J36: =IF(ISBLANK(A36), "", IFERROR(VLOOKUP(A36, STOCKS!A:W, 9, FALSE), "")) -> 0 | K36: =IF(ISBLANK(A36), "", IFERROR(VLOOKUP(A36, STOCKS!A:W, 10, FALSE), "")) -> 275 | L36: =IF(ISBLANK(A36), "", IFERROR(VLOOKUP(A36, STOCKS!A:W, 11, FALSE), "")) -> 0.33 | M36: =IF(ISBLANK(A36), "", IFERROR(VLOOKUP(A36, STOCKS!A:W, 12, FALSE), "")) -> 109.5 | N36: =IF(ISBLANK(A36), "", IFERROR(VLOOKUP(A36, STOCKS!A:W, 13, FALSE), "")) -> 108.5 | O36: =IF(ISBLANK(A36), "", IFERROR(VLOOKUP(A36, STOCKS!A:W, 14, FALSE), "")) -> 107.53 | P36: =IF(ISBLANK(A36), "", IFERROR(VLOOKUP(A36, STOCKS!A:W, 15, FALSE), "")) -> -2 | Q36: =IF(ISBLANK(A36), "", IFERROR(VLOOKUP(A36, STOCKS!A:W, 16, FALSE), "")) -> '+--+- | R36: =IF(ISBLANK(A36), "", IFERROR(VLOOKUP(A36, STOCKS!A:W, 17, FALSE), "")) -> 25 | S36: =IF(ISBLANK(A36), "", IFERROR(VLOOKUP(A36, STOCKS!A:W, 18, FALSE), "")) -> 0 | T36: =IF(ISBLANK(A36), "", IFERROR(VLOOKUP(A36, STOCKS!A:W, 19, FALSE), "")) -> 42 | U36: =IF(ISBLANK(A36), "", IFERROR(VLOOKUP(A36, STOCKS!A:W, 20, FALSE), "")) -> 15.27 | V36: =IF(ISBLANK(A36), "", IFERROR(VLOOKUP(A36, STOCKS!A:W, 21, FALSE), "")) -> 46132 | W36: =IF(ISBLANK(A36), "", IFERROR(VLOOKUP(A36, STOCKS!A:W, 22, FALSE), ""))
A37: 題材-PCB
A38: 3189 | B38: =IF(ISBLANK(A38), "", IFERROR(VLOOKUP(A38, STOCKS!A:W, 2, FALSE), "")) -> 景碩 | C38: =IF(ISBLANK(A38), "", IFERROR(VLOOKUP(A38, STOCKS!A:W, 3, FALSE), "")) -> 半導體業 | D38: =IF(ISBLANK(A38), "", IFERROR(VLOOKUP(A38, category!A:C, 3, FALSE), "")) -> PCB/ABF載板 | E38: =IF(ISBLANK(A38), "", IFERROR(VLOOKUP(A38, STOCKS!A:W, 4, FALSE), "")) -> 430.5 | F38: =IF(ISBLANK(A38), "", IFERROR(VLOOKUP(A38, STOCKS!A:W, 5, FALSE), "")) -> 39 | G38: =IF(ISBLANK(A38), "", IFERROR(VLOOKUP(A38, STOCKS!A:W, 6, FALSE), "")) -> 9.96 | H38: =IF(ISBLANK(A38), "", IFERROR(VLOOKUP(A38, STOCKS!A:W, 7, FALSE), "")) -> '+++-+ | I38: =IF(ISBLANK(A38), "", IFERROR(VLOOKUP(A38, STOCKS!A:W, 8, FALSE), "")) -> 16.66 | J38: =IF(ISBLANK(A38), "", IFERROR(VLOOKUP(A38, STOCKS!A:W, 9, FALSE), "")) -> 3 | K38: =IF(ISBLANK(A38), "", IFERROR(VLOOKUP(A38, STOCKS!A:W, 10, FALSE), "")) -> 33909 | L38: =IF(ISBLANK(A38), "", IFERROR(VLOOKUP(A38, STOCKS!A:W, 11, FALSE), "")) -> 6.44 | M38: =IF(ISBLANK(A38), "", IFERROR(VLOOKUP(A38, STOCKS!A:W, 12, FALSE), "")) -> 394 | N38: =IF(ISBLANK(A38), "", IFERROR(VLOOKUP(A38, STOCKS!A:W, 13, FALSE), "")) -> 385.7 | O38: =IF(ISBLANK(A38), "", IFERROR(VLOOKUP(A38, STOCKS!A:W, 14, FALSE), "")) -> 364.3 | P38: =IF(ISBLANK(A38), "", IFERROR(VLOOKUP(A38, STOCKS!A:W, 15, FALSE), "")) -> 4063 | Q38: =IF(ISBLANK(A38), "", IFERROR(VLOOKUP(A38, STOCKS!A:W, 16, FALSE), "")) -> '++--+ | R38: =IF(ISBLANK(A38), "", IFERROR(VLOOKUP(A38, STOCKS!A:W, 17, FALSE), "")) -> 0 | S38: =IF(ISBLANK(A38), "", IFERROR(VLOOKUP(A38, STOCKS!A:W, 18, FALSE), "")) -> 571 | T38: =IF(ISBLANK(A38), "", IFERROR(VLOOKUP(A38, STOCKS!A:W, 19, FALSE), "")) -> 14946 | U38: =IF(ISBLANK(A38), "", IFERROR(VLOOKUP(A38, STOCKS!A:W, 20, FALSE), "")) -> 44.08 | V38: =IF(ISBLANK(A38), "", IFERROR(VLOOKUP(A38, STOCKS!A:W, 21, FALSE), "")) -> 46132 | W38: =IF(ISBLANK(A38), "", IFERROR(VLOOKUP(A38, STOCKS!A:W, 22, FALSE), ""))
A39: 3037 | B39: =IF(ISBLANK(A39), "", IFERROR(VLOOKUP(A39, STOCKS!A:W, 2, FALSE), "")) -> 欣興 | C39: =IF(ISBLANK(A39), "", IFERROR(VLOOKUP(A39, STOCKS!A:W, 3, FALSE), "")) -> 電子零組件業 | D39: =IF(ISBLANK(A39), "", IFERROR(VLOOKUP(A39, category!A:C, 3, FALSE), "")) -> PCB/ABF載板 | E39: =IF(ISBLANK(A39), "", IFERROR(VLOOKUP(A39, STOCKS!A:W, 4, FALSE), "")) -> 678 | F39: =IF(ISBLANK(A39), "", IFERROR(VLOOKUP(A39, STOCKS!A:W, 5, FALSE), "")) -> 35 | G39: =IF(ISBLANK(A39), "", IFERROR(VLOOKUP(A39, STOCKS!A:W, 6, FALSE), "")) -> 5.44 | H39: =IF(ISBLANK(A39), "", IFERROR(VLOOKUP(A39, STOCKS!A:W, 7, FALSE), "")) -> '-++-+ | I39: =IF(ISBLANK(A39), "", IFERROR(VLOOKUP(A39, STOCKS!A:W, 8, FALSE), "")) -> 8.39 | J39: =IF(ISBLANK(A39), "", IFERROR(VLOOKUP(A39, STOCKS!A:W, 9, FALSE), "")) -> 3 | K39: =IF(ISBLANK(A39), "", IFERROR(VLOOKUP(A39, STOCKS!A:W, 10, FALSE), "")) -> 9523 | L39: =IF(ISBLANK(A39), "", IFERROR(VLOOKUP(A39, STOCKS!A:W, 11, FALSE), "")) -> 0.6 | M39: =IF(ISBLANK(A39), "", IFERROR(VLOOKUP(A39, STOCKS!A:W, 12, FALSE), "")) -> 636.2 | N39: =IF(ISBLANK(A39), "", IFERROR(VLOOKUP(A39, STOCKS!A:W, 13, FALSE), "")) -> 625.4 | O39: =IF(ISBLANK(A39), "", IFERROR(VLOOKUP(A39, STOCKS!A:W, 14, FALSE), "")) -> 561.27 | P39: =IF(ISBLANK(A39), "", IFERROR(VLOOKUP(A39, STOCKS!A:W, 15, FALSE), "")) -> 135 | Q39: =IF(ISBLANK(A39), "", IFERROR(VLOOKUP(A39, STOCKS!A:W, 16, FALSE), "")) -> '+++++ | R39: =IF(ISBLANK(A39), "", IFERROR(VLOOKUP(A39, STOCKS!A:W, 17, FALSE), "")) -> -238 | S39: =IF(ISBLANK(A39), "", IFERROR(VLOOKUP(A39, STOCKS!A:W, 18, FALSE), "")) -> 897 | T39: =IF(ISBLANK(A39), "", IFERROR(VLOOKUP(A39, STOCKS!A:W, 19, FALSE), "")) -> 0 | U39: =IF(ISBLANK(A39), "", IFERROR(VLOOKUP(A39, STOCKS!A:W, 20, FALSE), "")) -> 0 | V39: =IF(ISBLANK(A39), "", IFERROR(VLOOKUP(A39, STOCKS!A:W, 21, FALSE), "")) -> 46132 | W39: =IF(ISBLANK(A39), "", IFERROR(VLOOKUP(A39, STOCKS!A:W, 22, FALSE), "")) -> 公告本公司民國115年第一季財務報告董事會召開日期
A40: 8046 | B40: =IF(ISBLANK(A40), "", IFERROR(VLOOKUP(A40, STOCKS!A:W, 2, FALSE), "")) -> 南電 | C40: =IF(ISBLANK(A40), "", IFERROR(VLOOKUP(A40, STOCKS!A:W, 3, FALSE), "")) -> 電子零組件業 | D40: =IF(ISBLANK(A40), "", IFERROR(VLOOKUP(A40, category!A:C, 3, FALSE), "")) -> PCB/ABF載板 | E40: =IF(ISBLANK(A40), "", IFERROR(VLOOKUP(A40, STOCKS!A:W, 4, FALSE), "")) -> 796 | F40: =IF(ISBLANK(A40), "", IFERROR(VLOOKUP(A40, STOCKS!A:W, 5, FALSE), "")) -> 72 | G40: =IF(ISBLANK(A40), "", IFERROR(VLOOKUP(A40, STOCKS!A:W, 6, FALSE), "")) -> 9.94 | H40: =IF(ISBLANK(A40), "", IFERROR(VLOOKUP(A40, STOCKS!A:W, 7, FALSE), "")) -> '-++++ | I40: =IF(ISBLANK(A40), "", IFERROR(VLOOKUP(A40, STOCKS!A:W, 8, FALSE), "")) -> 20.45 | J40: =IF(ISBLANK(A40), "", IFERROR(VLOOKUP(A40, STOCKS!A:W, 9, FALSE), "")) -> 5 | K40: =IF(ISBLANK(A40), "", IFERROR(VLOOKUP(A40, STOCKS!A:W, 10, FALSE), "")) -> 17335 | L40: =IF(ISBLANK(A40), "", IFERROR(VLOOKUP(A40, STOCKS!A:W, 11, FALSE), "")) -> 2.68 | M40: =IF(ISBLANK(A40), "", IFERROR(VLOOKUP(A40, STOCKS!A:W, 12, FALSE), "")) -> 708.6 | N40: =IF(ISBLANK(A40), "", IFERROR(VLOOKUP(A40, STOCKS!A:W, 13, FALSE), "")) -> 679.5 | O40: =IF(ISBLANK(A40), "", IFERROR(VLOOKUP(A40, STOCKS!A:W, 14, FALSE), "")) -> 613.75 | P40: =IF(ISBLANK(A40), "", IFERROR(VLOOKUP(A40, STOCKS!A:W, 15, FALSE), "")) -> 663 | Q40: =IF(ISBLANK(A40), "", IFERROR(VLOOKUP(A40, STOCKS!A:W, 16, FALSE), "")) -> '-++-+ | R40: =IF(ISBLANK(A40), "", IFERROR(VLOOKUP(A40, STOCKS!A:W, 17, FALSE), "")) -> 323 | S40: =IF(ISBLANK(A40), "", IFERROR(VLOOKUP(A40, STOCKS!A:W, 18, FALSE), "")) -> 52 | T40: =IF(ISBLANK(A40), "", IFERROR(VLOOKUP(A40, STOCKS!A:W, 19, FALSE), "")) -> 10410 | U40: =IF(ISBLANK(A40), "", IFERROR(VLOOKUP(A40, STOCKS!A:W, 20, FALSE), "")) -> 60.05 | V40: =IF(ISBLANK(A40), "", IFERROR(VLOOKUP(A40, STOCKS!A:W, 21, FALSE), "")) -> 46132 | W40: =IF(ISBLANK(A40), "", IFERROR(VLOOKUP(A40, STOCKS!A:W, 22, FALSE), ""))
A41: 2313 | B41: =IF(ISBLANK(A41), "", IFERROR(VLOOKUP(A41, STOCKS!A:W, 2, FALSE), "")) -> 華通 | C41: =IF(ISBLANK(A41), "", IFERROR(VLOOKUP(A41, STOCKS!A:W, 3, FALSE), "")) -> 電子零組件業 | D41: =IF(ISBLANK(A41), "", IFERROR(VLOOKUP(A41, category!A:C, 3, FALSE), "")) -> PCB/低軌衛星 | E41: =IF(ISBLANK(A41), "", IFERROR(VLOOKUP(A41, STOCKS!A:W, 4, FALSE), "")) -> 250.5 | F41: =IF(ISBLANK(A41), "", IFERROR(VLOOKUP(A41, STOCKS!A:W, 5, FALSE), "")) -> -11 | G41: =IF(ISBLANK(A41), "", IFERROR(VLOOKUP(A41, STOCKS!A:W, 6, FALSE), "")) -> -4.21 | H41: =IF(ISBLANK(A41), "", IFERROR(VLOOKUP(A41, STOCKS!A:W, 7, FALSE), "")) -> '-+-+- | I41: =IF(ISBLANK(A41), "", IFERROR(VLOOKUP(A41, STOCKS!A:W, 8, FALSE), "")) -> -10.34 | J41: =IF(ISBLANK(A41), "", IFERROR(VLOOKUP(A41, STOCKS!A:W, 9, FALSE), "")) -> 2 | K41: =IF(ISBLANK(A41), "", IFERROR(VLOOKUP(A41, STOCKS!A:W, 10, FALSE), "")) -> 72814 | L41: =IF(ISBLANK(A41), "", IFERROR(VLOOKUP(A41, STOCKS!A:W, 11, FALSE), "")) -> 6.11 | M41: =IF(ISBLANK(A41), "", IFERROR(VLOOKUP(A41, STOCKS!A:W, 12, FALSE), "")) -> 258.5 | N41: =IF(ISBLANK(A41), "", IFERROR(VLOOKUP(A41, STOCKS!A:W, 13, FALSE), "")) -> 268.8 | O41: =IF(ISBLANK(A41), "", IFERROR(VLOOKUP(A41, STOCKS!A:W, 14, FALSE), "")) -> 255.9 | P41: =IF(ISBLANK(A41), "", IFERROR(VLOOKUP(A41, STOCKS!A:W, 15, FALSE), "")) -> -4848 | Q41: =IF(ISBLANK(A41), "", IFERROR(VLOOKUP(A41, STOCKS!A:W, 16, FALSE), "")) -> '-+--- | R41: =IF(ISBLANK(A41), "", IFERROR(VLOOKUP(A41, STOCKS!A:W, 17, FALSE), "")) -> -4561 | S41: =IF(ISBLANK(A41), "", IFERROR(VLOOKUP(A41, STOCKS!A:W, 18, FALSE), "")) -> -528 | T41: =IF(ISBLANK(A41), "", IFERROR(VLOOKUP(A41, STOCKS!A:W, 19, FALSE), "")) -> 32150 | U41: =IF(ISBLANK(A41), "", IFERROR(VLOOKUP(A41, STOCKS!A:W, 20, FALSE), "")) -> 44.15 | V41: =IF(ISBLANK(A41), "", IFERROR(VLOOKUP(A41, STOCKS!A:W, 21, FALSE), "")) -> 46132 | W41: =IF(ISBLANK(A41), "", IFERROR(VLOOKUP(A41, STOCKS!A:W, 22, FALSE), ""))
A42: 2316 | B42: =IF(ISBLANK(A42), "", IFERROR(VLOOKUP(A42, STOCKS!A:W, 2, FALSE), "")) -> 楠梓電 | C42: =IF(ISBLANK(A42), "", IFERROR(VLOOKUP(A42, STOCKS!A:W, 3, FALSE), "")) -> 電子零組件業 | D42: =IF(ISBLANK(A42), "", IFERROR(VLOOKUP(A42, category!A:C, 3, FALSE), "")) -> PCB | E42: =IF(ISBLANK(A42), "", IFERROR(VLOOKUP(A42, STOCKS!A:W, 4, FALSE), "")) -> 112 | F42: =IF(ISBLANK(A42), "", IFERROR(VLOOKUP(A42, STOCKS!A:W, 5, FALSE), "")) -> -2.5 | G42: =IF(ISBLANK(A42), "", IFERROR(VLOOKUP(A42, STOCKS!A:W, 6, FALSE), "")) -> -2.18 | H42: =IF(ISBLANK(A42), "", IFERROR(VLOOKUP(A42, STOCKS!A:W, 7, FALSE), "")) -> '+---- | I42: =IF(ISBLANK(A42), "", IFERROR(VLOOKUP(A42, STOCKS!A:W, 8, FALSE), "")) -> -0.71 | J42: =IF(ISBLANK(A42), "", IFERROR(VLOOKUP(A42, STOCKS!A:W, 9, FALSE), "")) -> 2 | K42: =IF(ISBLANK(A42), "", IFERROR(VLOOKUP(A42, STOCKS!A:W, 10, FALSE), "")) -> 8250 | L42: =IF(ISBLANK(A42), "", IFERROR(VLOOKUP(A42, STOCKS!A:W, 11, FALSE), "")) -> 4.51 | M42: =IF(ISBLANK(A42), "", IFERROR(VLOOKUP(A42, STOCKS!A:W, 12, FALSE), "")) -> 115 | N42: =IF(ISBLANK(A42), "", IFERROR(VLOOKUP(A42, STOCKS!A:W, 13, FALSE), "")) -> 110.42 | O42: =IF(ISBLANK(A42), "", IFERROR(VLOOKUP(A42, STOCKS!A:W, 14, FALSE), "")) -> 106.35 | P42: =IF(ISBLANK(A42), "", IFERROR(VLOOKUP(A42, STOCKS!A:W, 15, FALSE), "")) -> -2343 | Q42: =IF(ISBLANK(A42), "", IFERROR(VLOOKUP(A42, STOCKS!A:W, 16, FALSE), "")) -> '--+-- | R42: =IF(ISBLANK(A42), "", IFERROR(VLOOKUP(A42, STOCKS!A:W, 17, FALSE), "")) -> -56 | S42: =IF(ISBLANK(A42), "", IFERROR(VLOOKUP(A42, STOCKS!A:W, 18, FALSE), "")) -> -99 | T42: =IF(ISBLANK(A42), "", IFERROR(VLOOKUP(A42, STOCKS!A:W, 19, FALSE), "")) -> 3276 | U42: =IF(ISBLANK(A42), "", IFERROR(VLOOKUP(A42, STOCKS!A:W, 20, FALSE), "")) -> 39.71 | V42: =IF(ISBLANK(A42), "", IFERROR(VLOOKUP(A42, STOCKS!A:W, 21, FALSE), "")) -> 46132 | W42: =IF(ISBLANK(A42), "", IFERROR(VLOOKUP(A42, STOCKS!A:W, 22, FALSE), ""))
A43: 2355 | B43: =IF(ISBLANK(A43), "", IFERROR(VLOOKUP(A43, STOCKS!A:W, 2, FALSE), "")) -> 敬鵬 | C43: =IF(ISBLANK(A43), "", IFERROR(VLOOKUP(A43, STOCKS!A:W, 3, FALSE), "")) -> 電子零組件業 | D43: =IF(ISBLANK(A43), "", IFERROR(VLOOKUP(A43, category!A:C, 3, FALSE), "")) -> PCB/低軌衛星 | E43: =IF(ISBLANK(A43), "", IFERROR(VLOOKUP(A43, STOCKS!A:W, 4, FALSE), "")) -> 51 | F43: =IF(ISBLANK(A43), "", IFERROR(VLOOKUP(A43, STOCKS!A:W, 5, FALSE), "")) -> -1.1 | G43: =IF(ISBLANK(A43), "", IFERROR(VLOOKUP(A43, STOCKS!A:W, 6, FALSE), "")) -> -2.11 | H43: =IF(ISBLANK(A43), "", IFERROR(VLOOKUP(A43, STOCKS!A:W, 7, FALSE), "")) -> '--++- | I43: =IF(ISBLANK(A43), "", IFERROR(VLOOKUP(A43, STOCKS!A:W, 8, FALSE), "")) -> -3.04 | J43: =IF(ISBLANK(A43), "", IFERROR(VLOOKUP(A43, STOCKS!A:W, 9, FALSE), "")) -> 1 | K43: =IF(ISBLANK(A43), "", IFERROR(VLOOKUP(A43, STOCKS!A:W, 10, FALSE), "")) -> 15204 | L43: =IF(ISBLANK(A43), "", IFERROR(VLOOKUP(A43, STOCKS!A:W, 11, FALSE), "")) -> 3.82 | M43: =IF(ISBLANK(A43), "", IFERROR(VLOOKUP(A43, STOCKS!A:W, 12, FALSE), "")) -> 51.6 | N43: =IF(ISBLANK(A43), "", IFERROR(VLOOKUP(A43, STOCKS!A:W, 13, FALSE), "")) -> 51.98 | O43: =IF(ISBLANK(A43), "", IFERROR(VLOOKUP(A43, STOCKS!A:W, 14, FALSE), "")) -> 50.14 | P43: =IF(ISBLANK(A43), "", IFERROR(VLOOKUP(A43, STOCKS!A:W, 15, FALSE), "")) -> -2297 | Q43: =IF(ISBLANK(A43), "", IFERROR(VLOOKUP(A43, STOCKS!A:W, 16, FALSE), "")) -> '++++- | R43: =IF(ISBLANK(A43), "", IFERROR(VLOOKUP(A43, STOCKS!A:W, 17, FALSE), "")) -> 139 | S43: =IF(ISBLANK(A43), "", IFERROR(VLOOKUP(A43, STOCKS!A:W, 18, FALSE), "")) -> 86 | T43: =IF(ISBLANK(A43), "", IFERROR(VLOOKUP(A43, STOCKS!A:W, 19, FALSE), "")) -> 3422 | U43: =IF(ISBLANK(A43), "", IFERROR(VLOOKUP(A43, STOCKS!A:W, 20, FALSE), "")) -> 22.51 | V43: =IF(ISBLANK(A43), "", IFERROR(VLOOKUP(A43, STOCKS!A:W, 21, FALSE), "")) -> 46132 | W43: =IF(ISBLANK(A43), "", IFERROR(VLOOKUP(A43, STOCKS!A:W, 22, FALSE), ""))
A44: 2367 | B44: =IF(ISBLANK(A44), "", IFERROR(VLOOKUP(A44, STOCKS!A:W, 2, FALSE), "")) -> 燿華 | C44: =IF(ISBLANK(A44), "", IFERROR(VLOOKUP(A44, STOCKS!A:W, 3, FALSE), "")) -> 電子零組件業 | D44: =IF(ISBLANK(A44), "", IFERROR(VLOOKUP(A44, category!A:C, 3, FALSE), "")) -> PCB/低軌衛星 | E44: =IF(ISBLANK(A44), "", IFERROR(VLOOKUP(A44, STOCKS!A:W, 4, FALSE), "")) -> 65.6 | F44: =IF(ISBLANK(A44), "", IFERROR(VLOOKUP(A44, STOCKS!A:W, 5, FALSE), "")) -> -2.9 | G44: =IF(ISBLANK(A44), "", IFERROR(VLOOKUP(A44, STOCKS!A:W, 6, FALSE), "")) -> -4.23 | H44: =IF(ISBLANK(A44), "", IFERROR(VLOOKUP(A44, STOCKS!A:W, 7, FALSE), "")) -> '-+--- | I44: =IF(ISBLANK(A44), "", IFERROR(VLOOKUP(A44, STOCKS!A:W, 8, FALSE), "")) -> -11.85 | J44: =IF(ISBLANK(A44), "", IFERROR(VLOOKUP(A44, STOCKS!A:W, 9, FALSE), "")) -> 1 | K44: =IF(ISBLANK(A44), "", IFERROR(VLOOKUP(A44, STOCKS!A:W, 10, FALSE), "")) -> 61759 | L44: =IF(ISBLANK(A44), "", IFERROR(VLOOKUP(A44, STOCKS!A:W, 11, FALSE), "")) -> 8.74 | M44: =IF(ISBLANK(A44), "", IFERROR(VLOOKUP(A44, STOCKS!A:W, 12, FALSE), "")) -> 69.72 | N44: =IF(ISBLANK(A44), "", IFERROR(VLOOKUP(A44, STOCKS!A:W, 13, FALSE), "")) -> 72.11 | O44: =IF(ISBLANK(A44), "", IFERROR(VLOOKUP(A44, STOCKS!A:W, 14, FALSE), "")) -> 72.91 | P44: =IF(ISBLANK(A44), "", IFERROR(VLOOKUP(A44, STOCKS!A:W, 15, FALSE), "")) -> 6083 | Q44: =IF(ISBLANK(A44), "", IFERROR(VLOOKUP(A44, STOCKS!A:W, 16, FALSE), "")) -> '-+--+ | R44: =IF(ISBLANK(A44), "", IFERROR(VLOOKUP(A44, STOCKS!A:W, 17, FALSE), "")) -> -431 | S44: =IF(ISBLANK(A44), "", IFERROR(VLOOKUP(A44, STOCKS!A:W, 18, FALSE), "")) -> -808 | T44: =IF(ISBLANK(A44), "", IFERROR(VLOOKUP(A44, STOCKS!A:W, 19, FALSE), "")) -> 24374 | U44: =IF(ISBLANK(A44), "", IFERROR(VLOOKUP(A44, STOCKS!A:W, 20, FALSE), "")) -> 39.47 | V44: =IF(ISBLANK(A44), "", IFERROR(VLOOKUP(A44, STOCKS!A:W, 21, FALSE), "")) -> 46132 | W44: =IF(ISBLANK(A44), "", IFERROR(VLOOKUP(A44, STOCKS!A:W, 22, FALSE), ""))
A45: 2368 | B45: =IF(ISBLANK(A45), "", IFERROR(VLOOKUP(A45, STOCKS!A:W, 2, FALSE), "")) -> 金像電 | C45: =IF(ISBLANK(A45), "", IFERROR(VLOOKUP(A45, STOCKS!A:W, 3, FALSE), "")) -> 電子零組件業 | D45: =IF(ISBLANK(A45), "", IFERROR(VLOOKUP(A45, category!A:C, 3, FALSE), "")) -> PCB/低軌衛星 | E45: =IF(ISBLANK(A45), "", IFERROR(VLOOKUP(A45, STOCKS!A:W, 4, FALSE), "")) -> 1210 | F45: =IF(ISBLANK(A45), "", IFERROR(VLOOKUP(A45, STOCKS!A:W, 5, FALSE), "")) -> 35 | G45: =IF(ISBLANK(A45), "", IFERROR(VLOOKUP(A45, STOCKS!A:W, 6, FALSE), "")) -> 2.98 | H45: =IF(ISBLANK(A45), "", IFERROR(VLOOKUP(A45, STOCKS!A:W, 7, FALSE), "")) -> '++-++ | I45: =IF(ISBLANK(A45), "", IFERROR(VLOOKUP(A45, STOCKS!A:W, 8, FALSE), "")) -> 14.14 | J45: =IF(ISBLANK(A45), "", IFERROR(VLOOKUP(A45, STOCKS!A:W, 9, FALSE), "")) -> 2 | K45: =IF(ISBLANK(A45), "", IFERROR(VLOOKUP(A45, STOCKS!A:W, 10, FALSE), "")) -> 5889 | L45: =IF(ISBLANK(A45), "", IFERROR(VLOOKUP(A45, STOCKS!A:W, 11, FALSE), "")) -> 1.14 | M45: =IF(ISBLANK(A45), "", IFERROR(VLOOKUP(A45, STOCKS!A:W, 12, FALSE), "")) -> 1173 | N45: =IF(ISBLANK(A45), "", IFERROR(VLOOKUP(A45, STOCKS!A:W, 13, FALSE), "")) -> 1103 | O45: =IF(ISBLANK(A45), "", IFERROR(VLOOKUP(A45, STOCKS!A:W, 14, FALSE), "")) -> 1012.05 | P45: =IF(ISBLANK(A45), "", IFERROR(VLOOKUP(A45, STOCKS!A:W, 15, FALSE), "")) -> -169 | Q45: =IF(ISBLANK(A45), "", IFERROR(VLOOKUP(A45, STOCKS!A:W, 16, FALSE), "")) -> '++--- | R45: =IF(ISBLANK(A45), "", IFERROR(VLOOKUP(A45, STOCKS!A:W, 17, FALSE), "")) -> 275 | S45: =IF(ISBLANK(A45), "", IFERROR(VLOOKUP(A45, STOCKS!A:W, 18, FALSE), "")) -> -61 | T45: =IF(ISBLANK(A45), "", IFERROR(VLOOKUP(A45, STOCKS!A:W, 19, FALSE), "")) -> 3316 | U45: =IF(ISBLANK(A45), "", IFERROR(VLOOKUP(A45, STOCKS!A:W, 20, FALSE), "")) -> 56.31 | V45: =IF(ISBLANK(A45), "", IFERROR(VLOOKUP(A45, STOCKS!A:W, 21, FALSE), "")) -> 46132 | W45: =IF(ISBLANK(A45), "", IFERROR(VLOOKUP(A45, STOCKS!A:W, 22, FALSE), ""))
A46: 2383 | B46: =IF(ISBLANK(A46), "", IFERROR(VLOOKUP(A46, STOCKS!A:W, 2, FALSE), "")) -> 台光電 | C46: =IF(ISBLANK(A46), "", IFERROR(VLOOKUP(A46, STOCKS!A:W, 3, FALSE), "")) -> 電子零組件業 | D46: =IF(ISBLANK(A46), "", IFERROR(VLOOKUP(A46, category!A:C, 3, FALSE), "")) -> PCB/低軌衛星 | E46: =IF(ISBLANK(A46), "", IFERROR(VLOOKUP(A46, STOCKS!A:W, 4, FALSE), "")) -> 3850 | F46: =IF(ISBLANK(A46), "", IFERROR(VLOOKUP(A46, STOCKS!A:W, 5, FALSE), "")) -> 50 | G46: =IF(ISBLANK(A46), "", IFERROR(VLOOKUP(A46, STOCKS!A:W, 6, FALSE), "")) -> 1.32 | H46: =IF(ISBLANK(A46), "", IFERROR(VLOOKUP(A46, STOCKS!A:W, 7, FALSE), "")) -> '+++-+ | I46: =IF(ISBLANK(A46), "", IFERROR(VLOOKUP(A46, STOCKS!A:W, 8, FALSE), "")) -> 15.18 | J46: =IF(ISBLANK(A46), "", IFERROR(VLOOKUP(A46, STOCKS!A:W, 9, FALSE), "")) -> 2 | K46: =IF(ISBLANK(A46), "", IFERROR(VLOOKUP(A46, STOCKS!A:W, 10, FALSE), "")) -> 3606 | L46: =IF(ISBLANK(A46), "", IFERROR(VLOOKUP(A46, STOCKS!A:W, 11, FALSE), "")) -> 1.01 | M46: =IF(ISBLANK(A46), "", IFERROR(VLOOKUP(A46, STOCKS!A:W, 12, FALSE), "")) -> 3780 | N46: =IF(ISBLANK(A46), "", IFERROR(VLOOKUP(A46, STOCKS!A:W, 13, FALSE), "")) -> 3492 | O46: =IF(ISBLANK(A46), "", IFERROR(VLOOKUP(A46, STOCKS!A:W, 14, FALSE), "")) -> 3147 | P46: =IF(ISBLANK(A46), "", IFERROR(VLOOKUP(A46, STOCKS!A:W, 15, FALSE), "")) -> -57 | Q46: =IF(ISBLANK(A46), "", IFERROR(VLOOKUP(A46, STOCKS!A:W, 16, FALSE), "")) -> '++--- | R46: =IF(ISBLANK(A46), "", IFERROR(VLOOKUP(A46, STOCKS!A:W, 17, FALSE), "")) -> 22 | S46: =IF(ISBLANK(A46), "", IFERROR(VLOOKUP(A46, STOCKS!A:W, 18, FALSE), "")) -> -11 | T46: =IF(ISBLANK(A46), "", IFERROR(VLOOKUP(A46, STOCKS!A:W, 19, FALSE), "")) -> 1796 | U46: =IF(ISBLANK(A46), "", IFERROR(VLOOKUP(A46, STOCKS!A:W, 20, FALSE), "")) -> 49.81 | V46: =IF(ISBLANK(A46), "", IFERROR(VLOOKUP(A46, STOCKS!A:W, 21, FALSE), "")) -> 46132 | W46: =IF(ISBLANK(A46), "", IFERROR(VLOOKUP(A46, STOCKS!A:W, 22, FALSE), ""))
A47: 2467 | B47: =IF(ISBLANK(A47), "", IFERROR(VLOOKUP(A47, STOCKS!A:W, 2, FALSE), "")) -> 志聖 | C47: =IF(ISBLANK(A47), "", IFERROR(VLOOKUP(A47, STOCKS!A:W, 3, FALSE), "")) -> 電子零組件業 | D47: =IF(ISBLANK(A47), "", IFERROR(VLOOKUP(A47, category!A:C, 3, FALSE), "")) -> PCB/廠務 | E47: =IF(ISBLANK(A47), "", IFERROR(VLOOKUP(A47, STOCKS!A:W, 4, FALSE), "")) -> 570 | F47: =IF(ISBLANK(A47), "", IFERROR(VLOOKUP(A47, STOCKS!A:W, 5, FALSE), "")) -> 20 | G47: =IF(ISBLANK(A47), "", IFERROR(VLOOKUP(A47, STOCKS!A:W, 6, FALSE), "")) -> 3.64 | H47: =IF(ISBLANK(A47), "", IFERROR(VLOOKUP(A47, STOCKS!A:W, 7, FALSE), "")) -> '--+++ | I47: =IF(ISBLANK(A47), "", IFERROR(VLOOKUP(A47, STOCKS!A:W, 8, FALSE), "")) -> 4.31 | J47: =IF(ISBLANK(A47), "", IFERROR(VLOOKUP(A47, STOCKS!A:W, 9, FALSE), "")) -> 4 | K47: =IF(ISBLANK(A47), "", IFERROR(VLOOKUP(A47, STOCKS!A:W, 10, FALSE), "")) -> 892 | L47: =IF(ISBLANK(A47), "", IFERROR(VLOOKUP(A47, STOCKS!A:W, 11, FALSE), "")) -> 0.57 | M47: =IF(ISBLANK(A47), "", IFERROR(VLOOKUP(A47, STOCKS!A:W, 12, FALSE), "")) -> 538.6 | N47: =IF(ISBLANK(A47), "", IFERROR(VLOOKUP(A47, STOCKS!A:W, 13, FALSE), "")) -> 513.5 | O47: =IF(ISBLANK(A47), "", IFERROR(VLOOKUP(A47, STOCKS!A:W, 14, FALSE), "")) -> 452.93 | P47: =IF(ISBLANK(A47), "", IFERROR(VLOOKUP(A47, STOCKS!A:W, 15, FALSE), "")) -> 182 | Q47: =IF(ISBLANK(A47), "", IFERROR(VLOOKUP(A47, STOCKS!A:W, 16, FALSE), "")) -> '--+++ | R47: =IF(ISBLANK(A47), "", IFERROR(VLOOKUP(A47, STOCKS!A:W, 17, FALSE), "")) -> -16 | S47: =IF(ISBLANK(A47), "", IFERROR(VLOOKUP(A47, STOCKS!A:W, 18, FALSE), "")) -> 4 | T47: =IF(ISBLANK(A47), "", IFERROR(VLOOKUP(A47, STOCKS!A:W, 19, FALSE), "")) -> 0 | U47: =IF(ISBLANK(A47), "", IFERROR(VLOOKUP(A47, STOCKS!A:W, 20, FALSE), "")) -> 0 | V47: =IF(ISBLANK(A47), "", IFERROR(VLOOKUP(A47, STOCKS!A:W, 21, FALSE), "")) -> 46132 | W47: =IF(ISBLANK(A47), "", IFERROR(VLOOKUP(A47, STOCKS!A:W, 22, FALSE), "")) -> 代重要子公司志聖科技(廣州)有限公司公告 2026年第二次股東臨時會重要決議事項
A48: 2493 | B48: =IF(ISBLANK(A48), "", IFERROR(VLOOKUP(A48, STOCKS!A:W, 2, FALSE), "")) -> 揚博 | C48: =IF(ISBLANK(A48), "", IFERROR(VLOOKUP(A48, STOCKS!A:W, 3, FALSE), "")) -> 電子零組件業 | D48: =IF(ISBLANK(A48), "", IFERROR(VLOOKUP(A48, category!A:C, 3, FALSE), "")) -> PCB | E48: =IF(ISBLANK(A48), "", IFERROR(VLOOKUP(A48, STOCKS!A:W, 4, FALSE), "")) -> 136.5 | F48: =IF(ISBLANK(A48), "", IFERROR(VLOOKUP(A48, STOCKS!A:W, 5, FALSE), "")) -> -4.5 | G48: =IF(ISBLANK(A48), "", IFERROR(VLOOKUP(A48, STOCKS!A:W, 6, FALSE), "")) -> -3.19 | H48: =IF(ISBLANK(A48), "", IFERROR(VLOOKUP(A48, STOCKS!A:W, 7, FALSE), "")) -> '++--- | I48: =IF(ISBLANK(A48), "", IFERROR(VLOOKUP(A48, STOCKS!A:W, 8, FALSE), "")) -> 5.34 | J48: =IF(ISBLANK(A48), "", IFERROR(VLOOKUP(A48, STOCKS!A:W, 9, FALSE), "")) -> 3 | K48: =IF(ISBLANK(A48), "", IFERROR(VLOOKUP(A48, STOCKS!A:W, 10, FALSE), "")) -> 2924 | L48: =IF(ISBLANK(A48), "", IFERROR(VLOOKUP(A48, STOCKS!A:W, 11, FALSE), "")) -> 2.31 | M48: =IF(ISBLANK(A48), "", IFERROR(VLOOKUP(A48, STOCKS!A:W, 12, FALSE), "")) -> 143.2 | N48: =IF(ISBLANK(A48), "", IFERROR(VLOOKUP(A48, STOCKS!A:W, 13, FALSE), "")) -> 130.25 | O48: =IF(ISBLANK(A48), "", IFERROR(VLOOKUP(A48, STOCKS!A:W, 14, FALSE), "")) -> 119.5 | P48: =IF(ISBLANK(A48), "", IFERROR(VLOOKUP(A48, STOCKS!A:W, 15, FALSE), "")) -> 335 | Q48: =IF(ISBLANK(A48), "", IFERROR(VLOOKUP(A48, STOCKS!A:W, 16, FALSE), "")) -> '+--++ | R48: =IF(ISBLANK(A48), "", IFERROR(VLOOKUP(A48, STOCKS!A:W, 17, FALSE), "")) -> -70 | S48: =IF(ISBLANK(A48), "", IFERROR(VLOOKUP(A48, STOCKS!A:W, 18, FALSE), "")) -> -15 | T48: =IF(ISBLANK(A48), "", IFERROR(VLOOKUP(A48, STOCKS!A:W, 19, FALSE), "")) -> 1072 | U48: =IF(ISBLANK(A48), "", IFERROR(VLOOKUP(A48, STOCKS!A:W, 20, FALSE), "")) -> 36.66 | V48: =IF(ISBLANK(A48), "", IFERROR(VLOOKUP(A48, STOCKS!A:W, 21, FALSE), "")) -> 46132 | W48: =IF(ISBLANK(A48), "", IFERROR(VLOOKUP(A48, STOCKS!A:W, 22, FALSE), ""))
A49: 5340 | B49: =IF(ISBLANK(A49), "", IFERROR(VLOOKUP(A49, STOCKS!A:W, 2, FALSE), "")) -> 建榮 | C49: =IF(ISBLANK(A49), "", IFERROR(VLOOKUP(A49, STOCKS!A:W, 3, FALSE), "")) -> 電子零組件業 | D49: =IF(ISBLANK(A49), "", IFERROR(VLOOKUP(A49, category!A:C, 3, FALSE), "")) -> PCB/玻纖布 | E49: =IF(ISBLANK(A49), "", IFERROR(VLOOKUP(A49, STOCKS!A:W, 4, FALSE), "")) -> 125.5 | F49: =IF(ISBLANK(A49), "", IFERROR(VLOOKUP(A49, STOCKS!A:W, 5, FALSE), "")) -> -8.5 | G49: =IF(ISBLANK(A49), "", IFERROR(VLOOKUP(A49, STOCKS!A:W, 6, FALSE), "")) -> -6.34 | H49: =IF(ISBLANK(A49), "", IFERROR(VLOOKUP(A49, STOCKS!A:W, 7, FALSE), "")) -> '+-++- | I49: =IF(ISBLANK(A49), "", IFERROR(VLOOKUP(A49, STOCKS!A:W, 8, FALSE), "")) -> 10.54 | J49: =IF(ISBLANK(A49), "", IFERROR(VLOOKUP(A49, STOCKS!A:W, 9, FALSE), "")) -> 2 | K49: =IF(ISBLANK(A49), "", IFERROR(VLOOKUP(A49, STOCKS!A:W, 10, FALSE), "")) -> 17409 | L49: =IF(ISBLANK(A49), "", IFERROR(VLOOKUP(A49, STOCKS!A:W, 11, FALSE), "")) -> 8.93 | M49: =IF(ISBLANK(A49), "", IFERROR(VLOOKUP(A49, STOCKS!A:W, 12, FALSE), "")) -> 122.9 | N49: =IF(ISBLANK(A49), "", IFERROR(VLOOKUP(A49, STOCKS!A:W, 13, FALSE), "")) -> 119.1 | O49: =IF(ISBLANK(A49), "", IFERROR(VLOOKUP(A49, STOCKS!A:W, 14, FALSE), "")) -> 111.28 | P49: =IF(ISBLANK(A49), "", IFERROR(VLOOKUP(A49, STOCKS!A:W, 15, FALSE), "")) -> -2951 | Q49: =IF(ISBLANK(A49), "", IFERROR(VLOOKUP(A49, STOCKS!A:W, 16, FALSE), "")) -> '-++-- | R49: =IF(ISBLANK(A49), "", IFERROR(VLOOKUP(A49, STOCKS!A:W, 17, FALSE), "")) -> 0 | S49: =IF(ISBLANK(A49), "", IFERROR(VLOOKUP(A49, STOCKS!A:W, 18, FALSE), "")) -> -4 | T49: =IF(ISBLANK(A49), "", IFERROR(VLOOKUP(A49, STOCKS!A:W, 19, FALSE), "")) -> 9228 | U49: =IF(ISBLANK(A49), "", IFERROR(VLOOKUP(A49, STOCKS!A:W, 20, FALSE), "")) -> 53.01 | V49: =IF(ISBLANK(A49), "", IFERROR(VLOOKUP(A49, STOCKS!A:W, 21, FALSE), "")) -> 46132 | W49: =IF(ISBLANK(A49), "", IFERROR(VLOOKUP(A49, STOCKS!A:W, 22, FALSE), ""))
... A57: 1815 | B57: =IF(ISBLANK(A57), "", IFERROR(VLOOKUP(A57, STOCKS!A:W, 2, FALSE), "")) -> 富喬 | C57: =IF(ISBLANK(A57), "", IFERROR(VLOOKUP(A57, STOCKS!A:W, 3, FALSE), "")) -> 電子零組件業 | D57: =IF(ISBLANK(A57), "", IFERROR(VLOOKUP(A57, category!A:C, 3, FALSE), "")) -> PCB-玻纖布 | E57: =IF(ISBLANK(A57), "", IFERROR(VLOOKUP(A57, STOCKS!A:W, 4, FALSE), "")) -> 118 | F57: =IF(ISBLANK(A57), "", IFERROR(VLOOKUP(A57, STOCKS!A:W, 5, FALSE), "")) -> -9 | G57: =IF(ISBLANK(A57), "", IFERROR(VLOOKUP(A57, STOCKS!A:W, 6, FALSE), "")) -> -7.09 | H57: =IF(ISBLANK(A57), "", IFERROR(VLOOKUP(A57, STOCKS!A:W, 7, FALSE), "")) -> '+-++- | I57: =IF(ISBLANK(A57), "", IFERROR(VLOOKUP(A57, STOCKS!A:W, 8, FALSE), "")) -> 5.14 | J57: =IF(ISBLANK(A57), "", IFERROR(VLOOKUP(A57, STOCKS!A:W, 9, FALSE), "")) -> 3 | K57: =IF(ISBLANK(A57), "", IFERROR(VLOOKUP(A57, STOCKS!A:W, 10, FALSE), "")) -> 118516 | L57: =IF(ISBLANK(A57), "", IFERROR(VLOOKUP(A57, STOCKS!A:W, 11, FALSE), "")) -> 20.24 | M57: =IF(ISBLANK(A57), "", IFERROR(VLOOKUP(A57, STOCKS!A:W, 12, FALSE), "")) -> 117.4 | N57: =IF(ISBLANK(A57), "", IFERROR(VLOOKUP(A57, STOCKS!A:W, 13, FALSE), "")) -> 114.55 | O57: =IF(ISBLANK(A57), "", IFERROR(VLOOKUP(A57, STOCKS!A:W, 14, FALSE), "")) -> 108.17 | P57: =IF(ISBLANK(A57), "", IFERROR(VLOOKUP(A57, STOCKS!A:W, 15, FALSE), "")) -> -18413 | Q57: =IF(ISBLANK(A57), "", IFERROR(VLOOKUP(A57, STOCKS!A:W, 16, FALSE), "")) -> '--++- | R57: =IF(ISBLANK(A57), "", IFERROR(VLOOKUP(A57, STOCKS!A:W, 17, FALSE), "")) -> 340 | S57: =IF(ISBLANK(A57), "", IFERROR(VLOOKUP(A57, STOCKS!A:W, 18, FALSE), "")) -> -804 | T57: =IF(ISBLANK(A57), "", IFERROR(VLOOKUP(A57, STOCKS!A:W, 19, FALSE), "")) -> 41354 | U57: =IF(ISBLANK(A57), "", IFERROR(VLOOKUP(A57, STOCKS!A:W, 20, FALSE), "")) -> 34.89 | V57: =IF(ISBLANK(A57), "", IFERROR(VLOOKUP(A57, STOCKS!A:W, 21, FALSE), "")) -> 46132 | W57: =IF(ISBLANK(A57), "", IFERROR(VLOOKUP(A57, STOCKS!A:W, 22, FALSE), ""))
A58: 題材-BBU
A59: 2301 | B59: =IF(ISBLANK(A59), "", IFERROR(VLOOKUP(A59, STOCKS!A:W, 2, FALSE), "")) -> 光寶科 | C59: =IF(ISBLANK(A59), "", IFERROR(VLOOKUP(A59, STOCKS!A:W, 3, FALSE), "")) -> 電腦及週邊設備業 | D59: =IF(ISBLANK(A59), "", IFERROR(VLOOKUP(A59, category!A:C, 3, FALSE), "")) -> BBU | E59: =IF(ISBLANK(A59), "", IFERROR(VLOOKUP(A59, STOCKS!A:W, 4, FALSE), "")) -> 165 | F59: =IF(ISBLANK(A59), "", IFERROR(VLOOKUP(A59, STOCKS!A:W, 5, FALSE), "")) -> 3 | G59: =IF(ISBLANK(A59), "", IFERROR(VLOOKUP(A59, STOCKS!A:W, 6, FALSE), "")) -> 1.85 | H59: =IF(ISBLANK(A59), "", IFERROR(VLOOKUP(A59, STOCKS!A:W, 7, FALSE), "")) -> '+++++ | I59: =IF(ISBLANK(A59), "", IFERROR(VLOOKUP(A59, STOCKS!A:W, 8, FALSE), "")) -> 7.29 | J59: =IF(ISBLANK(A59), "", IFERROR(VLOOKUP(A59, STOCKS!A:W, 9, FALSE), "")) -> 1 | K59: =IF(ISBLANK(A59), "", IFERROR(VLOOKUP(A59, STOCKS!A:W, 10, FALSE), "")) -> 30332 | L59: =IF(ISBLANK(A59), "", IFERROR(VLOOKUP(A59, STOCKS!A:W, 11, FALSE), "")) -> 1.31 | M59: =IF(ISBLANK(A59), "", IFERROR(VLOOKUP(A59, STOCKS!A:W, 12, FALSE), "")) -> 160.9 | N59: =IF(ISBLANK(A59), "", IFERROR(VLOOKUP(A59, STOCKS!A:W, 13, FALSE), "")) -> 157.35 | O59: =IF(ISBLANK(A59), "", IFERROR(VLOOKUP(A59, STOCKS!A:W, 14, FALSE), "")) -> 154.32 | P59: =IF(ISBLANK(A59), "", IFERROR(VLOOKUP(A59, STOCKS!A:W, 15, FALSE), "")) -> 7914 | Q59: =IF(ISBLANK(A59), "", IFERROR(VLOOKUP(A59, STOCKS!A:W, 16, FALSE), "")) -> '+++++ | R59: =IF(ISBLANK(A59), "", IFERROR(VLOOKUP(A59, STOCKS!A:W, 17, FALSE), "")) -> -1339 | S59: =IF(ISBLANK(A59), "", IFERROR(VLOOKUP(A59, STOCKS!A:W, 18, FALSE), "")) -> -51 | T59: =IF(ISBLANK(A59), "", IFERROR(VLOOKUP(A59, STOCKS!A:W, 19, FALSE), "")) -> 9939 | U59: =IF(ISBLANK(A59), "", IFERROR(VLOOKUP(A59, STOCKS!A:W, 20, FALSE), "")) -> 32.77 | V59: =IF(ISBLANK(A59), "", IFERROR(VLOOKUP(A59, STOCKS!A:W, 21, FALSE), "")) -> 46132 | W59: =IF(ISBLANK(A59), "", IFERROR(VLOOKUP(A59, STOCKS!A:W, 22, FALSE), "")) -> 光寶科技115年第一季法人說明會
A60: 2308 | B60: =IF(ISBLANK(A60), "", IFERROR(VLOOKUP(A60, STOCKS!A:W, 2, FALSE), "")) -> 台達電 | C60: =IF(ISBLANK(A60), "", IFERROR(VLOOKUP(A60, STOCKS!A:W, 3, FALSE), "")) -> 電子零組件業 | D60: =IF(ISBLANK(A60), "", IFERROR(VLOOKUP(A60, category!A:C, 3, FALSE), "")) -> BBU/機器人 | E60: =IF(ISBLANK(A60), "", IFERROR(VLOOKUP(A60, STOCKS!A:W, 4, FALSE), "")) -> 1900 | F60: =IF(ISBLANK(A60), "", IFERROR(VLOOKUP(A60, STOCKS!A:W, 5, FALSE), "")) -> 60 | G60: =IF(ISBLANK(A60), "", IFERROR(VLOOKUP(A60, STOCKS!A:W, 6, FALSE), "")) -> 3.26 | H60: =IF(ISBLANK(A60), "", IFERROR(VLOOKUP(A60, STOCKS!A:W, 7, FALSE), "")) -> '+++-+ | I60: =IF(ISBLANK(A60), "", IFERROR(VLOOKUP(A60, STOCKS!A:W, 8, FALSE), "")) -> 8.92 | J60: =IF(ISBLANK(A60), "", IFERROR(VLOOKUP(A60, STOCKS!A:W, 9, FALSE), "")) -> 2 | K60: =IF(ISBLANK(A60), "", IFERROR(VLOOKUP(A60, STOCKS!A:W, 10, FALSE), "")) -> 12064 | L60: =IF(ISBLANK(A60), "", IFERROR(VLOOKUP(A60, STOCKS!A:W, 11, FALSE), "")) -> 0.46 | M60: =IF(ISBLANK(A60), "", IFERROR(VLOOKUP(A60, STOCKS!A:W, 12, FALSE), "")) -> 1824 | N60: =IF(ISBLANK(A60), "", IFERROR(VLOOKUP(A60, STOCKS!A:W, 13, FALSE), "")) -> 1742 | O60: =IF(ISBLANK(A60), "", IFERROR(VLOOKUP(A60, STOCKS!A:W, 14, FALSE), "")) -> 1603.25 | P60: =IF(ISBLANK(A60), "", IFERROR(VLOOKUP(A60, STOCKS!A:W, 15, FALSE), "")) -> 444 | Q60: =IF(ISBLANK(A60), "", IFERROR(VLOOKUP(A60, STOCKS!A:W, 16, FALSE), "")) -> '-++-+ | R60: =IF(ISBLANK(A60), "", IFERROR(VLOOKUP(A60, STOCKS!A:W, 17, FALSE), "")) -> 25 | S60: =IF(ISBLANK(A60), "", IFERROR(VLOOKUP(A60, STOCKS!A:W, 18, FALSE), "")) -> 18 | T60: =IF(ISBLANK(A60), "", IFERROR(VLOOKUP(A60, STOCKS!A:W, 19, FALSE), "")) -> 3542 | U60: =IF(ISBLANK(A60), "", IFERROR(VLOOKUP(A60, STOCKS!A:W, 20, FALSE), "")) -> 29.36 | V60: =IF(ISBLANK(A60), "", IFERROR(VLOOKUP(A60, STOCKS!A:W, 21, FALSE), "")) -> 46132 | W60: =IF(ISBLANK(A60), "", IFERROR(VLOOKUP(A60, STOCKS!A:W, 22, FALSE), ""))
A61: 3211 | B61: =IF(ISBLANK(A61), "", IFERROR(VLOOKUP(A61, STOCKS!A:W, 2, FALSE), "")) -> 順達 | C61: =IF(ISBLANK(A61), "", IFERROR(VLOOKUP(A61, STOCKS!A:W, 3, FALSE), "")) -> 電腦及週邊設備業 | D61: =IF(ISBLANK(A61), "", IFERROR(VLOOKUP(A61, category!A:C, 3, FALSE), "")) -> BBU | E61: =IF(ISBLANK(A61), "", IFERROR(VLOOKUP(A61, STOCKS!A:W, 4, FALSE), "")) -> 369 | F61: =IF(ISBLANK(A61), "", IFERROR(VLOOKUP(A61, STOCKS!A:W, 5, FALSE), "")) -> 10 | G61: =IF(ISBLANK(A61), "", IFERROR(VLOOKUP(A61, STOCKS!A:W, 6, FALSE), "")) -> 2.79 | H61: =IF(ISBLANK(A61), "", IFERROR(VLOOKUP(A61, STOCKS!A:W, 7, FALSE), "")) -> '--+++ | I61: =IF(ISBLANK(A61), "", IFERROR(VLOOKUP(A61, STOCKS!A:W, 8, FALSE), "")) -> 2.73 | J61: =IF(ISBLANK(A61), "", IFERROR(VLOOKUP(A61, STOCKS!A:W, 9, FALSE), "")) -> 1 | K61: =IF(ISBLANK(A61), "", IFERROR(VLOOKUP(A61, STOCKS!A:W, 10, FALSE), "")) -> 10305 | L61: =IF(ISBLANK(A61), "", IFERROR(VLOOKUP(A61, STOCKS!A:W, 11, FALSE), "")) -> 6.67 | M61: =IF(ISBLANK(A61), "", IFERROR(VLOOKUP(A61, STOCKS!A:W, 12, FALSE), "")) -> 354.9 | N61: =IF(ISBLANK(A61), "", IFERROR(VLOOKUP(A61, STOCKS!A:W, 13, FALSE), "")) -> 361.1 | O61: =IF(ISBLANK(A61), "", IFERROR(VLOOKUP(A61, STOCKS!A:W, 14, FALSE), "")) -> 350.55 | P61: =IF(ISBLANK(A61), "", IFERROR(VLOOKUP(A61, STOCKS!A:W, 15, FALSE), "")) -> -1080 | Q61: =IF(ISBLANK(A61), "", IFERROR(VLOOKUP(A61, STOCKS!A:W, 16, FALSE), "")) -> '---+- | R61: =IF(ISBLANK(A61), "", IFERROR(VLOOKUP(A61, STOCKS!A:W, 17, FALSE), "")) -> 186 | S61: =IF(ISBLANK(A61), "", IFERROR(VLOOKUP(A61, STOCKS!A:W, 18, FALSE), "")) -> 93 | T61: =IF(ISBLANK(A61), "", IFERROR(VLOOKUP(A61, STOCKS!A:W, 19, FALSE), "")) -> 5399 | U61: =IF(ISBLANK(A61), "", IFERROR(VLOOKUP(A61, STOCKS!A:W, 20, FALSE), "")) -> 52.39 | V61: =IF(ISBLANK(A61), "", IFERROR(VLOOKUP(A61, STOCKS!A:W, 21, FALSE), "")) -> 46132 | W61: =IF(ISBLANK(A61), "", IFERROR(VLOOKUP(A61, STOCKS!A:W, 22, FALSE), ""))
A62: 3323 | B62: =IF(ISBLANK(A62), "", IFERROR(VLOOKUP(A62, STOCKS!A:W, 2, FALSE), "")) -> 加百裕 | C62: =IF(ISBLANK(A62), "", IFERROR(VLOOKUP(A62, STOCKS!A:W, 3, FALSE), "")) -> 電腦及週邊設備業 | D62: =IF(ISBLANK(A62), "", IFERROR(VLOOKUP(A62, category!A:C, 3, FALSE), "")) -> BBU | E62: =IF(ISBLANK(A62), "", IFERROR(VLOOKUP(A62, STOCKS!A:W, 4, FALSE), "")) -> 33.8 | F62: =IF(ISBLANK(A62), "", IFERROR(VLOOKUP(A62, STOCKS!A:W, 5, FALSE), "")) -> 0.65 | G62: =IF(ISBLANK(A62), "", IFERROR(VLOOKUP(A62, STOCKS!A:W, 6, FALSE), "")) -> 1.96 | H62: =IF(ISBLANK(A62), "", IFERROR(VLOOKUP(A62, STOCKS!A:W, 7, FALSE), "")) -> '+++++ | I62: =IF(ISBLANK(A62), "", IFERROR(VLOOKUP(A62, STOCKS!A:W, 8, FALSE), "")) -> 5.19 | J62: =IF(ISBLANK(A62), "", IFERROR(VLOOKUP(A62, STOCKS!A:W, 9, FALSE), "")) -> 0 | K62: =IF(ISBLANK(A62), "", IFERROR(VLOOKUP(A62, STOCKS!A:W, 10, FALSE), "")) -> 1166 | L62: =IF(ISBLANK(A62), "", IFERROR(VLOOKUP(A62, STOCKS!A:W, 11, FALSE), "")) -> 1.17 | M62: =IF(ISBLANK(A62), "", IFERROR(VLOOKUP(A62, STOCKS!A:W, 12, FALSE), "")) -> 32.91 | N62: =IF(ISBLANK(A62), "", IFERROR(VLOOKUP(A62, STOCKS!A:W, 13, FALSE), "")) -> 32.64 | O62: =IF(ISBLANK(A62), "", IFERROR(VLOOKUP(A62, STOCKS!A:W, 14, FALSE), "")) -> 33.48 | P62: =IF(ISBLANK(A62), "", IFERROR(VLOOKUP(A62, STOCKS!A:W, 15, FALSE), "")) -> 212 | Q62: =IF(ISBLANK(A62), "", IFERROR(VLOOKUP(A62, STOCKS!A:W, 16, FALSE), "")) -> '---++ | R62: =IF(ISBLANK(A62), "", IFERROR(VLOOKUP(A62, STOCKS!A:W, 17, FALSE), "")) -> 0 | S62: =IF(ISBLANK(A62), "", IFERROR(VLOOKUP(A62, STOCKS!A:W, 18, FALSE), "")) -> -1 | T62: =IF(ISBLANK(A62), "", IFERROR(VLOOKUP(A62, STOCKS!A:W, 19, FALSE), "")) -> 282 | U62: =IF(ISBLANK(A62), "", IFERROR(VLOOKUP(A62, STOCKS!A:W, 20, FALSE), "")) -> 24.19 | V62: =IF(ISBLANK(A62), "", IFERROR(VLOOKUP(A62, STOCKS!A:W, 21, FALSE), "")) -> 46132 | W62: =IF(ISBLANK(A62), "", IFERROR(VLOOKUP(A62, STOCKS!A:W, 22, FALSE), ""))
A63: 4931 | B63: =IF(ISBLANK(A63), "", IFERROR(VLOOKUP(A63, STOCKS!A:W, 2, FALSE), "")) -> 新盛力 | C63: =IF(ISBLANK(A63), "", IFERROR(VLOOKUP(A63, STOCKS!A:W, 3, FALSE), "")) -> 電腦及週邊設備業 | D63: =IF(ISBLANK(A63), "", IFERROR(VLOOKUP(A63, category!A:C, 3, FALSE), "")) -> BBU | E63: =IF(ISBLANK(A63), "", IFERROR(VLOOKUP(A63, STOCKS!A:W, 4, FALSE), "")) -> 142.5 | F63: =IF(ISBLANK(A63), "", IFERROR(VLOOKUP(A63, STOCKS!A:W, 5, FALSE), "")) -> -2.5 | G63: =IF(ISBLANK(A63), "", IFERROR(VLOOKUP(A63, STOCKS!A:W, 6, FALSE), "")) -> -1.72 | H63: =IF(ISBLANK(A63), "", IFERROR(VLOOKUP(A63, STOCKS!A:W, 7, FALSE), "")) -> '--++- | I63: =IF(ISBLANK(A63), "", IFERROR(VLOOKUP(A63, STOCKS!A:W, 8, FALSE), "")) -> 1.5 | J63: =IF(ISBLANK(A63), "", IFERROR(VLOOKUP(A63, STOCKS!A:W, 9, FALSE), "")) -> 1 | K63: =IF(ISBLANK(A63), "", IFERROR(VLOOKUP(A63, STOCKS!A:W, 10, FALSE), "")) -> 6498 | L63: =IF(ISBLANK(A63), "", IFERROR(VLOOKUP(A63, STOCKS!A:W, 11, FALSE), "")) -> 9.91 | M63: =IF(ISBLANK(A63), "", IFERROR(VLOOKUP(A63, STOCKS!A:W, 12, FALSE), "")) -> 141.1 | N63: =IF(ISBLANK(A63), "", IFERROR(VLOOKUP(A63, STOCKS!A:W, 13, FALSE), "")) -> 138.1 | O63: =IF(ISBLANK(A63), "", IFERROR(VLOOKUP(A63, STOCKS!A:W, 14, FALSE), "")) -> 138.78 | P63: =IF(ISBLANK(A63), "", IFERROR(VLOOKUP(A63, STOCKS!A:W, 15, FALSE), "")) -> -538 | Q63: =IF(ISBLANK(A63), "", IFERROR(VLOOKUP(A63, STOCKS!A:W, 16, FALSE), "")) -> '---+- | R63: =IF(ISBLANK(A63), "", IFERROR(VLOOKUP(A63, STOCKS!A:W, 17, FALSE), "")) -> 0 | S63: =IF(ISBLANK(A63), "", IFERROR(VLOOKUP(A63, STOCKS!A:W, 18, FALSE), "")) -> 43 | T63: =IF(ISBLANK(A63), "", IFERROR(VLOOKUP(A63, STOCKS!A:W, 19, FALSE), "")) -> 3176 | U63: =IF(ISBLANK(A63), "", IFERROR(VLOOKUP(A63, STOCKS!A:W, 20, FALSE), "")) -> 48.88 | V63: =IF(ISBLANK(A63), "", IFERROR(VLOOKUP(A63, STOCKS!A:W, 21, FALSE), "")) -> 46132 | W63: =IF(ISBLANK(A63), "", IFERROR(VLOOKUP(A63, STOCKS!A:W, 22, FALSE), ""))
A64: 6558 | B64: =IF(ISBLANK(A64), "", IFERROR(VLOOKUP(A64, STOCKS!A:W, 2, FALSE), "")) -> 興能高 | C64: =IF(ISBLANK(A64), "", IFERROR(VLOOKUP(A64, STOCKS!A:W, 3, FALSE), "")) -> 其他電子業 | D64: =IF(ISBLANK(A64), "", IFERROR(VLOOKUP(A64, category!A:C, 3, FALSE), "")) -> BBU | E64: =IF(ISBLANK(A64), "", IFERROR(VLOOKUP(A64, STOCKS!A:W, 4, FALSE), "")) -> 30.35 | F64: =IF(ISBLANK(A64), "", IFERROR(VLOOKUP(A64, STOCKS!A:W, 5, FALSE), "")) -> 0.35 | G64: =IF(ISBLANK(A64), "", IFERROR(VLOOKUP(A64, STOCKS!A:W, 6, FALSE), "")) -> 1.17 | H64: =IF(ISBLANK(A64), "", IFERROR(VLOOKUP(A64, STOCKS!A:W, 7, FALSE), "")) -> '+++++ | I64: =IF(ISBLANK(A64), "", IFERROR(VLOOKUP(A64, STOCKS!A:W, 8, FALSE), "")) -> 5.46 | J64: =IF(ISBLANK(A64), "", IFERROR(VLOOKUP(A64, STOCKS!A:W, 9, FALSE), "")) -> 0 | K64: =IF(ISBLANK(A64), "", IFERROR(VLOOKUP(A64, STOCKS!A:W, 10, FALSE), "")) -> 520 | L64: =IF(ISBLANK(A64), "", IFERROR(VLOOKUP(A64, STOCKS!A:W, 11, FALSE), "")) -> 0.55 | M64: =IF(ISBLANK(A64), "", IFERROR(VLOOKUP(A64, STOCKS!A:W, 12, FALSE), "")) -> 29.73 | N64: =IF(ISBLANK(A64), "", IFERROR(VLOOKUP(A64, STOCKS!A:W, 13, FALSE), "")) -> 28.66 | O64: =IF(ISBLANK(A64), "", IFERROR(VLOOKUP(A64, STOCKS!A:W, 14, FALSE), "")) -> 28.66 | P64: =IF(ISBLANK(A64), "", IFERROR(VLOOKUP(A64, STOCKS!A:W, 15, FALSE), "")) -> 141 | Q64: =IF(ISBLANK(A64), "", IFERROR(VLOOKUP(A64, STOCKS!A:W, 16, FALSE), "")) -> '-++++ | R64: =IF(ISBLANK(A64), "", IFERROR(VLOOKUP(A64, STOCKS!A:W, 17, FALSE), "")) -> 0 | S64: =IF(ISBLANK(A64), "", IFERROR(VLOOKUP(A64, STOCKS!A:W, 18, FALSE), "")) -> 0 | T64: =IF(ISBLANK(A64), "", IFERROR(VLOOKUP(A64, STOCKS!A:W, 19, FALSE), "")) -> 123 | U64: =IF(ISBLANK(A64), "", IFERROR(VLOOKUP(A64, STOCKS!A:W, 20, FALSE), "")) -> 23.65 | V64: =IF(ISBLANK(A64), "", IFERROR(VLOOKUP(A64, STOCKS!A:W, 21, FALSE), "")) -> 46132 | W64: =IF(ISBLANK(A64), "", IFERROR(VLOOKUP(A64, STOCKS!A:W, 22, FALSE), ""))
A65: 6781 | B65: =IF(ISBLANK(A65), "", IFERROR(VLOOKUP(A65, STOCKS!A:W, 2, FALSE), "")) -> AES-KY | C65: =IF(ISBLANK(A65), "", IFERROR(VLOOKUP(A65, STOCKS!A:W, 3, FALSE), "")) -> 電子零組件業 | D65: =IF(ISBLANK(A65), "", IFERROR(VLOOKUP(A65, category!A:C, 3, FALSE), "")) -> BBU | E65: =IF(ISBLANK(A65), "", IFERROR(VLOOKUP(A65, STOCKS!A:W, 4, FALSE), "")) -> 1010 | F65: =IF(ISBLANK(A65), "", IFERROR(VLOOKUP(A65, STOCKS!A:W, 5, FALSE), "")) -> -30 | G65: =IF(ISBLANK(A65), "", IFERROR(VLOOKUP(A65, STOCKS!A:W, 6, FALSE), "")) -> -2.88 | H65: =IF(ISBLANK(A65), "", IFERROR(VLOOKUP(A65, STOCKS!A:W, 7, FALSE), "")) -> '-+++- | I65: =IF(ISBLANK(A65), "", IFERROR(VLOOKUP(A65, STOCKS!A:W, 8, FALSE), "")) -> 2.45 | J65: =IF(ISBLANK(A65), "", IFERROR(VLOOKUP(A65, STOCKS!A:W, 9, FALSE), "")) -> 1 | K65: =IF(ISBLANK(A65), "", IFERROR(VLOOKUP(A65, STOCKS!A:W, 10, FALSE), "")) -> 1275 | L65: =IF(ISBLANK(A65), "", IFERROR(VLOOKUP(A65, STOCKS!A:W, 11, FALSE), "")) -> 1.49 | M65: =IF(ISBLANK(A65), "", IFERROR(VLOOKUP(A65, STOCKS!A:W, 12, FALSE), "")) -> 1004.8 | N65: =IF(ISBLANK(A65), "", IFERROR(VLOOKUP(A65, STOCKS!A:W, 13, FALSE), "")) -> 994.4 | O65: =IF(ISBLANK(A65), "", IFERROR(VLOOKUP(A65, STOCKS!A:W, 14, FALSE), "")) -> 1020.7 | P65: =IF(ISBLANK(A65), "", IFERROR(VLOOKUP(A65, STOCKS!A:W, 15, FALSE), "")) -> -75 | Q65: =IF(ISBLANK(A65), "", IFERROR(VLOOKUP(A65, STOCKS!A:W, 16, FALSE), "")) -> '-+--- | R65: =IF(ISBLANK(A65), "", IFERROR(VLOOKUP(A65, STOCKS!A:W, 17, FALSE), "")) -> -137 | S65: =IF(ISBLANK(A65), "", IFERROR(VLOOKUP(A65, STOCKS!A:W, 18, FALSE), "")) -> 0 | T65: =IF(ISBLANK(A65), "", IFERROR(VLOOKUP(A65, STOCKS!A:W, 19, FALSE), "")) -> 571 | U65: =IF(ISBLANK(A65), "", IFERROR(VLOOKUP(A65, STOCKS!A:W, 20, FALSE), "")) -> 44.78 | V65: =IF(ISBLANK(A65), "", IFERROR(VLOOKUP(A65, STOCKS!A:W, 21, FALSE), "")) -> 46132 | W65: =IF(ISBLANK(A65), "", IFERROR(VLOOKUP(A65, STOCKS!A:W, 22, FALSE), ""))
A66: 2349 | B66: =IF(ISBLANK(A66), "", IFERROR(VLOOKUP(A66, STOCKS!A:W, 2, FALSE), "")) -> 錸德 | C66: =IF(ISBLANK(A66), "", IFERROR(VLOOKUP(A66, STOCKS!A:W, 3, FALSE), "")) -> 光電業 | D66: =IF(ISBLANK(A66), "", IFERROR(VLOOKUP(A66, category!A:C, 3, FALSE), "")) -> BBU | E66: =IF(ISBLANK(A66), "", IFERROR(VLOOKUP(A66, STOCKS!A:W, 4, FALSE), "")) -> 13.55 | F66: =IF(ISBLANK(A66), "", IFERROR(VLOOKUP(A66, STOCKS!A:W, 5, FALSE), "")) -> -0.2 | G66: =IF(ISBLANK(A66), "", IFERROR(VLOOKUP(A66, STOCKS!A:W, 6, FALSE), "")) -> -1.45 | H66: =IF(ISBLANK(A66), "", IFERROR(VLOOKUP(A66, STOCKS!A:W, 7, FALSE), "")) -> '+++-- | I66: =IF(ISBLANK(A66), "", IFERROR(VLOOKUP(A66, STOCKS!A:W, 8, FALSE), "")) -> 1.25 | J66: =IF(ISBLANK(A66), "", IFERROR(VLOOKUP(A66, STOCKS!A:W, 9, FALSE), "")) -> 1 | K66: =IF(ISBLANK(A66), "", IFERROR(VLOOKUP(A66, STOCKS!A:W, 10, FALSE), "")) -> 4238 | L66: =IF(ISBLANK(A66), "", IFERROR(VLOOKUP(A66, STOCKS!A:W, 11, FALSE), "")) -> 0.61 | M66: =IF(ISBLANK(A66), "", IFERROR(VLOOKUP(A66, STOCKS!A:W, 12, FALSE), "")) -> 13.71 | N66: =IF(ISBLANK(A66), "", IFERROR(VLOOKUP(A66, STOCKS!A:W, 13, FALSE), "")) -> 13.44 | O66: =IF(ISBLANK(A66), "", IFERROR(VLOOKUP(A66, STOCKS!A:W, 14, FALSE), "")) -> 13.57 | P66: =IF(ISBLANK(A66), "", IFERROR(VLOOKUP(A66, STOCKS!A:W, 15, FALSE), "")) -> -97 | Q66: =IF(ISBLANK(A66), "", IFERROR(VLOOKUP(A66, STOCKS!A:W, 16, FALSE), "")) -> '++++- | R66: =IF(ISBLANK(A66), "", IFERROR(VLOOKUP(A66, STOCKS!A:W, 17, FALSE), "")) -> 0 | S66: =IF(ISBLANK(A66), "", IFERROR(VLOOKUP(A66, STOCKS!A:W, 18, FALSE), "")) -> -88 | T66: =IF(ISBLANK(A66), "", IFERROR(VLOOKUP(A66, STOCKS!A:W, 19, FALSE), "")) -> 0 | U66: =IF(ISBLANK(A66), "", IFERROR(VLOOKUP(A66, STOCKS!A:W, 20, FALSE), "")) -> 0 | V66: =IF(ISBLANK(A66), "", IFERROR(VLOOKUP(A66, STOCKS!A:W, 21, FALSE), "")) -> 46132 | W66: =IF(ISBLANK(A66), "", IFERROR(VLOOKUP(A66, STOCKS!A:W, 22, FALSE), ""))
A67: 5309 | B67: =IF(ISBLANK(A67), "", IFERROR(VLOOKUP(A67, STOCKS!A:W, 2, FALSE), "")) -> 系統電 | C67: =IF(ISBLANK(A67), "", IFERROR(VLOOKUP(A67, STOCKS!A:W, 3, FALSE), "")) -> 電子零組件業 | D67: =IF(ISBLANK(A67), "", IFERROR(VLOOKUP(A67, category!A:C, 3, FALSE), "")) -> BBU | E67: =IF(ISBLANK(A67), "", IFERROR(VLOOKUP(A67, STOCKS!A:W, 4, FALSE), "")) -> 60.2 | F67: =IF(ISBLANK(A67), "", IFERROR(VLOOKUP(A67, STOCKS!A:W, 5, FALSE), "")) -> 1.4 | G67: =IF(ISBLANK(A67), "", IFERROR(VLOOKUP(A67, STOCKS!A:W, 6, FALSE), "")) -> 2.38 | H67: =IF(ISBLANK(A67), "", IFERROR(VLOOKUP(A67, STOCKS!A:W, 7, FALSE), "")) -> '+++-+ | I67: =IF(ISBLANK(A67), "", IFERROR(VLOOKUP(A67, STOCKS!A:W, 8, FALSE), "")) -> 6.95 | J67: =IF(ISBLANK(A67), "", IFERROR(VLOOKUP(A67, STOCKS!A:W, 9, FALSE), "")) -> 0 | K67: =IF(ISBLANK(A67), "", IFERROR(VLOOKUP(A67, STOCKS!A:W, 10, FALSE), "")) -> 5360 | L67: =IF(ISBLANK(A67), "", IFERROR(VLOOKUP(A67, STOCKS!A:W, 11, FALSE), "")) -> 2.33 | M67: =IF(ISBLANK(A67), "", IFERROR(VLOOKUP(A67, STOCKS!A:W, 12, FALSE), "")) -> 58.64 | N67: =IF(ISBLANK(A67), "", IFERROR(VLOOKUP(A67, STOCKS!A:W, 13, FALSE), "")) -> 57.52 | O67: =IF(ISBLANK(A67), "", IFERROR(VLOOKUP(A67, STOCKS!A:W, 14, FALSE), "")) -> 58.28 | P67: =IF(ISBLANK(A67), "", IFERROR(VLOOKUP(A67, STOCKS!A:W, 15, FALSE), "")) -> 1324 | Q67: =IF(ISBLANK(A67), "", IFERROR(VLOOKUP(A67, STOCKS!A:W, 16, FALSE), "")) -> '+-+-+ | R67: =IF(ISBLANK(A67), "", IFERROR(VLOOKUP(A67, STOCKS!A:W, 17, FALSE), "")) -> 0 | S67: =IF(ISBLANK(A67), "", IFERROR(VLOOKUP(A67, STOCKS!A:W, 18, FALSE), "")) -> 77 | T67: =IF(ISBLANK(A67), "", IFERROR(VLOOKUP(A67, STOCKS!A:W, 19, FALSE), "")) -> 1733 | U67: =IF(ISBLANK(A67), "", IFERROR(VLOOKUP(A67, STOCKS!A:W, 20, FALSE), "")) -> 32.33 | V67: =IF(ISBLANK(A67), "", IFERROR(VLOOKUP(A67, STOCKS!A:W, 21, FALSE), "")) -> 46132 | W67: =IF(ISBLANK(A67), "", IFERROR(VLOOKUP(A67, STOCKS!A:W, 22, FALSE), ""))
A68: 題材-航太
A69: 2634 | B69: =IF(ISBLANK(A69), "", IFERROR(VLOOKUP(A69, STOCKS!A:W, 2, FALSE), "")) -> 漢翔 | C69: =IF(ISBLANK(A69), "", IFERROR(VLOOKUP(A69, STOCKS!A:W, 3, FALSE), "")) -> 航運業 | D69: =IF(ISBLANK(A69), "", IFERROR(VLOOKUP(A69, category!A:C, 3, FALSE), "")) -> 軍工/航太 | E69: =IF(ISBLANK(A69), "", IFERROR(VLOOKUP(A69, STOCKS!A:W, 4, FALSE), "")) -> 50.4 | F69: =IF(ISBLANK(A69), "", IFERROR(VLOOKUP(A69, STOCKS!A:W, 5, FALSE), "")) -> 0 | G69: =IF(ISBLANK(A69), "", IFERROR(VLOOKUP(A69, STOCKS!A:W, 6, FALSE), "")) -> 0 | H69: =IF(ISBLANK(A69), "", IFERROR(VLOOKUP(A69, STOCKS!A:W, 7, FALSE), "")) -> '++++- | I69: =IF(ISBLANK(A69), "", IFERROR(VLOOKUP(A69, STOCKS!A:W, 8, FALSE), "")) -> 7.19 | J69: =IF(ISBLANK(A69), "", IFERROR(VLOOKUP(A69, STOCKS!A:W, 9, FALSE), "")) -> 0 | K69: =IF(ISBLANK(A69), "", IFERROR(VLOOKUP(A69, STOCKS!A:W, 10, FALSE), "")) -> 6483 | L69: =IF(ISBLANK(A69), "", IFERROR(VLOOKUP(A69, STOCKS!A:W, 11, FALSE), "")) -> 0.69 | M69: =IF(ISBLANK(A69), "", IFERROR(VLOOKUP(A69, STOCKS!A:W, 12, FALSE), "")) -> 49.14 | N69: =IF(ISBLANK(A69), "", IFERROR(VLOOKUP(A69, STOCKS!A:W, 13, FALSE), "")) -> 47.93 | O69: =IF(ISBLANK(A69), "", IFERROR(VLOOKUP(A69, STOCKS!A:W, 14, FALSE), "")) -> 48.3 | P69: =IF(ISBLANK(A69), "", IFERROR(VLOOKUP(A69, STOCKS!A:W, 15, FALSE), "")) -> -799 | Q69: =IF(ISBLANK(A69), "", IFERROR(VLOOKUP(A69, STOCKS!A:W, 16, FALSE), "")) -> '+-++- | R69: =IF(ISBLANK(A69), "", IFERROR(VLOOKUP(A69, STOCKS!A:W, 17, FALSE), "")) -> -6 | S69: =IF(ISBLANK(A69), "", IFERROR(VLOOKUP(A69, STOCKS!A:W, 18, FALSE), "")) -> 4 | T69: =IF(ISBLANK(A69), "", IFERROR(VLOOKUP(A69, STOCKS!A:W, 19, FALSE), "")) -> 1976 | U69: =IF(ISBLANK(A69), "", IFERROR(VLOOKUP(A69, STOCKS!A:W, 20, FALSE), "")) -> 30.48 | V69: =IF(ISBLANK(A69), "", IFERROR(VLOOKUP(A69, STOCKS!A:W, 21, FALSE), "")) -> 46132 | W69: =IF(ISBLANK(A69), "", IFERROR(VLOOKUP(A69, STOCKS!A:W, 22, FALSE), ""))
A70: 2645 | B70: =IF(ISBLANK(A70), "", IFERROR(VLOOKUP(A70, STOCKS!A:W, 2, FALSE), "")) -> 長榮航太 | C70: =IF(ISBLANK(A70), "", IFERROR(VLOOKUP(A70, STOCKS!A:W, 3, FALSE), "")) -> 航運業 | D70: =IF(ISBLANK(A70), "", IFERROR(VLOOKUP(A70, category!A:C, 3, FALSE), "")) -> 軍工/航太 | E70: =IF(ISBLANK(A70), "", IFERROR(VLOOKUP(A70, STOCKS!A:W, 4, FALSE), "")) -> 166 | F70: =IF(ISBLANK(A70), "", IFERROR(VLOOKUP(A70, STOCKS!A:W, 5, FALSE), "")) -> 5.5 | G70: =IF(ISBLANK(A70), "", IFERROR(VLOOKUP(A70, STOCKS!A:W, 6, FALSE), "")) -> 3.43 | H70: =IF(ISBLANK(A70), "", IFERROR(VLOOKUP(A70, STOCKS!A:W, 7, FALSE), "")) -> '+++++ | I70: =IF(ISBLANK(A70), "", IFERROR(VLOOKUP(A70, STOCKS!A:W, 8, FALSE), "")) -> 9.93 | J70: =IF(ISBLANK(A70), "", IFERROR(VLOOKUP(A70, STOCKS!A:W, 9, FALSE), "")) -> 0 | K70: =IF(ISBLANK(A70), "", IFERROR(VLOOKUP(A70, STOCKS!A:W, 10, FALSE), "")) -> 2331 | L70: =IF(ISBLANK(A70), "", IFERROR(VLOOKUP(A70, STOCKS!A:W, 11, FALSE), "")) -> 0.62 | M70: =IF(ISBLANK(A70), "", IFERROR(VLOOKUP(A70, STOCKS!A:W, 12, FALSE), "")) -> 157.6 | N70: =IF(ISBLANK(A70), "", IFERROR(VLOOKUP(A70, STOCKS!A:W, 13, FALSE), "")) -> 153.55 | O70: =IF(ISBLANK(A70), "", IFERROR(VLOOKUP(A70, STOCKS!A:W, 14, FALSE), "")) -> 151.78 | P70: =IF(ISBLANK(A70), "", IFERROR(VLOOKUP(A70, STOCKS!A:W, 15, FALSE), "")) -> 893 | Q70: =IF(ISBLANK(A70), "", IFERROR(VLOOKUP(A70, STOCKS!A:W, 16, FALSE), "")) -> '+++++ | R70: =IF(ISBLANK(A70), "", IFERROR(VLOOKUP(A70, STOCKS!A:W, 17, FALSE), "")) -> -3 | S70: =IF(ISBLANK(A70), "", IFERROR(VLOOKUP(A70, STOCKS!A:W, 18, FALSE), "")) -> 74 | T70: =IF(ISBLANK(A70), "", IFERROR(VLOOKUP(A70, STOCKS!A:W, 19, FALSE), "")) -> 656 | U70: =IF(ISBLANK(A70), "", IFERROR(VLOOKUP(A70, STOCKS!A:W, 20, FALSE), "")) -> 28.14 | V70: =IF(ISBLANK(A70), "", IFERROR(VLOOKUP(A70, STOCKS!A:W, 21, FALSE), "")) -> 46132 | W70: =IF(ISBLANK(A70), "", IFERROR(VLOOKUP(A70, STOCKS!A:W, 22, FALSE), ""))
A71: 4541 | B71: =IF(ISBLANK(A71), "", IFERROR(VLOOKUP(A71, STOCKS!A:W, 2, FALSE), "")) -> 晟田 | C71: =IF(ISBLANK(A71), "", IFERROR(VLOOKUP(A71, STOCKS!A:W, 3, FALSE), "")) -> 其他業 | D71: =IF(ISBLANK(A71), "", IFERROR(VLOOKUP(A71, category!A:C, 3, FALSE), "")) -> 軍工/航太 | E71: =IF(ISBLANK(A71), "", IFERROR(VLOOKUP(A71, STOCKS!A:W, 4, FALSE), "")) -> 49.35 | F71: =IF(ISBLANK(A71), "", IFERROR(VLOOKUP(A71, STOCKS!A:W, 5, FALSE), "")) -> 1.05 | G71: =IF(ISBLANK(A71), "", IFERROR(VLOOKUP(A71, STOCKS!A:W, 6, FALSE), "")) -> 2.17 | H71: =IF(ISBLANK(A71), "", IFERROR(VLOOKUP(A71, STOCKS!A:W, 7, FALSE), "")) -> '+-+++ | I71: =IF(ISBLANK(A71), "", IFERROR(VLOOKUP(A71, STOCKS!A:W, 8, FALSE), "")) -> 6.37 | J71: =IF(ISBLANK(A71), "", IFERROR(VLOOKUP(A71, STOCKS!A:W, 9, FALSE), "")) -> 1 | K71: =IF(ISBLANK(A71), "", IFERROR(VLOOKUP(A71, STOCKS!A:W, 10, FALSE), "")) -> 3379 | L71: =IF(ISBLANK(A71), "", IFERROR(VLOOKUP(A71, STOCKS!A:W, 11, FALSE), "")) -> 5 | M71: =IF(ISBLANK(A71), "", IFERROR(VLOOKUP(A71, STOCKS!A:W, 12, FALSE), "")) -> 47.72 | N71: =IF(ISBLANK(A71), "", IFERROR(VLOOKUP(A71, STOCKS!A:W, 13, FALSE), "")) -> 45.71 | O71: =IF(ISBLANK(A71), "", IFERROR(VLOOKUP(A71, STOCKS!A:W, 14, FALSE), "")) -> 43.71 | P71: =IF(ISBLANK(A71), "", IFERROR(VLOOKUP(A71, STOCKS!A:W, 15, FALSE), "")) -> 438 | Q71: =IF(ISBLANK(A71), "", IFERROR(VLOOKUP(A71, STOCKS!A:W, 16, FALSE), "")) -> '+++++ | R71: =IF(ISBLANK(A71), "", IFERROR(VLOOKUP(A71, STOCKS!A:W, 17, FALSE), "")) -> 0 | S71: =IF(ISBLANK(A71), "", IFERROR(VLOOKUP(A71, STOCKS!A:W, 18, FALSE), "")) -> 2 | T71: =IF(ISBLANK(A71), "", IFERROR(VLOOKUP(A71, STOCKS!A:W, 19, FALSE), "")) -> 1176 | U71: =IF(ISBLANK(A71), "", IFERROR(VLOOKUP(A71, STOCKS!A:W, 20, FALSE), "")) -> 34.8 | V71: =IF(ISBLANK(A71), "", IFERROR(VLOOKUP(A71, STOCKS!A:W, 21, FALSE), "")) -> 46132 | W71: =IF(ISBLANK(A71), "", IFERROR(VLOOKUP(A71, STOCKS!A:W, 22, FALSE), ""))
A72: 4572 | B72: =IF(ISBLANK(A72), "", IFERROR(VLOOKUP(A72, STOCKS!A:W, 2, FALSE), "")) -> 駐龍 | C72: =IF(ISBLANK(A72), "", IFERROR(VLOOKUP(A72, STOCKS!A:W, 3, FALSE), "")) -> 電機機械 | D72: =IF(ISBLANK(A72), "", IFERROR(VLOOKUP(A72, category!A:C, 3, FALSE), "")) -> 軍工/航太 | E72: =IF(ISBLANK(A72), "", IFERROR(VLOOKUP(A72, STOCKS!A:W, 4, FALSE), "")) -> 148 | F72: =IF(ISBLANK(A72), "", IFERROR(VLOOKUP(A72, STOCKS!A:W, 5, FALSE), "")) -> 1.5 | G72: =IF(ISBLANK(A72), "", IFERROR(VLOOKUP(A72, STOCKS!A:W, 6, FALSE), "")) -> 1.02 | H72: =IF(ISBLANK(A72), "", IFERROR(VLOOKUP(A72, STOCKS!A:W, 7, FALSE), "")) -> '+++++ | I72: =IF(ISBLANK(A72), "", IFERROR(VLOOKUP(A72, STOCKS!A:W, 8, FALSE), "")) -> 4.51 | J72: =IF(ISBLANK(A72), "", IFERROR(VLOOKUP(A72, STOCKS!A:W, 9, FALSE), "")) -> 0 | K72: =IF(ISBLANK(A72), "", IFERROR(VLOOKUP(A72, STOCKS!A:W, 10, FALSE), "")) -> 49 | L72: =IF(ISBLANK(A72), "", IFERROR(VLOOKUP(A72, STOCKS!A:W, 11, FALSE), "")) -> 0.12 | M72: =IF(ISBLANK(A72), "", IFERROR(VLOOKUP(A72, STOCKS!A:W, 12, FALSE), "")) -> 145.6 | N72: =IF(ISBLANK(A72), "", IFERROR(VLOOKUP(A72, STOCKS!A:W, 13, FALSE), "")) -> 143.55 | O72: =IF(ISBLANK(A72), "", IFERROR(VLOOKUP(A72, STOCKS!A:W, 14, FALSE), "")) -> 143 | P72: =IF(ISBLANK(A72), "", IFERROR(VLOOKUP(A72, STOCKS!A:W, 15, FALSE), "")) -> 20 | Q72: =IF(ISBLANK(A72), "", IFERROR(VLOOKUP(A72, STOCKS!A:W, 16, FALSE), "")) -> '+++++ | R72: =IF(ISBLANK(A72), "", IFERROR(VLOOKUP(A72, STOCKS!A:W, 17, FALSE), "")) -> 0 | S72: =IF(ISBLANK(A72), "", IFERROR(VLOOKUP(A72, STOCKS!A:W, 18, FALSE), "")) -> 0 | T72: =IF(ISBLANK(A72), "", IFERROR(VLOOKUP(A72, STOCKS!A:W, 19, FALSE), "")) -> 11 | U72: =IF(ISBLANK(A72), "", IFERROR(VLOOKUP(A72, STOCKS!A:W, 20, FALSE), "")) -> 22.45 | V72: =IF(ISBLANK(A72), "", IFERROR(VLOOKUP(A72, STOCKS!A:W, 21, FALSE), "")) -> 46132 | W72: =IF(ISBLANK(A72), "", IFERROR(VLOOKUP(A72, STOCKS!A:W, 22, FALSE), ""))
A73: 6829 | B73: =IF(ISBLANK(A73), "", IFERROR(VLOOKUP(A73, STOCKS!A:W, 2, FALSE), "")) -> 千附精密 | C73: =IF(ISBLANK(A73), "", IFERROR(VLOOKUP(A73, STOCKS!A:W, 3, FALSE), "")) -> 半導體業 | D73: =IF(ISBLANK(A73), "", IFERROR(VLOOKUP(A73, category!A:C, 3, FALSE), "")) -> 軍工/航太 | E73: =IF(ISBLANK(A73), "", IFERROR(VLOOKUP(A73, STOCKS!A:W, 4, FALSE), "")) -> 216.5 | F73: =IF(ISBLANK(A73), "", IFERROR(VLOOKUP(A73, STOCKS!A:W, 5, FALSE), "")) -> 19.5 | G73: =IF(ISBLANK(A73), "", IFERROR(VLOOKUP(A73, STOCKS!A:W, 6, FALSE), "")) -> 9.9 | H73: =IF(ISBLANK(A73), "", IFERROR(VLOOKUP(A73, STOCKS!A:W, 7, FALSE), "")) -> '+++++ | I73: =IF(ISBLANK(A73), "", IFERROR(VLOOKUP(A73, STOCKS!A:W, 8, FALSE), "")) -> 46.36 | J73: =IF(ISBLANK(A73), "", IFERROR(VLOOKUP(A73, STOCKS!A:W, 9, FALSE), "")) -> 5 | K73: =IF(ISBLANK(A73), "", IFERROR(VLOOKUP(A73, STOCKS!A:W, 10, FALSE), "")) -> 742 | L73: =IF(ISBLANK(A73), "", IFERROR(VLOOKUP(A73, STOCKS!A:W, 11, FALSE), "")) -> 1.25 | M73: =IF(ISBLANK(A73), "", IFERROR(VLOOKUP(A73, STOCKS!A:W, 12, FALSE), "")) -> 181.1 | N73: =IF(ISBLANK(A73), "", IFERROR(VLOOKUP(A73, STOCKS!A:W, 13, FALSE), "")) -> 154.35 | O73: =IF(ISBLANK(A73), "", IFERROR(VLOOKUP(A73, STOCKS!A:W, 14, FALSE), "")) -> 134.55 | P73: =IF(ISBLANK(A73), "", IFERROR(VLOOKUP(A73, STOCKS!A:W, 15, FALSE), "")) -> -21 | Q73: =IF(ISBLANK(A73), "", IFERROR(VLOOKUP(A73, STOCKS!A:W, 16, FALSE), "")) -> '+--+- | R73: =IF(ISBLANK(A73), "", IFERROR(VLOOKUP(A73, STOCKS!A:W, 17, FALSE), "")) -> 0 | S73: =IF(ISBLANK(A73), "", IFERROR(VLOOKUP(A73, STOCKS!A:W, 18, FALSE), "")) -> 0 | T73: =IF(ISBLANK(A73), "", IFERROR(VLOOKUP(A73, STOCKS!A:W, 19, FALSE), "")) -> 0 | U73: =IF(ISBLANK(A73), "", IFERROR(VLOOKUP(A73, STOCKS!A:W, 20, FALSE), "")) -> 0 | V73: =IF(ISBLANK(A73), "", IFERROR(VLOOKUP(A73, STOCKS!A:W, 21, FALSE), "")) -> 46132 | W73: =IF(ISBLANK(A73), "", IFERROR(VLOOKUP(A73, STOCKS!A:W, 22, FALSE), "")) -> 本公司有價證券近期多次達公佈注意交易資訊標準， 故公告相關訊息，以利投資人區別瞭解。
A74: 5284 | B74: =IF(ISBLANK(A74), "", IFERROR(VLOOKUP(A74, STOCKS!A:W, 2, FALSE), "")) -> jpp-KY | C74: =IF(ISBLANK(A74), "", IFERROR(VLOOKUP(A74, STOCKS!A:W, 3, FALSE), "")) -> 其他業 | D74: =IF(ISBLANK(A74), "", IFERROR(VLOOKUP(A74, category!A:C, 3, FALSE), "")) -> 航太 | E74: =IF(ISBLANK(A74), "", IFERROR(VLOOKUP(A74, STOCKS!A:W, 4, FALSE), "")) -> 350 | F74: =IF(ISBLANK(A74), "", IFERROR(VLOOKUP(A74, STOCKS!A:W, 5, FALSE), "")) -> 31.5 | G74: =IF(ISBLANK(A74), "", IFERROR(VLOOKUP(A74, STOCKS!A:W, 6, FALSE), "")) -> 9.89 | H74: =IF(ISBLANK(A74), "", IFERROR(VLOOKUP(A74, STOCKS!A:W, 7, FALSE), "")) -> '-+-++ | I74: =IF(ISBLANK(A74), "", IFERROR(VLOOKUP(A74, STOCKS!A:W, 8, FALSE), "")) -> 11.44 | J74: =IF(ISBLANK(A74), "", IFERROR(VLOOKUP(A74, STOCKS!A:W, 9, FALSE), "")) -> 1 | K74: =IF(ISBLANK(A74), "", IFERROR(VLOOKUP(A74, STOCKS!A:W, 10, FALSE), "")) -> 1872 | L74: =IF(ISBLANK(A74), "", IFERROR(VLOOKUP(A74, STOCKS!A:W, 11, FALSE), "")) -> 3.54 | M74: =IF(ISBLANK(A74), "", IFERROR(VLOOKUP(A74, STOCKS!A:W, 12, FALSE), "")) -> 323.3 | N74: =IF(ISBLANK(A74), "", IFERROR(VLOOKUP(A74, STOCKS!A:W, 13, FALSE), "")) -> 310.5 | O74: =IF(ISBLANK(A74), "", IFERROR(VLOOKUP(A74, STOCKS!A:W, 14, FALSE), "")) -> 294.62 | P74: =IF(ISBLANK(A74), "", IFERROR(VLOOKUP(A74, STOCKS!A:W, 15, FALSE), "")) -> 448 | Q74: =IF(ISBLANK(A74), "", IFERROR(VLOOKUP(A74, STOCKS!A:W, 16, FALSE), "")) -> '-+-++ | R74: =IF(ISBLANK(A74), "", IFERROR(VLOOKUP(A74, STOCKS!A:W, 17, FALSE), "")) -> 0 | S74: =IF(ISBLANK(A74), "", IFERROR(VLOOKUP(A74, STOCKS!A:W, 18, FALSE), "")) -> 69 | T74: =IF(ISBLANK(A74), "", IFERROR(VLOOKUP(A74, STOCKS!A:W, 19, FALSE), "")) -> 350 | U74: =IF(ISBLANK(A74), "", IFERROR(VLOOKUP(A74, STOCKS!A:W, 20, FALSE), "")) -> 18.7 | V74: =IF(ISBLANK(A74), "", IFERROR(VLOOKUP(A74, STOCKS!A:W, 21, FALSE), "")) -> 46132 | W74: =IF(ISBLANK(A74), "", IFERROR(VLOOKUP(A74, STOCKS!A:W, 22, FALSE), "")) -> 公告本公司簽訂發行第四及第五次無擔保轉換公司債 代收股款行庫及存儲專戶
A75: 8222 | B75: =IF(ISBLANK(A75), "", IFERROR(VLOOKUP(A75, STOCKS!A:W, 2, FALSE), "")) -> 寶一 | C75: =IF(ISBLANK(A75), "", IFERROR(VLOOKUP(A75, STOCKS!A:W, 3, FALSE), "")) -> 電機機械 | D75: =IF(ISBLANK(A75), "", IFERROR(VLOOKUP(A75, category!A:C, 3, FALSE), "")) -> 軍工/航太 | E75: =IF(ISBLANK(A75), "", IFERROR(VLOOKUP(A75, STOCKS!A:W, 4, FALSE), "")) -> 37.85 | F75: =IF(ISBLANK(A75), "", IFERROR(VLOOKUP(A75, STOCKS!A:W, 5, FALSE), "")) -> 0 | G75: =IF(ISBLANK(A75), "", IFERROR(VLOOKUP(A75, STOCKS!A:W, 6, FALSE), "")) -> 0 | H75: =IF(ISBLANK(A75), "", IFERROR(VLOOKUP(A75, STOCKS!A:W, 7, FALSE), "")) -> '++++- | I75: =IF(ISBLANK(A75), "", IFERROR(VLOOKUP(A75, STOCKS!A:W, 8, FALSE), "")) -> 9.45 | J75: =IF(ISBLANK(A75), "", IFERROR(VLOOKUP(A75, STOCKS!A:W, 9, FALSE), "")) -> 0 | K75: =IF(ISBLANK(A75), "", IFERROR(VLOOKUP(A75, STOCKS!A:W, 10, FALSE), "")) -> 565 | L75: =IF(ISBLANK(A75), "", IFERROR(VLOOKUP(A75, STOCKS!A:W, 11, FALSE), "")) -> 0.82 | M75: =IF(ISBLANK(A75), "", IFERROR(VLOOKUP(A75, STOCKS!A:W, 12, FALSE), "")) -> 36.89 | N75: =IF(ISBLANK(A75), "", IFERROR(VLOOKUP(A75, STOCKS!A:W, 13, FALSE), "")) -> 35.61 | O75: =IF(ISBLANK(A75), "", IFERROR(VLOOKUP(A75, STOCKS!A:W, 14, FALSE), "")) -> 35.82 | P75: =IF(ISBLANK(A75), "", IFERROR(VLOOKUP(A75, STOCKS!A:W, 15, FALSE), "")) -> 61 | Q75: =IF(ISBLANK(A75), "", IFERROR(VLOOKUP(A75, STOCKS!A:W, 16, FALSE), "")) -> '++-++ | R75: =IF(ISBLANK(A75), "", IFERROR(VLOOKUP(A75, STOCKS!A:W, 17, FALSE), "")) -> 0 | S75: =IF(ISBLANK(A75), "", IFERROR(VLOOKUP(A75, STOCKS!A:W, 18, FALSE), "")) -> 0 | T75: =IF(ISBLANK(A75), "", IFERROR(VLOOKUP(A75, STOCKS!A:W, 19, FALSE), "")) -> 134 | U75: =IF(ISBLANK(A75), "", IFERROR(VLOOKUP(A75, STOCKS!A:W, 20, FALSE), "")) -> 23.72 | V75: =IF(ISBLANK(A75), "", IFERROR(VLOOKUP(A75, STOCKS!A:W, 21, FALSE), "")) -> 46132 | W75: =IF(ISBLANK(A75), "", IFERROR(VLOOKUP(A75, STOCKS!A:W, 22, FALSE), ""))
A76: 3004 | B76: =IF(ISBLANK(A76), "", IFERROR(VLOOKUP(A76, STOCKS!A:W, 2, FALSE), "")) -> 豐達科 | C76: =IF(ISBLANK(A76), "", IFERROR(VLOOKUP(A76, STOCKS!A:W, 3, FALSE), "")) -> 鋼鐵工業 | D76: =IF(ISBLANK(A76), "", IFERROR(VLOOKUP(A76, category!A:C, 3, FALSE), "")) -> 航太 | E76: =IF(ISBLANK(A76), "", IFERROR(VLOOKUP(A76, STOCKS!A:W, 4, FALSE), "")) -> 117.5 | F76: =IF(ISBLANK(A76), "", IFERROR(VLOOKUP(A76, STOCKS!A:W, 5, FALSE), "")) -> 4.5 | G76: =IF(ISBLANK(A76), "", IFERROR(VLOOKUP(A76, STOCKS!A:W, 6, FALSE), "")) -> 3.98 | H76: =IF(ISBLANK(A76), "", IFERROR(VLOOKUP(A76, STOCKS!A:W, 7, FALSE), "")) -> '----+ | I76: =IF(ISBLANK(A76), "", IFERROR(VLOOKUP(A76, STOCKS!A:W, 8, FALSE), "")) -> -1.14 | J76: =IF(ISBLANK(A76), "", IFERROR(VLOOKUP(A76, STOCKS!A:W, 9, FALSE), "")) -> 2 | K76: =IF(ISBLANK(A76), "", IFERROR(VLOOKUP(A76, STOCKS!A:W, 10, FALSE), "")) -> 467 | L76: =IF(ISBLANK(A76), "", IFERROR(VLOOKUP(A76, STOCKS!A:W, 11, FALSE), "")) -> 0.73 | M76: =IF(ISBLANK(A76), "", IFERROR(VLOOKUP(A76, STOCKS!A:W, 12, FALSE), "")) -> 115.6 | N76: =IF(ISBLANK(A76), "", IFERROR(VLOOKUP(A76, STOCKS!A:W, 13, FALSE), "")) -> 115 | O76: =IF(ISBLANK(A76), "", IFERROR(VLOOKUP(A76, STOCKS!A:W, 14, FALSE), "")) -> 108.66 | P76: =IF(ISBLANK(A76), "", IFERROR(VLOOKUP(A76, STOCKS!A:W, 15, FALSE), "")) -> 64 | Q76: =IF(ISBLANK(A76), "", IFERROR(VLOOKUP(A76, STOCKS!A:W, 16, FALSE), "")) -> '-+-++ | R76: =IF(ISBLANK(A76), "", IFERROR(VLOOKUP(A76, STOCKS!A:W, 17, FALSE), "")) -> 0 | S76: =IF(ISBLANK(A76), "", IFERROR(VLOOKUP(A76, STOCKS!A:W, 18, FALSE), "")) -> 45 | T76: =IF(ISBLANK(A76), "", IFERROR(VLOOKUP(A76, STOCKS!A:W, 19, FALSE), "")) -> 110 | U76: =IF(ISBLANK(A76), "", IFERROR(VLOOKUP(A76, STOCKS!A:W, 20, FALSE), "")) -> 23.55 | V76: =IF(ISBLANK(A76), "", IFERROR(VLOOKUP(A76, STOCKS!A:W, 21, FALSE), "")) -> 46132 | W76: =IF(ISBLANK(A76), "", IFERROR(VLOOKUP(A76, STOCKS!A:W, 22, FALSE), ""))
A77: 5009 | B77: =IF(ISBLANK(A77), "", IFERROR(VLOOKUP(A77, STOCKS!A:W, 2, FALSE), "")) -> 榮剛 | C77: =IF(ISBLANK(A77), "", IFERROR(VLOOKUP(A77, STOCKS!A:W, 3, FALSE), "")) -> 鋼鐵工業 | D77: =IF(ISBLANK(A77), "", IFERROR(VLOOKUP(A77, category!A:C, 3, FALSE), "")) -> 航太 | E77: =IF(ISBLANK(A77), "", IFERROR(VLOOKUP(A77, STOCKS!A:W, 4, FALSE), "")) -> 33.7 | F77: =IF(ISBLANK(A77), "", IFERROR(VLOOKUP(A77, STOCKS!A:W, 5, FALSE), "")) -> 2.4 | G77: =IF(ISBLANK(A77), "", IFERROR(VLOOKUP(A77, STOCKS!A:W, 6, FALSE), "")) -> 7.67 | H77: =IF(ISBLANK(A77), "", IFERROR(VLOOKUP(A77, STOCKS!A:W, 7, FALSE), "")) -> '--+++ | I77: =IF(ISBLANK(A77), "", IFERROR(VLOOKUP(A77, STOCKS!A:W, 8, FALSE), "")) -> 8.15 | J77: =IF(ISBLANK(A77), "", IFERROR(VLOOKUP(A77, STOCKS!A:W, 9, FALSE), "")) -> 0 | K77: =IF(ISBLANK(A77), "", IFERROR(VLOOKUP(A77, STOCKS!A:W, 10, FALSE), "")) -> 6513 | L77: =IF(ISBLANK(A77), "", IFERROR(VLOOKUP(A77, STOCKS!A:W, 11, FALSE), "")) -> 1.08 | M77: =IF(ISBLANK(A77), "", IFERROR(VLOOKUP(A77, STOCKS!A:W, 12, FALSE), "")) -> 31.7 | N77: =IF(ISBLANK(A77), "", IFERROR(VLOOKUP(A77, STOCKS!A:W, 13, FALSE), "")) -> 31.8 | O77: =IF(ISBLANK(A77), "", IFERROR(VLOOKUP(A77, STOCKS!A:W, 14, FALSE), "")) -> 32.35 | P77: =IF(ISBLANK(A77), "", IFERROR(VLOOKUP(A77, STOCKS!A:W, 15, FALSE), "")) -> 2382 | Q77: =IF(ISBLANK(A77), "", IFERROR(VLOOKUP(A77, STOCKS!A:W, 16, FALSE), "")) -> '+--++ | R77: =IF(ISBLANK(A77), "", IFERROR(VLOOKUP(A77, STOCKS!A:W, 17, FALSE), "")) -> -1 | S77: =IF(ISBLANK(A77), "", IFERROR(VLOOKUP(A77, STOCKS!A:W, 18, FALSE), "")) -> 357 | T77: =IF(ISBLANK(A77), "", IFERROR(VLOOKUP(A77, STOCKS!A:W, 19, FALSE), "")) -> 1136 | U77: =IF(ISBLANK(A77), "", IFERROR(VLOOKUP(A77, STOCKS!A:W, 20, FALSE), "")) -> 17.44 | V77: =IF(ISBLANK(A77), "", IFERROR(VLOOKUP(A77, STOCKS!A:W, 21, FALSE), "")) -> 46132 | W77: =IF(ISBLANK(A77), "", IFERROR(VLOOKUP(A77, STOCKS!A:W, 22, FALSE), ""))
A78: 4536 | B78: =IF(ISBLANK(A78), "", IFERROR(VLOOKUP(A78, STOCKS!A:W, 2, FALSE), "")) -> 拓凱 | C78: =IF(ISBLANK(A78), "", IFERROR(VLOOKUP(A78, STOCKS!A:W, 3, FALSE), "")) -> 運動休閒 | D78: =IF(ISBLANK(A78), "", IFERROR(VLOOKUP(A78, category!A:C, 3, FALSE), "")) -> 航太 | E78: =IF(ISBLANK(A78), "", IFERROR(VLOOKUP(A78, STOCKS!A:W, 4, FALSE), "")) -> 157 | F78: =IF(ISBLANK(A78), "", IFERROR(VLOOKUP(A78, STOCKS!A:W, 5, FALSE), "")) -> 0.5 | G78: =IF(ISBLANK(A78), "", IFERROR(VLOOKUP(A78, STOCKS!A:W, 6, FALSE), "")) -> 0.32 | H78: =IF(ISBLANK(A78), "", IFERROR(VLOOKUP(A78, STOCKS!A:W, 7, FALSE), "")) -> '+++++ | I78: =IF(ISBLANK(A78), "", IFERROR(VLOOKUP(A78, STOCKS!A:W, 8, FALSE), "")) -> 3.58 | J78: =IF(ISBLANK(A78), "", IFERROR(VLOOKUP(A78, STOCKS!A:W, 9, FALSE), "")) -> 0 | K78: =IF(ISBLANK(A78), "", IFERROR(VLOOKUP(A78, STOCKS!A:W, 10, FALSE), "")) -> 171 | L78: =IF(ISBLANK(A78), "", IFERROR(VLOOKUP(A78, STOCKS!A:W, 11, FALSE), "")) -> 0.19 | M78: =IF(ISBLANK(A78), "", IFERROR(VLOOKUP(A78, STOCKS!A:W, 12, FALSE), "")) -> 155.6 | N78: =IF(ISBLANK(A78), "", IFERROR(VLOOKUP(A78, STOCKS!A:W, 13, FALSE), "")) -> 153.05 | O78: =IF(ISBLANK(A78), "", IFERROR(VLOOKUP(A78, STOCKS!A:W, 14, FALSE), "")) -> 151.57 | P78: =IF(ISBLANK(A78), "", IFERROR(VLOOKUP(A78, STOCKS!A:W, 15, FALSE), "")) -> -11 | Q78: =IF(ISBLANK(A78), "", IFERROR(VLOOKUP(A78, STOCKS!A:W, 16, FALSE), "")) -> '+++-- | R78: =IF(ISBLANK(A78), "", IFERROR(VLOOKUP(A78, STOCKS!A:W, 17, FALSE), "")) -> -1 | S78: =IF(ISBLANK(A78), "", IFERROR(VLOOKUP(A78, STOCKS!A:W, 18, FALSE), "")) -> 0 | T78: =IF(ISBLANK(A78), "", IFERROR(VLOOKUP(A78, STOCKS!A:W, 19, FALSE), "")) -> 13 | U78: =IF(ISBLANK(A78), "", IFERROR(VLOOKUP(A78, STOCKS!A:W, 20, FALSE), "")) -> 7.6 | V78: =IF(ISBLANK(A78), "", IFERROR(VLOOKUP(A78, STOCKS!A:W, 21, FALSE), "")) -> 46132 | W78: =IF(ISBLANK(A78), "", IFERROR(VLOOKUP(A78, STOCKS!A:W, 22, FALSE), ""))
A79: 1513 | B79: =IF(ISBLANK(A79), "", IFERROR(VLOOKUP(A79, STOCKS!A:W, 2, FALSE), "")) -> 中興電 | C79: =IF(ISBLANK(A79), "", IFERROR(VLOOKUP(A79, STOCKS!A:W, 3, FALSE), "")) -> 電機機械 | D79: =IF(ISBLANK(A79), "", IFERROR(VLOOKUP(A79, category!A:C, 3, FALSE), "")) -> 航太 | E79: =IF(ISBLANK(A79), "", IFERROR(VLOOKUP(A79, STOCKS!A:W, 4, FALSE), "")) -> 153.5 | F79: =IF(ISBLANK(A79), "", IFERROR(VLOOKUP(A79, STOCKS!A:W, 5, FALSE), "")) -> 0.5 | G79: =IF(ISBLANK(A79), "", IFERROR(VLOOKUP(A79, STOCKS!A:W, 6, FALSE), "")) -> 0.33 | H79: =IF(ISBLANK(A79), "", IFERROR(VLOOKUP(A79, STOCKS!A:W, 7, FALSE), "")) -> '--+-+ | I79: =IF(ISBLANK(A79), "", IFERROR(VLOOKUP(A79, STOCKS!A:W, 8, FALSE), "")) -> 1.37 | J79: =IF(ISBLANK(A79), "", IFERROR(VLOOKUP(A79, STOCKS!A:W, 9, FALSE), "")) -> 0 | K79: =IF(ISBLANK(A79), "", IFERROR(VLOOKUP(A79, STOCKS!A:W, 10, FALSE), "")) -> 7113 | L79: =IF(ISBLANK(A79), "", IFERROR(VLOOKUP(A79, STOCKS!A:W, 11, FALSE), "")) -> 1.41 | M79: =IF(ISBLANK(A79), "", IFERROR(VLOOKUP(A79, STOCKS!A:W, 12, FALSE), "")) -> 152.7 | N79: =IF(ISBLANK(A79), "", IFERROR(VLOOKUP(A79, STOCKS!A:W, 13, FALSE), "")) -> 150.8 | O79: =IF(ISBLANK(A79), "", IFERROR(VLOOKUP(A79, STOCKS!A:W, 14, FALSE), "")) -> 151.05 | P79: =IF(ISBLANK(A79), "", IFERROR(VLOOKUP(A79, STOCKS!A:W, 15, FALSE), "")) -> -1224 | Q79: =IF(ISBLANK(A79), "", IFERROR(VLOOKUP(A79, STOCKS!A:W, 16, FALSE), "")) -> '--+-- | R79: =IF(ISBLANK(A79), "", IFERROR(VLOOKUP(A79, STOCKS!A:W, 17, FALSE), "")) -> 128 | S79: =IF(ISBLANK(A79), "", IFERROR(VLOOKUP(A79, STOCKS!A:W, 18, FALSE), "")) -> -2 | T79: =IF(ISBLANK(A79), "", IFERROR(VLOOKUP(A79, STOCKS!A:W, 19, FALSE), "")) -> 1932 | U79: =IF(ISBLANK(A79), "", IFERROR(VLOOKUP(A79, STOCKS!A:W, 20, FALSE), "")) -> 27.16 | V79: =IF(ISBLANK(A79), "", IFERROR(VLOOKUP(A79, STOCKS!A:W, 21, FALSE), "")) -> 46132 | W79: =IF(ISBLANK(A79), "", IFERROR(VLOOKUP(A79, STOCKS!A:W, 22, FALSE), ""))
A80: 1583 | B80: =IF(ISBLANK(A80), "", IFERROR(VLOOKUP(A80, STOCKS!A:W, 2, FALSE), "")) -> 程泰 | C80: =IF(ISBLANK(A80), "", IFERROR(VLOOKUP(A80, STOCKS!A:W, 3, FALSE), "")) -> 電機機械 | D80: =IF(ISBLANK(A80), "", IFERROR(VLOOKUP(A80, category!A:C, 3, FALSE), "")) -> 航太 | E80: =IF(ISBLANK(A80), "", IFERROR(VLOOKUP(A80, STOCKS!A:W, 4, FALSE), "")) -> 48.3 | F80: =IF(ISBLANK(A80), "", IFERROR(VLOOKUP(A80, STOCKS!A:W, 5, FALSE), "")) -> 0.1 | G80: =IF(ISBLANK(A80), "", IFERROR(VLOOKUP(A80, STOCKS!A:W, 6, FALSE), "")) -> 0.21 | H80: =IF(ISBLANK(A80), "", IFERROR(VLOOKUP(A80, STOCKS!A:W, 7, FALSE), "")) -> '+++++ | I80: =IF(ISBLANK(A80), "", IFERROR(VLOOKUP(A80, STOCKS!A:W, 8, FALSE), "")) -> 8.52 | J80: =IF(ISBLANK(A80), "", IFERROR(VLOOKUP(A80, STOCKS!A:W, 9, FALSE), "")) -> 0 | K80: =IF(ISBLANK(A80), "", IFERROR(VLOOKUP(A80, STOCKS!A:W, 10, FALSE), "")) -> 32 | L80: =IF(ISBLANK(A80), "", IFERROR(VLOOKUP(A80, STOCKS!A:W, 11, FALSE), "")) -> 0.03 | M80: =IF(ISBLANK(A80), "", IFERROR(VLOOKUP(A80, STOCKS!A:W, 12, FALSE), "")) -> 47.22 | N80: =IF(ISBLANK(A80), "", IFERROR(VLOOKUP(A80, STOCKS!A:W, 13, FALSE), "")) -> 45.69 | O80: =IF(ISBLANK(A80), "", IFERROR(VLOOKUP(A80, STOCKS!A:W, 14, FALSE), "")) -> 44.97 | P80: =IF(ISBLANK(A80), "", IFERROR(VLOOKUP(A80, STOCKS!A:W, 15, FALSE), "")) -> 8 | Q80: =IF(ISBLANK(A80), "", IFERROR(VLOOKUP(A80, STOCKS!A:W, 16, FALSE), "")) -> '+++++ | R80: =IF(ISBLANK(A80), "", IFERROR(VLOOKUP(A80, STOCKS!A:W, 17, FALSE), "")) -> 0 | S80: =IF(ISBLANK(A80), "", IFERROR(VLOOKUP(A80, STOCKS!A:W, 18, FALSE), "")) -> 0 | T80: =IF(ISBLANK(A80), "", IFERROR(VLOOKUP(A80, STOCKS!A:W, 19, FALSE), "")) -> 6 | U80: =IF(ISBLANK(A80), "", IFERROR(VLOOKUP(A80, STOCKS!A:W, 20, FALSE), "")) -> 18.75 | V80: =IF(ISBLANK(A80), "", IFERROR(VLOOKUP(A80, STOCKS!A:W, 21, FALSE), "")) -> 46132 | W80: =IF(ISBLANK(A80), "", IFERROR(VLOOKUP(A80, STOCKS!A:W, 22, FALSE), ""))
... A85: 7402 | B85: =IF(ISBLANK(A85), "", IFERROR(VLOOKUP(A85, STOCKS!A:W, 2, FALSE), "")) -> 邑錡 | C85: =IF(ISBLANK(A85), "", IFERROR(VLOOKUP(A85, STOCKS!A:W, 3, FALSE), "")) -> 光電業 | D85: =IF(ISBLANK(A85), "", IFERROR(VLOOKUP(A85, category!A:C, 3, FALSE), "")) -> 軍工/航太 | E85: =IF(ISBLANK(A85), "", IFERROR(VLOOKUP(A85, STOCKS!A:W, 4, FALSE), "")) -> 133.5 | F85: =IF(ISBLANK(A85), "", IFERROR(VLOOKUP(A85, STOCKS!A:W, 5, FALSE), "")) -> 8 | G85: =IF(ISBLANK(A85), "", IFERROR(VLOOKUP(A85, STOCKS!A:W, 6, FALSE), "")) -> 6.37 | H85: =IF(ISBLANK(A85), "", IFERROR(VLOOKUP(A85, STOCKS!A:W, 7, FALSE), "")) -> '+++++ | I85: =IF(ISBLANK(A85), "", IFERROR(VLOOKUP(A85, STOCKS!A:W, 8, FALSE), "")) -> 10.91 | J85: =IF(ISBLANK(A85), "", IFERROR(VLOOKUP(A85, STOCKS!A:W, 9, FALSE), "")) -> 0 | K85: =IF(ISBLANK(A85), "", IFERROR(VLOOKUP(A85, STOCKS!A:W, 10, FALSE), "")) -> 1906 | L85: =IF(ISBLANK(A85), "", IFERROR(VLOOKUP(A85, STOCKS!A:W, 11, FALSE), "")) -> 5.4 | M85: =IF(ISBLANK(A85), "", IFERROR(VLOOKUP(A85, STOCKS!A:W, 12, FALSE), "")) -> 125.1 | N85: =IF(ISBLANK(A85), "", IFERROR(VLOOKUP(A85, STOCKS!A:W, 13, FALSE), "")) -> 121 | O85: =IF(ISBLANK(A85), "", IFERROR(VLOOKUP(A85, STOCKS!A:W, 14, FALSE), "")) -> 120.97 | P85: =IF(ISBLANK(A85), "", IFERROR(VLOOKUP(A85, STOCKS!A:W, 15, FALSE), "")) -> 82 | Q85: =IF(ISBLANK(A85), "", IFERROR(VLOOKUP(A85, STOCKS!A:W, 16, FALSE), "")) -> '+---+ | R85: =IF(ISBLANK(A85), "", IFERROR(VLOOKUP(A85, STOCKS!A:W, 17, FALSE), "")) -> 0 | S85: =IF(ISBLANK(A85), "", IFERROR(VLOOKUP(A85, STOCKS!A:W, 18, FALSE), "")) -> -10 | T85: =IF(ISBLANK(A85), "", IFERROR(VLOOKUP(A85, STOCKS!A:W, 19, FALSE), "")) -> 830 | U85: =IF(ISBLANK(A85), "", IFERROR(VLOOKUP(A85, STOCKS!A:W, 20, FALSE), "")) -> 43.55 | V85: =IF(ISBLANK(A85), "", IFERROR(VLOOKUP(A85, STOCKS!A:W, 21, FALSE), "")) -> 46132 | W85: =IF(ISBLANK(A85), "", IFERROR(VLOOKUP(A85, STOCKS!A:W, 22, FALSE), ""))
A86: 題材-資訊服務
A87: 2390 | B87: =IF(ISBLANK(A87), "", IFERROR(VLOOKUP(A87, STOCKS!A:W, 2, FALSE), "")) -> 云辰 | C87: =IF(ISBLANK(A87), "", IFERROR(VLOOKUP(A87, STOCKS!A:W, 3, FALSE), "")) -> 其他電子業 | D87: =IF(ISBLANK(A87), "", IFERROR(VLOOKUP(A87, category!A:C, 3, FALSE), "")) -> 資訊服務 | E87: =IF(ISBLANK(A87), "", IFERROR(VLOOKUP(A87, STOCKS!A:W, 4, FALSE), "")) -> 10.2 | F87: =IF(ISBLANK(A87), "", IFERROR(VLOOKUP(A87, STOCKS!A:W, 5, FALSE), "")) -> 0.1 | G87: =IF(ISBLANK(A87), "", IFERROR(VLOOKUP(A87, STOCKS!A:W, 6, FALSE), "")) -> 0.99 | H87: =IF(ISBLANK(A87), "", IFERROR(VLOOKUP(A87, STOCKS!A:W, 7, FALSE), "")) -> '--+-+ | I87: =IF(ISBLANK(A87), "", IFERROR(VLOOKUP(A87, STOCKS!A:W, 8, FALSE), "")) -> 0.5 | J87: =IF(ISBLANK(A87), "", IFERROR(VLOOKUP(A87, STOCKS!A:W, 9, FALSE), "")) -> 0 | K87: =IF(ISBLANK(A87), "", IFERROR(VLOOKUP(A87, STOCKS!A:W, 10, FALSE), "")) -> 523 | L87: =IF(ISBLANK(A87), "", IFERROR(VLOOKUP(A87, STOCKS!A:W, 11, FALSE), "")) -> 0.27 | M87: =IF(ISBLANK(A87), "", IFERROR(VLOOKUP(A87, STOCKS!A:W, 12, FALSE), "")) -> 10.11 | N87: =IF(ISBLANK(A87), "", IFERROR(VLOOKUP(A87, STOCKS!A:W, 13, FALSE), "")) -> 10.13 | O87: =IF(ISBLANK(A87), "", IFERROR(VLOOKUP(A87, STOCKS!A:W, 14, FALSE), "")) -> 10.26 | P87: =IF(ISBLANK(A87), "", IFERROR(VLOOKUP(A87, STOCKS!A:W, 15, FALSE), "")) -> 119 | Q87: =IF(ISBLANK(A87), "", IFERROR(VLOOKUP(A87, STOCKS!A:W, 16, FALSE), "")) -> '--+++ | R87: =IF(ISBLANK(A87), "", IFERROR(VLOOKUP(A87, STOCKS!A:W, 17, FALSE), "")) -> 0 | S87: =IF(ISBLANK(A87), "", IFERROR(VLOOKUP(A87, STOCKS!A:W, 18, FALSE), "")) -> 0 | T87: =IF(ISBLANK(A87), "", IFERROR(VLOOKUP(A87, STOCKS!A:W, 19, FALSE), "")) -> 45 | U87: =IF(ISBLANK(A87), "", IFERROR(VLOOKUP(A87, STOCKS!A:W, 20, FALSE), "")) -> 8.6 | V87: =IF(ISBLANK(A87), "", IFERROR(VLOOKUP(A87, STOCKS!A:W, 21, FALSE), "")) -> 46132 | W87: =IF(ISBLANK(A87), "", IFERROR(VLOOKUP(A87, STOCKS!A:W, 22, FALSE), ""))
A88: 2427 | B88: =IF(ISBLANK(A88), "", IFERROR(VLOOKUP(A88, STOCKS!A:W, 2, FALSE), "")) -> 三商電 | C88: =IF(ISBLANK(A88), "", IFERROR(VLOOKUP(A88, STOCKS!A:W, 3, FALSE), "")) -> 資訊服務業 | D88: =IF(ISBLANK(A88), "", IFERROR(VLOOKUP(A88, category!A:C, 3, FALSE), "")) -> 資訊服務 | E88: =IF(ISBLANK(A88), "", IFERROR(VLOOKUP(A88, STOCKS!A:W, 4, FALSE), "")) -> 22.05 | F88: =IF(ISBLANK(A88), "", IFERROR(VLOOKUP(A88, STOCKS!A:W, 5, FALSE), "")) -> -0.2 | G88: =IF(ISBLANK(A88), "", IFERROR(VLOOKUP(A88, STOCKS!A:W, 6, FALSE), "")) -> -0.9 | H88: =IF(ISBLANK(A88), "", IFERROR(VLOOKUP(A88, STOCKS!A:W, 7, FALSE), "")) -> '+-+-- | I88: =IF(ISBLANK(A88), "", IFERROR(VLOOKUP(A88, STOCKS!A:W, 8, FALSE), "")) -> -0.66 | J88: =IF(ISBLANK(A88), "", IFERROR(VLOOKUP(A88, STOCKS!A:W, 9, FALSE), "")) -> 0 | K88: =IF(ISBLANK(A88), "", IFERROR(VLOOKUP(A88, STOCKS!A:W, 10, FALSE), "")) -> 498 | L88: =IF(ISBLANK(A88), "", IFERROR(VLOOKUP(A88, STOCKS!A:W, 11, FALSE), "")) -> 0.25 | M88: =IF(ISBLANK(A88), "", IFERROR(VLOOKUP(A88, STOCKS!A:W, 12, FALSE), "")) -> 22.25 | N88: =IF(ISBLANK(A88), "", IFERROR(VLOOKUP(A88, STOCKS!A:W, 13, FALSE), "")) -> 22.54 | O88: =IF(ISBLANK(A88), "", IFERROR(VLOOKUP(A88, STOCKS!A:W, 14, FALSE), "")) -> 22.95 | P88: =IF(ISBLANK(A88), "", IFERROR(VLOOKUP(A88, STOCKS!A:W, 15, FALSE), "")) -> -39 | Q88: =IF(ISBLANK(A88), "", IFERROR(VLOOKUP(A88, STOCKS!A:W, 16, FALSE), "")) -> '+++-- | R88: =IF(ISBLANK(A88), "", IFERROR(VLOOKUP(A88, STOCKS!A:W, 17, FALSE), "")) -> 0 | S88: =IF(ISBLANK(A88), "", IFERROR(VLOOKUP(A88, STOCKS!A:W, 18, FALSE), "")) -> 0 | T88: =IF(ISBLANK(A88), "", IFERROR(VLOOKUP(A88, STOCKS!A:W, 19, FALSE), "")) -> 56 | U88: =IF(ISBLANK(A88), "", IFERROR(VLOOKUP(A88, STOCKS!A:W, 20, FALSE), "")) -> 11.24 | V88: =IF(ISBLANK(A88), "", IFERROR(VLOOKUP(A88, STOCKS!A:W, 21, FALSE), "")) -> 46132 | W88: =IF(ISBLANK(A88), "", IFERROR(VLOOKUP(A88, STOCKS!A:W, 22, FALSE), ""))
A89: 2453 | B89: =IF(ISBLANK(A89), "", IFERROR(VLOOKUP(A89, STOCKS!A:W, 2, FALSE), "")) -> 凌群 | C89: =IF(ISBLANK(A89), "", IFERROR(VLOOKUP(A89, STOCKS!A:W, 3, FALSE), "")) -> 資訊服務業 | D89: =IF(ISBLANK(A89), "", IFERROR(VLOOKUP(A89, category!A:C, 3, FALSE), "")) -> 資訊服務 | E89: =IF(ISBLANK(A89), "", IFERROR(VLOOKUP(A89, STOCKS!A:W, 4, FALSE), "")) -> 54.6 | F89: =IF(ISBLANK(A89), "", IFERROR(VLOOKUP(A89, STOCKS!A:W, 5, FALSE), "")) -> -0.9 | G89: =IF(ISBLANK(A89), "", IFERROR(VLOOKUP(A89, STOCKS!A:W, 6, FALSE), "")) -> -1.62 | H89: =IF(ISBLANK(A89), "", IFERROR(VLOOKUP(A89, STOCKS!A:W, 7, FALSE), "")) -> '+-+-- | I89: =IF(ISBLANK(A89), "", IFERROR(VLOOKUP(A89, STOCKS!A:W, 8, FALSE), "")) -> 1.56 | J89: =IF(ISBLANK(A89), "", IFERROR(VLOOKUP(A89, STOCKS!A:W, 9, FALSE), "")) -> 0 | K89: =IF(ISBLANK(A89), "", IFERROR(VLOOKUP(A89, STOCKS!A:W, 10, FALSE), "")) -> 427 | L89: =IF(ISBLANK(A89), "", IFERROR(VLOOKUP(A89, STOCKS!A:W, 11, FALSE), "")) -> 0.43 | M89: =IF(ISBLANK(A89), "", IFERROR(VLOOKUP(A89, STOCKS!A:W, 12, FALSE), "")) -> 54.88 | N89: =IF(ISBLANK(A89), "", IFERROR(VLOOKUP(A89, STOCKS!A:W, 13, FALSE), "")) -> 54 | O89: =IF(ISBLANK(A89), "", IFERROR(VLOOKUP(A89, STOCKS!A:W, 14, FALSE), "")) -> 53.59 | P89: =IF(ISBLANK(A89), "", IFERROR(VLOOKUP(A89, STOCKS!A:W, 15, FALSE), "")) -> 125 | Q89: =IF(ISBLANK(A89), "", IFERROR(VLOOKUP(A89, STOCKS!A:W, 16, FALSE), "")) -> '-++-+ | R89: =IF(ISBLANK(A89), "", IFERROR(VLOOKUP(A89, STOCKS!A:W, 17, FALSE), "")) -> 0 | S89: =IF(ISBLANK(A89), "", IFERROR(VLOOKUP(A89, STOCKS!A:W, 18, FALSE), "")) -> 4 | T89: =IF(ISBLANK(A89), "", IFERROR(VLOOKUP(A89, STOCKS!A:W, 19, FALSE), "")) -> 56 | U89: =IF(ISBLANK(A89), "", IFERROR(VLOOKUP(A89, STOCKS!A:W, 20, FALSE), "")) -> 13.11 | V89: =IF(ISBLANK(A89), "", IFERROR(VLOOKUP(A89, STOCKS!A:W, 21, FALSE), "")) -> 46132 | W89: =IF(ISBLANK(A89), "", IFERROR(VLOOKUP(A89, STOCKS!A:W, 22, FALSE), ""))
A90: 2468 | B90: =IF(ISBLANK(A90), "", IFERROR(VLOOKUP(A90, STOCKS!A:W, 2, FALSE), "")) -> 華經 | C90: =IF(ISBLANK(A90), "", IFERROR(VLOOKUP(A90, STOCKS!A:W, 3, FALSE), "")) -> 資訊服務業 | D90: =IF(ISBLANK(A90), "", IFERROR(VLOOKUP(A90, category!A:C, 3, FALSE), "")) -> 資訊服務 | E90: =IF(ISBLANK(A90), "", IFERROR(VLOOKUP(A90, STOCKS!A:W, 4, FALSE), "")) -> 34.6 | F90: =IF(ISBLANK(A90), "", IFERROR(VLOOKUP(A90, STOCKS!A:W, 5, FALSE), "")) -> -0.3 | G90: =IF(ISBLANK(A90), "", IFERROR(VLOOKUP(A90, STOCKS!A:W, 6, FALSE), "")) -> -0.86 | H90: =IF(ISBLANK(A90), "", IFERROR(VLOOKUP(A90, STOCKS!A:W, 7, FALSE), "")) -> '+-+-- | I90: =IF(ISBLANK(A90), "", IFERROR(VLOOKUP(A90, STOCKS!A:W, 8, FALSE), "")) -> 1.81 | J90: =IF(ISBLANK(A90), "", IFERROR(VLOOKUP(A90, STOCKS!A:W, 9, FALSE), "")) -> 0 | K90: =IF(ISBLANK(A90), "", IFERROR(VLOOKUP(A90, STOCKS!A:W, 10, FALSE), "")) -> 252 | L90: =IF(ISBLANK(A90), "", IFERROR(VLOOKUP(A90, STOCKS!A:W, 11, FALSE), "")) -> 0.36 | M90: =IF(ISBLANK(A90), "", IFERROR(VLOOKUP(A90, STOCKS!A:W, 12, FALSE), "")) -> 34.9 | N90: =IF(ISBLANK(A90), "", IFERROR(VLOOKUP(A90, STOCKS!A:W, 13, FALSE), "")) -> 34.3 | O90: =IF(ISBLANK(A90), "", IFERROR(VLOOKUP(A90, STOCKS!A:W, 14, FALSE), "")) -> 35.32 | P90: =IF(ISBLANK(A90), "", IFERROR(VLOOKUP(A90, STOCKS!A:W, 15, FALSE), "")) -> 30 | Q90: =IF(ISBLANK(A90), "", IFERROR(VLOOKUP(A90, STOCKS!A:W, 16, FALSE), "")) -> '--+++ | R90: =IF(ISBLANK(A90), "", IFERROR(VLOOKUP(A90, STOCKS!A:W, 17, FALSE), "")) -> 0 | S90: =IF(ISBLANK(A90), "", IFERROR(VLOOKUP(A90, STOCKS!A:W, 18, FALSE), "")) -> 0 | T90: =IF(ISBLANK(A90), "", IFERROR(VLOOKUP(A90, STOCKS!A:W, 19, FALSE), "")) -> 39 | U90: =IF(ISBLANK(A90), "", IFERROR(VLOOKUP(A90, STOCKS!A:W, 20, FALSE), "")) -> 15.48 | V90: =IF(ISBLANK(A90), "", IFERROR(VLOOKUP(A90, STOCKS!A:W, 21, FALSE), "")) -> 46132 | W90: =IF(ISBLANK(A90), "", IFERROR(VLOOKUP(A90, STOCKS!A:W, 22, FALSE), ""))
A91: 2471 | B91: =IF(ISBLANK(A91), "", IFERROR(VLOOKUP(A91, STOCKS!A:W, 2, FALSE), "")) -> 資通 | C91: =IF(ISBLANK(A91), "", IFERROR(VLOOKUP(A91, STOCKS!A:W, 3, FALSE), "")) -> 資訊服務業 | D91: =IF(ISBLANK(A91), "", IFERROR(VLOOKUP(A91, category!A:C, 3, FALSE), "")) -> 資訊服務 | E91: =IF(ISBLANK(A91), "", IFERROR(VLOOKUP(A91, STOCKS!A:W, 4, FALSE), "")) -> 53.2 | F91: =IF(ISBLANK(A91), "", IFERROR(VLOOKUP(A91, STOCKS!A:W, 5, FALSE), "")) -> -0.8 | G91: =IF(ISBLANK(A91), "", IFERROR(VLOOKUP(A91, STOCKS!A:W, 6, FALSE), "")) -> -1.48 | H91: =IF(ISBLANK(A91), "", IFERROR(VLOOKUP(A91, STOCKS!A:W, 7, FALSE), "")) -> '+++-- | I91: =IF(ISBLANK(A91), "", IFERROR(VLOOKUP(A91, STOCKS!A:W, 8, FALSE), "")) -> 4 | J91: =IF(ISBLANK(A91), "", IFERROR(VLOOKUP(A91, STOCKS!A:W, 9, FALSE), "")) -> 0 | K91: =IF(ISBLANK(A91), "", IFERROR(VLOOKUP(A91, STOCKS!A:W, 10, FALSE), "")) -> 230 | L91: =IF(ISBLANK(A91), "", IFERROR(VLOOKUP(A91, STOCKS!A:W, 11, FALSE), "")) -> 0.49 | M91: =IF(ISBLANK(A91), "", IFERROR(VLOOKUP(A91, STOCKS!A:W, 12, FALSE), "")) -> 53.12 | N91: =IF(ISBLANK(A91), "", IFERROR(VLOOKUP(A91, STOCKS!A:W, 13, FALSE), "")) -> 52.43 | O91: =IF(ISBLANK(A91), "", IFERROR(VLOOKUP(A91, STOCKS!A:W, 14, FALSE), "")) -> 52.1 | P91: =IF(ISBLANK(A91), "", IFERROR(VLOOKUP(A91, STOCKS!A:W, 15, FALSE), "")) -> -52 | Q91: =IF(ISBLANK(A91), "", IFERROR(VLOOKUP(A91, STOCKS!A:W, 16, FALSE), "")) -> '--+-- | R91: =IF(ISBLANK(A91), "", IFERROR(VLOOKUP(A91, STOCKS!A:W, 17, FALSE), "")) -> 0 | S91: =IF(ISBLANK(A91), "", IFERROR(VLOOKUP(A91, STOCKS!A:W, 18, FALSE), "")) -> -11 | T91: =IF(ISBLANK(A91), "", IFERROR(VLOOKUP(A91, STOCKS!A:W, 19, FALSE), "")) -> 15 | U91: =IF(ISBLANK(A91), "", IFERROR(VLOOKUP(A91, STOCKS!A:W, 20, FALSE), "")) -> 6.52 | V91: =IF(ISBLANK(A91), "", IFERROR(VLOOKUP(A91, STOCKS!A:W, 21, FALSE), "")) -> 46132 | W91: =IF(ISBLANK(A91), "", IFERROR(VLOOKUP(A91, STOCKS!A:W, 22, FALSE), ""))
A92: 2480 | B92: =IF(ISBLANK(A92), "", IFERROR(VLOOKUP(A92, STOCKS!A:W, 2, FALSE), "")) -> 敦陽科 | C92: =IF(ISBLANK(A92), "", IFERROR(VLOOKUP(A92, STOCKS!A:W, 3, FALSE), "")) -> 資訊服務業 | D92: =IF(ISBLANK(A92), "", IFERROR(VLOOKUP(A92, category!A:C, 3, FALSE), "")) -> 資訊服務 | E92: =IF(ISBLANK(A92), "", IFERROR(VLOOKUP(A92, STOCKS!A:W, 4, FALSE), "")) -> 140 | F92: =IF(ISBLANK(A92), "", IFERROR(VLOOKUP(A92, STOCKS!A:W, 5, FALSE), "")) -> -0.5 | G92: =IF(ISBLANK(A92), "", IFERROR(VLOOKUP(A92, STOCKS!A:W, 6, FALSE), "")) -> -0.36 | H92: =IF(ISBLANK(A92), "", IFERROR(VLOOKUP(A92, STOCKS!A:W, 7, FALSE), "")) -> '+-++- | I92: =IF(ISBLANK(A92), "", IFERROR(VLOOKUP(A92, STOCKS!A:W, 8, FALSE), "")) -> 1.08 | J92: =IF(ISBLANK(A92), "", IFERROR(VLOOKUP(A92, STOCKS!A:W, 9, FALSE), "")) -> 0 | K92: =IF(ISBLANK(A92), "", IFERROR(VLOOKUP(A92, STOCKS!A:W, 10, FALSE), "")) -> 416 | L92: =IF(ISBLANK(A92), "", IFERROR(VLOOKUP(A92, STOCKS!A:W, 11, FALSE), "")) -> 0.39 | M92: =IF(ISBLANK(A92), "", IFERROR(VLOOKUP(A92, STOCKS!A:W, 12, FALSE), "")) -> 139.7 | N92: =IF(ISBLANK(A92), "", IFERROR(VLOOKUP(A92, STOCKS!A:W, 13, FALSE), "")) -> 139.75 | O92: =IF(ISBLANK(A92), "", IFERROR(VLOOKUP(A92, STOCKS!A:W, 14, FALSE), "")) -> 139.88 | P92: =IF(ISBLANK(A92), "", IFERROR(VLOOKUP(A92, STOCKS!A:W, 15, FALSE), "")) -> -37 | Q92: =IF(ISBLANK(A92), "", IFERROR(VLOOKUP(A92, STOCKS!A:W, 16, FALSE), "")) -> '--++- | R92: =IF(ISBLANK(A92), "", IFERROR(VLOOKUP(A92, STOCKS!A:W, 17, FALSE), "")) -> -3 | S92: =IF(ISBLANK(A92), "", IFERROR(VLOOKUP(A92, STOCKS!A:W, 18, FALSE), "")) -> 0 | T92: =IF(ISBLANK(A92), "", IFERROR(VLOOKUP(A92, STOCKS!A:W, 19, FALSE), "")) -> 51 | U92: =IF(ISBLANK(A92), "", IFERROR(VLOOKUP(A92, STOCKS!A:W, 20, FALSE), "")) -> 12.26 | V92: =IF(ISBLANK(A92), "", IFERROR(VLOOKUP(A92, STOCKS!A:W, 21, FALSE), "")) -> 46132 | W92: =IF(ISBLANK(A92), "", IFERROR(VLOOKUP(A92, STOCKS!A:W, 22, FALSE), ""))
A93: 3029 | B93: =IF(ISBLANK(A93), "", IFERROR(VLOOKUP(A93, STOCKS!A:W, 2, FALSE), "")) -> 零壹 | C93: =IF(ISBLANK(A93), "", IFERROR(VLOOKUP(A93, STOCKS!A:W, 3, FALSE), "")) -> 資訊服務業 | D93: =IF(ISBLANK(A93), "", IFERROR(VLOOKUP(A93, category!A:C, 3, FALSE), "")) -> 資訊服務 | E93: =IF(ISBLANK(A93), "", IFERROR(VLOOKUP(A93, STOCKS!A:W, 4, FALSE), "")) -> 96 | F93: =IF(ISBLANK(A93), "", IFERROR(VLOOKUP(A93, STOCKS!A:W, 5, FALSE), "")) -> -1.3 | G93: =IF(ISBLANK(A93), "", IFERROR(VLOOKUP(A93, STOCKS!A:W, 6, FALSE), "")) -> -1.34 | H93: =IF(ISBLANK(A93), "", IFERROR(VLOOKUP(A93, STOCKS!A:W, 7, FALSE), "")) -> '+-+-- | I93: =IF(ISBLANK(A93), "", IFERROR(VLOOKUP(A93, STOCKS!A:W, 8, FALSE), "")) -> -0.81 | J93: =IF(ISBLANK(A93), "", IFERROR(VLOOKUP(A93, STOCKS!A:W, 9, FALSE), "")) -> 0 | K93: =IF(ISBLANK(A93), "", IFERROR(VLOOKUP(A93, STOCKS!A:W, 10, FALSE), "")) -> 1201 | L93: =IF(ISBLANK(A93), "", IFERROR(VLOOKUP(A93, STOCKS!A:W, 11, FALSE), "")) -> 0.72 | M93: =IF(ISBLANK(A93), "", IFERROR(VLOOKUP(A93, STOCKS!A:W, 12, FALSE), "")) -> 97.24 | N93: =IF(ISBLANK(A93), "", IFERROR(VLOOKUP(A93, STOCKS!A:W, 13, FALSE), "")) -> 97.07 | O93: =IF(ISBLANK(A93), "", IFERROR(VLOOKUP(A93, STOCKS!A:W, 14, FALSE), "")) -> 97.41 | P93: =IF(ISBLANK(A93), "", IFERROR(VLOOKUP(A93, STOCKS!A:W, 15, FALSE), "")) -> -279 | Q93: =IF(ISBLANK(A93), "", IFERROR(VLOOKUP(A93, STOCKS!A:W, 16, FALSE), "")) -> '+-+-- | R93: =IF(ISBLANK(A93), "", IFERROR(VLOOKUP(A93, STOCKS!A:W, 17, FALSE), "")) -> -2 | S93: =IF(ISBLANK(A93), "", IFERROR(VLOOKUP(A93, STOCKS!A:W, 18, FALSE), "")) -> 4 | T93: =IF(ISBLANK(A93), "", IFERROR(VLOOKUP(A93, STOCKS!A:W, 19, FALSE), "")) -> 283 | U93: =IF(ISBLANK(A93), "", IFERROR(VLOOKUP(A93, STOCKS!A:W, 20, FALSE), "")) -> 23.56 | V93: =IF(ISBLANK(A93), "", IFERROR(VLOOKUP(A93, STOCKS!A:W, 21, FALSE), "")) -> 46132 | W93: =IF(ISBLANK(A93), "", IFERROR(VLOOKUP(A93, STOCKS!A:W, 22, FALSE), ""))
